Workbook
Name FtrArmr: '[1]1-Hull'!$AA$17
Name FtrArmr: '[2]1-Hull'!$AA$17
Name FtrArmr: '1-Hull'!$AA$17
Name HullConfig: #REF!
Name Tech_Level: '[1]Ship Info'!$F$2
Name Tech_Level: '[2]Ship Info'!$F$2
Name Tech_Level: 'Ship Info'!$F$2
Name TL: '[1]Ship Info'!$F$2
Name TL: '[2]Ship Info'!$F$2
Name TL: 'Ship Info'!$F$2
Name Tonnage: '[1]1-Hull'!$B$4
Name Tonnage: '[2]1-Hull'!$B$4
Name Tonnage: '1-Hull'!$B$4

Sheet Instructions
A1: Version 2026, January 22
A3: This is a ship designer for a certain version of a certain D6 RPG game made popular in the 1970's using the current HG stats.
A5: The process has been broken up into several steps, and separated into tabs on the bottom.
A7: It is recommended that you copy the blank to another file, such as the name of the ship or class prior to entering any data, so that you can upgrade or save designs for later.
A9: Start with Ship Info. (Green Tab)
A10: There are now three modes on this tab that will determine how the rest of the sheet works. Ship, Station and Module. I recommend saving a copy of this file as a blank for each mode.
A12: This spreadsheet uses "," to separate 000's and "." to indicate decimals. If you get an #ARG! Error, check your EXCEL settings.
A14: Some ship's systems can be modded. These are optional rules. Clear their use with your game master first.
A16: The Summary, Record Sheet and the SSD automatically fill out based on your choices. These can be printed to a printer or as PDF's for later use.
A17: The SSD has room for 3000 damage boxes. These will scale by a factor of 10 or 100 with the hull points. Hatched boxes indicate the 10% critical threshhold.
A18: There are two sets of counters on the right that allow you to count partial boxes. The boxes and counters will be greyed out until applicable.
A19: The Capital Ship SSD is located after the Cargo Tab. It provides larger print and 10,560 boxes, with a maximum scale of x1000 and partial box counters going to the hundreds. Warning, it is slow.
... A33: Arkathan -October, 2021

Sheet Jank Build Info
A1: CLUSTER TRUCK BUILDER - Material Inventory & Construction
A3: MATERIAL INVENTORY
A4: Material Type | B4: Units Available | C4: Unit Cost (MCr) | D4: Total Value (MCr) | E4: Unit Weight (Tons) | F4: Total Weight
A5: Structural | B5: 0 | C5: 0.01 | D5: =B5*C5 -> 0 | E5: 0.1 | F5: =E5*B5 -> 0
A6: Technical | B6: 0 | C6: 0.025 | D6: =B6*C6 -> 0 | E6: 0.01 | F6: =E6*B6 -> 0
A7: Outfitting | B7: 0 | C7: 0.001 | D7: =B7*C7 -> 0 | E7: 0.1 | F7: =E7*B7 -> 0
A9: COMPONENT CONSTRUCTION
A10: Component Name | B10: Component Type | C10: Tonnage | D10: Current Quality | E10: Target Quality | F10: Structural Req | G10: Technical Req | H10: Outfitting Req | I10: Labor (Shifts) | K10: Crude
K11: Beyond Janky
K12: Janky
K13: Basic
K14: Standard
K15: Improved
A16: LABOR & FACILITY | K16: High Quality
A17: Facility Type | B17: Crew Only | C17: Basic Rig | D17: Full Cradle
A18: Shifts/Ton Formula | B18: 4D+4 | C18: 3D+3 | D18: 2D+2
A19: Shifts Range: (x6 for hours) | B19: (low 8, avg 18, high 28) | C19: (low 6, avg 13.5, high 21) | D19: (low 4, avg 9, high 14)
A21: QUALITY SYSTEM
A22: Quality Level | B22: Performance % | C22: DM Modifier | D22: Materials to Upgrade
A23: Busted | B23: 0 | C23: Non-Functional | D23: 0.1
A24: Crude | B24: 0.15 | C24: -4 | D24: 0.25 | H24: 0.1 | I24: 0.3 | J24: 0.6 | K24: 0.8
A25: Beyond Janky | B25: 0.4 | C25: -3 | D25: 0.5 | H25: 0.11 | I25: 0.31 | J25: 0.61 | K25: 0.81
A26: Janky | B26: 0.65 | C26: -2 | D26: 0.75 | H26: 0.12 | I26: 0.32 | J26: 0.62 | K26: 0.82
A27: Basic | B27: 0.85 | C27: -1 | D27: 1 | H27: 0.13 | I27: 0.33 | J27: 0.63 | K27: 0.83
A28: Standard | B28: 1 | C28: 0 | D28: 1.5 | H28: 0.14 | I28: 0.34 | J28: 0.64 | K28: 0.84
A29: Improved | B29: 1.2 | C29: 1 | D29: 2.5 | H29: 0.15 | I29: 0.35 | J29: 0.65 | K29: 0.85
A30: High-Quality | B30: 1.5 | C30: 2 | H30: 0.16 | I30: 0.36 | J30: 0.66 | K30: 0.86
H31: 0.17 | I31: 0.37 | J31: 0.67 | K31: 0.87
A32: Performance Mode: | B32: Reduce Actual Performance | H32: 0.18 | I32: 0.38 | J32: 0.68 | K32: 0.88
A33: Material Cost Mode: | B33: Average | H33: 0.19 | I33: 0.39 | J33: 0.69 | K33: 0.89
H34: 0.2 | I34: 0.4 | J34: 0.7 | K34: 0.9
I35: 0.41
A36: MATERIAL REQUIREMENTS - STRUCTURAL | I36: 0.42
A37: Component Type | B37: Example | C37: Requirement Construction (Ton) | D37: Requirement Upgrade (Ton) | I37: 0.43
A38: Structural | B38: Hull and Bulkheads | C38: 3D | D38: 1D | I38: 0.44
A39: Utility | B39: Cabins | C39: 3D | D39: 1D | I39: 0.45
A40: Control | B40: Bridge | C40: 1D | D40: D3 | I40: 0.46
A41: Machinery | B41: Power Plant | C41: 8D | D41: 2D | I41: 0.47
A42: Drives | B42: M-Drive | C42: 12D | D42: 4D | I42: 0.48
I43: 0.49
A44: MATERIAL REQUIREMENTS - TECHNICAL | I44: 0.5
A45: Component Type | B45: Example | C45: Requirement Construction (Ton) | D45: Requirement Upgrade (Ton)
A46: Structural | B46: Hull and Bulkheads | C46: 0 | D46: 0
A47: Utility | B47: Cabins | C47: 0 | D47: 0
A48: Control | B48: Bridge | C48: 2D | D48: 1D
A49: Machinery | B49: Power Plant | C49: 4D | D49: 2D
A50: Drives | B50: M-Drive | C50: 12D | D50: 4D
A52: MATERIAL REQUIREMENTS - OUTFITTING
A53: Component Type | B53: Example | C53: Requirement Construction (Ton) | D53: Requirement Upgrade (Ton)
A54: Structural | B54: Hull and Bulkheads | C54: 0 | D54: 0
A55: Utility | B55: Cabins | C55: 5D | D55: 2D
A56: Control | B56: Bridge | C56: 2D | D56: 1D
A57: Machinery | B57: Power Plant | C57: 3D | D57: 1D
A58: Drives | B58: M-Drive | C58: 0 | D58: 0

Sheet Cluster Truck Builder
A1: CLUSTER TRUCK: Salvage & Scrap Ship Construction System
A2: Mongoose Traveller 2e - Estuary Cluster Rules
A4: SECTION 1: MATERIAL INVENTORY & COSTS
A5: Material Type | B5: Units on Hand | C5: Cost per Unit (Cr) | D5: Weight per Unit (tons) | E5: Total Value (Cr)
A6: Structural | B6: 0 | C6: 10000 | D6: 0.1 | E6: =B6*C6 -> 0
A7: Technical | B7: 0 | C7: 25000 | D7: 0.01 | E7: =B7*C7 -> 0
A8: Outfitting | B8: 0 | C8: 1000 | D8: 0.1 | E8: =B8*C8 -> 0
A9: TOTAL INVENTORY VALUE | E9: =SUM(E6:E8) -> 0
A11: SECTION 2: COMPONENT CONSTRUCTION CALCULATOR | M11: Structural | O11: Crude | Q11: Build
A12: Component Type: | B12: Structural | D12: (Dropdown: Structural/Utility/Control/Machinery/Drives) | M12: Utility | O12: Beyond Janky | Q12: Upgrade
A13: Tonnage to Build: | B13: 10 | D13: tons | M13: Control | O13: Janky
A14: Target Quality: | B14: Janky | D14: (Dropdown: Crude/Beyond Janky/Janky/Basic/Standard) | M14: Machinery | O14: Basic
A15: Build or Upgrade | B15: Build | M15: Drives | O15: Standard
O16: Improved
A17: MATERIALS REQUIRED: | B17: Low | C17: Median | D17: High | O17: High Quality
A18: Structural units needed: | B18: =B12*10 -> #VALUE! | C18: =C12*10 -> 0 | D18: =D12*10 -> #VALUE!
A19: Technical units needed: | B19: =B12*5 -> #VALUE! | C19: =C12*5 -> 0 | D19: =D12*5 -> #VALUE!
A20: Outfitting units needed: | B20: =B12*2 -> #VALUE! | C20: =C12*2 -> 0 | D20: =D12*2 -> #VALUE!
A21: Total Material Cost: | B21: =(B18*10000)+(B19*25000)+(B20*1000) -> #VALUE! | C21: =(C18*10000)+(C19*25000)+(C20*1000) -> 0 | D21: =(D18*10000)+(D19*25000)+(D20*1000) -> #VALUE!
A22: Have sufficient materials? | B22: Check inventory above
A24: SECTION 3: LABOR & FACILITY REQUIREMENTS | M24: Crew Only
A25: Construction Facility: | B25: Basic Rig | D25: (Crew-Only/Makeshift Frame/Basic Rig/Full Cradle) | M25: Makeshift Frame
A26: Shifts Required: | B26: =(3*3+3)*10 -> 120 | D26: shifts (based on facility & tonnage) | M26: Basic Rig
A27: Crew Size: | B27: 5 | D27: workers | M27: Full Cradle
A28: Days to Complete: | B28: =B26/(B27*2) -> 12 | D28: days (assumes 2 shifts/day)
A29: Engineer Skill Level: | B29: 2 | D29: DM for quality roll
A31: SECTION 4: QUALITY ROLLER & RESULTS
A32: Roll 2D: | B32: 7 | D32: (Enter your 2D6 roll result)
A33: Quality DM: | B33: =B25 -> Basic Rig | D33: (From Engineer + Facility - TL difference)
A34: Final Result: | B34: =B32+B33 -> #VALUE!
A35: Component Quality: | B35: Janky | D35: (Lookup from quality table)
A36: Performance %: | B36: 65% | D36: (10-150% based on quality)
A37: DM Applied: | B37: -2 | D37: (-4 to +2 based on quality)
A39: SECTION 5: SALVAGE QUALITY DETERMINATION
A40: Salvage Source: | B40: Wreck | D40: (Wreck/Derelict/Scrap Yard)
A41: Salvage Roll (2D): | B41: 7
A42: Component Condition: | B42: Beyond Janky | D42: (Table lookup based on source + roll)
A43: Can Upgrade To: | B43: Janky | D43: (Next quality level)
A45: SECTION 6: UPGRADE COST CALCULATOR
A46: Current Quality: | B46: Janky
A47: Desired Quality: | B47: Basic | D47: (Must be +1 level only)
A49: MATERIALS TO UPGRADE:
A50: Structural units: | B50: 50
A51: Technical units: | B51: 25
A52: Outfitting units: | B52: 10
A53: Upgrade Cost: | B53: =(B50*10000)+(B51*25000)+(B52*1000) -> 1135000
A54: Labor Required: | B54: 120 | D54: shifts
A56: SECTION 7: DETERIORATION TRACKER
A57: Overall Ship Quality: | B57: Janky | D57: (Worst of Hull/Power Plant)
A58: Deterioration Check Period: | B58: 3 months | D58: (Based on ship quality)
A59: Next Check Due: | B59: 2026-05-05
A60: System at Risk: | B60: Power Plant | D60: (Roll 2D on deterioration table)
A61: Maintenance DM: | B61: +2 | D61: (Engineer skill to avoid deterioration)
A63: GLOBAL SETTINGS
A64: Performance Mode: | B64: DM Only | D64: (DM Only / Reduce Performance)
A65: Material Cost Roll: | B65: Middle | D65: (Minimum / Middle / High / Random)

Sheet Summary
A1: ="Class: "&'Ship Info'!B1&IF(OR('Ship Info'!B2=0,'Ship Info'!B2)="",""," - "&'Ship Info'!B2) -> Class: - | C1: =Tonnage -> 100 | D1: =" Tons "&I1&" TL "&Tech_Level -> Tons Ship TL 12 | I1: =IF(AND('Ship Info'!F7,'Ship Info'!I6="Yes"),"Pod",'Ship Info'!E6) -> Ship | K1: =""
A2: Components | C2: Tons | D2: Cost (Cr) | E2: 1 | F2: 1 | G2: Hull | H2: ='1-Hull'!$B$6&IF('1-Hull'!$B$7="","","-"&'1-Hull'!$B$7)&IF('1-Hull'!$B$6="Streamlined","",", "&'1-Hull'!$B$8)&", "&IF('1-Hull'!$D$5="Yes",""," Non-Gravitic ")&'1-Hull'!$D$6&": "&TEXT('1-Hull'!$D$7,"#,###") -> Standard, Partial, Standard Hull: 40 | I2: ="" | J2: ='1-Hull'!F6 -> 5000000 | K2: ='Ship Info'!C33 -> On
A3: Hull | B3: =H2 -> Standard, Partial, Standard Hull: 40 | D3: =J2 -> 5000000 | E3: =IF(H3="",E2,E2+1) -> 1 | F3: =IF(E3=E2,"",E3) | H3: =IF('1-Hull'!$C$9="No","","Military Hull") | I3: 0 | J3: ='1-Hull'!$F$9 -> 0 | K3: 1
A4: =IF(INDEX(F:J,MATCH(2,F:F,0),2)=0,"",INDEX(F:J,MATCH(2,F:F,0),2)) -> Power Plant | B4: =INDEX(F:J,MATCH(2,F:F,0),3) -> TL 12 Fusion Output: 20 | C4: =INDEX(F:J,MATCH(2,F:F,0),4) -> 1.3333333 | D4: =INDEX(F:J,MATCH(2,F:F,0),5) -> 1333333.3 | E4: =IF(H4="",E3,E3+1) -> 1 | F4: =IF(E4=E3,"",E4) | H4: =IF('1-Hull'!C36=0,"","Secondary Hull "&'1-Hull'!C36&" Tons, "&'1-Hull'!D38&" "&INDEX('1-Hull'!S2:T8,MATCH('1-Hull'!D38,'1-Hull'!S2:S8,0),2)&", "&'1-Hull'!D39) | K4: =IF(B4="","",IF(A4="",K3,K3+1)) -> 2
A5: =IF(INDEX(F:J,MATCH(3,F:F,0),2)=0,"",INDEX(F:J,MATCH(3,F:F,0),2)) -> Fuel | B5: =INDEX(F:J,MATCH(3,F:F,0),3) -> 4 Weeks of Operation* | C5: =INDEX(F:J,MATCH(3,F:F,0),4) -> 0.13333333 | D5: =INDEX(F:J,MATCH(3,F:F,0),5) | E5: =IF(H5="",E4,E4+1) -> 1 | F5: =IF(E5=E4,"",E5) | H5: =IF(J5=0,"",'1-Hull'!B28&": "&'1-Hull'!B29) | I5: ='1-Hull'!H28 -> 0 | J5: ='1-Hull'!F28 -> 0 | K5: =IF(B5="","",IF(A5="",K4,K4+1)) -> 3
A6: =IF(MAX(F:F)<4,"",IF(INDEX(F:J,MATCH(4,F:F,0),2)=0,"",INDEX(F:J,MATCH(4,F:F,0),2))) -> Bridge | B6: =IF(MAX(F:F)<4,"",INDEX(F:J,MATCH(4,F:F,0),3)) -> Standard Bridge | C6: =IF(MAX(F:F)<4,"",INDEX(F:J,MATCH(4,F:F,0),4)) -> 6 | D6: =IF(MAX(F:F)<4,"",INDEX(F:J,MATCH(4,F:F,0),5)) -> 500000 | E6: =IF(H6="",E5,E5+1) -> 1 | F6: =IF(E6=E5,"",E6) | H6: =IF('1-Hull'!A$14<>'1-Hull'!S$25,IF('1-Hull'!C36=0,"","Combined Hull: ")&'1-Hull'!S$26,IF('1-Hull'!C36=0,"",IF('1-Hull'!D14='1-Hull'!S25,"","Secondary Hull Only: "&'1-Hull'!S26))) | I6: ='1-Hull'!H$14 -> 0 | J6: ='1-Hull'!F$14 -> 0 | K6: =IF(B6="","",IF(A6="",K5,K5+1)) -> 4
A7: =IF(MAX(F:F)<5,"",IF(INDEX(F:J,MATCH(5,F:F,0),2)=0,"",INDEX(F:J,MATCH(5,F:F,0),2))) -> Computer | B7: =IF(MAX(F:F)<5,"",INDEX(F:J,MATCH(5,F:F,0),3)) -> Comp/ 5 | C7: =IF(MAX(F:F)<5,"",INDEX(F:J,MATCH(5,F:F,0),4)) -> 0 | D7: =IF(MAX(F:F)<5,"",INDEX(F:J,MATCH(5,F:F,0),5)) -> 30000 | E7: =IF(H7="",E6,E6+1) -> 1 | F7: =IF(E7=E6,"",E7) | H7: =IF('1-Hull'!A$15<>'1-Hull'!S$27,IF('1-Hull'!C36=0,"","Combined Hull: ")&'1-Hull'!S$28,IF('1-Hull'!C36=0,"",IF('1-Hull'!D15='1-Hull'!S$27,"","Secondary Hull Only: "&'1-Hull'!S$28))) | I7: ='1-Hull'!H$15 -> 0 | J7: ='1-Hull'!F$15 -> 0 | K7: =IF(B7="","",IF(A7="",K6,K6+1)) -> 5
A8: =IF(MAX(F:F)<6,"",IF(INDEX(F:J,MATCH(6,F:F,0),2)=0,"",INDEX(F:J,MATCH(6,F:F,0),2))) -> Software | B8: =IF(MAX(F:F)<6,"",INDEX(F:J,MATCH(6,F:F,0),3)) -> Library | C8: =IF(MAX(F:F)<6,"",INDEX(F:J,MATCH(6,F:F,0),4)) -> 0 | D8: =IF(MAX(F:F)<6,"",INDEX(F:J,MATCH(6,F:F,0),5)) -> 0 | E8: =IF(H8="",E7,E7+1) -> 1 | F8: =IF(E8=E7,"",E8) | H8: =IF('1-Hull'!A$16<>'1-Hull'!S$29,IF('1-Hull'!C36=0,"","Combined Hull: ")&'1-Hull'!S$30,IF('1-Hull'!C36=0,"",IF('1-Hull'!D$16='1-Hull'!S$29,"","Secondary Hull Only: "&'1-Hull'!S$30))) | I8: ='1-Hull'!H$16 -> 0 | J8: ='1-Hull'!F$16 -> 0 | K8: =IF(B8="","",IF(A8="",K7,K7+1)) -> 6
A9: =IF(MAX(F:F)<7,"",IF(INDEX(F:J,MATCH(7,F:F,0),2)=0,"",INDEX(F:J,MATCH(7,F:F,0),2))) | B9: =IF(MAX(F:F)<7,"",INDEX(F:J,MATCH(7,F:F,0),3)) -> Manoeuvre/0 | C9: =IF(MAX(F:F)<7,"",INDEX(F:J,MATCH(7,F:F,0),4)) -> 0 | D9: =IF(MAX(F:F)<7,"",INDEX(F:J,MATCH(7,F:F,0),5)) -> 0 | E9: =IF(H9="",E8,E8+1) -> 1 | F9: =IF(E9=E8,"",E9) | H9: =IF('1-Hull'!$A$17<>'1-Hull'!$S$48,IF('1-Hull'!C36=0,"","Combined Hull: ")&'1-Hull'!$S$49,IF('1-Hull'!C36=0,"",IF('1-Hull'!D$17='1-Hull'!S$48,"","Secondary Hull Only: "&'1-Hull'!S$49))) | I9: ='1-Hull'!H$17 -> 0 | J9: ='1-Hull'!F$17 -> 0 | K9: =IF(B9="","",IF(A9="",K8,K8+1)) -> 6
A10: =IF(MAX(F:F)<8,"",IF(INDEX(F:J,MATCH(8,F:F,0),2)=0,"",INDEX(F:J,MATCH(8,F:F,0),2))) | B10: =IF(MAX(F:F)<8,"",INDEX(F:J,MATCH(8,F:F,0),3)) -> Intellect | C10: =IF(MAX(F:F)<8,"",INDEX(F:J,MATCH(8,F:F,0),4)) -> 0 | D10: =IF(MAX(F:F)<8,"",INDEX(F:J,MATCH(8,F:F,0),5)) -> 0 | E10: =IF(H10="",E9,E9+1) -> 1 | F10: =IF(E10=E9,"",E10) | H10: =IF('1-Hull'!$A$18<>'1-Hull'!$S$31,IF('1-Hull'!C36=0,"","Combined Hull: ")&'1-Hull'!$A$18,IF('1-Hull'!C36=0,"",IF('1-Hull'!$D$18='1-Hull'!$S$31,"","Secondary Hull Only: "&'1-Hull'!$D$18))) | I10: ='1-Hull'!H$18 -> 0 | J10: ='1-Hull'!F$18 -> 0 | K10: =IF(B10="","",IF(A10="",K9,K9+1)) -> 6
A11: =IF(MAX(F:F)<9,"",IF(INDEX(F:J,MATCH(9,F:F,0),2)=0,"",INDEX(F:J,MATCH(9,F:F,0),2))) -> Sensors | B11: =IF(MAX(F:F)<9,"",INDEX(F:J,MATCH(9,F:F,0),3)) -> Main Sensor Array: Basic x1 | C11: =IF(MAX(F:F)<9,"",INDEX(F:J,MATCH(9,F:F,0),4)) -> 0 | D11: =IF(MAX(F:F)<9,"",INDEX(F:J,MATCH(9,F:F,0),5)) -> 0 | E11: =IF(H11="",E10,E10+1) -> 1 | F11: =IF(E11=E10,"",E11) | H11: =IF('1-Hull'!$A$19<>'1-Hull'!$S$33,IF('1-Hull'!C36=0,"","Combined Hull: ")&'1-Hull'!$A$19,IF('1-Hull'!C36=0,"",IF('1-Hull'!$D$19='1-Hull'!$S$33,"","Secondary Hull Only: "&'1-Hull'!$D$19))) | I11: ='1-Hull'!H$19 -> 0 | J11: ='1-Hull'!F$19 -> 0 | K11: =IF(B11="","",IF(A11="",K10,K10+1)) -> 7
A12: =IF(MAX(F:F)<10,"",IF(INDEX(F:J,MATCH(10,F:F,0),2)=0,"",INDEX(F:J,MATCH(10,F:F,0),2))) -> Systems | B12: =IF(MAX(F:F)<10,"",INDEX(F:J,MATCH(10,F:F,0),3)) -> 1x 2 ton Airlock | C12: =IF(MAX(F:F)<10,"",INDEX(F:J,MATCH(10,F:F,0),4)) -> 0 | D12: =IF(MAX(F:F)<10,"",INDEX(F:J,MATCH(10,F:F,0),5)) -> 0 | E12: =IF(H12="",E11,E11+1) -> 1 | F12: =IF(E12=E11,"",E12) | H12: =IF('1-Hull'!$A$20<>'1-Hull'!$S$38,IF('1-Hull'!C36=0,"","Combined Hull: ")&'1-Hull'!$A$20,IF('1-Hull'!C36=0,"",IF('1-Hull'!$D$20='1-Hull'!$S$38,"","Secondary Hull Only: "&'1-Hull'!$D$20))) | I12: ='1-Hull'!H$20 -> 0 | J12: ='1-Hull'!F$20 -> 0 | K12: =IF(B12="","",IF(A12="",K11,K11+1)) -> 8
A13: =IF(MAX(F:F)<11,"",IF(INDEX(F:J,MATCH(11,F:F,0),2)=0,"",INDEX(F:J,MATCH(11,F:F,0),2))) -> Total | B13: =IF(MAX(F:F)<11,"",INDEX(F:J,MATCH(11,F:F,0),3)) -> 6863333.3 | C13: =IF(MAX(F:F)<11,"",INDEX(F:J,MATCH(11,F:F,0),4)) -> CR | D13: =IF(MAX(F:F)<11,"",INDEX(F:J,MATCH(11,F:F,0),5)) | E13: =IF(H13="",E12,E12+1) -> 1 | F13: =IF(E13=E12,"",E13) | H13: =IF('1-Hull'!$A$21<>'1-Hull'!$S$41,IF('1-Hull'!C36=0,"","Combined Hull: ")&'1-Hull'!$A$21,IF('1-Hull'!C36=0,"",IF('1-Hull'!$D$21='1-Hull'!$S$41,"","Secondary Hull Only: "&'1-Hull'!$D$21))) | I13: ='1-Hull'!H$21 -> 0 | J13: ='1-Hull'!F$21 -> 0 | K13: =IF(B13="","",IF(A13="",K12,K12+1)) -> 9
A14: =IF(MAX(F:F)<12,"",IF(INDEX(F:J,MATCH(12,F:F,0),2)=0,"",INDEX(F:J,MATCH(12,F:F,0),2))) | B14: =IF(MAX(F:F)<12,"",INDEX(F:J,MATCH(12,F:F,0),3)) -> Purchase Price: | C14: =IF(MAX(F:F)<12,"",INDEX(F:J,MATCH(12,F:F,0),4)) | D14: =IF(MAX(F:F)<12,"",INDEX(F:J,MATCH(12,F:F,0),5)) -> 6177000 | E14: =IF(H14="",E13,E13+1) -> 1 | F14: =IF(E14=E13,"",E14) | H14: =IF('1-Hull'!$A$22<>'1-Hull'!$S$46,IF('1-Hull'!C36=0,"","Combined Hull: ")&'1-Hull'!$A$22&": "&'1-Hull'!B22,IF('1-Hull'!C36=0,"",IF('1-Hull'!$D$22='1-Hull'!$S$46,"","Secondary Only: "&'1-Hull'!$D$22&": "&INDEX('1-Hull'!S46:AA47,MATCH('1-Hull'!D22,'1-Hull'!S46:S47,0),9)))) | I14: ='1-Hull'!H$22 -> 0 | J14: ='1-Hull'!F$22 -> 0 | K14: =IF(B14="","",IF(A14="",K13,K13+1)) -> 9
A15: =IF(MAX(F:F)<13,"",IF(INDEX(F:J,MATCH(13,F:F,0),2)=0,"",INDEX(F:J,MATCH(13,F:F,0),2))) -> Ship Expenses | B15: =IF(MAX(F:F)<13,"",INDEX(F:J,MATCH(13,F:F,0),3)) -> Mortgage: | C15: =IF(MAX(F:F)<13,"",INDEX(F:J,MATCH(13,F:F,0),4)) | D15: =IF(MAX(F:F)<13,"",INDEX(F:J,MATCH(13,F:F,0),5)) -> 25737.5 | E15: =IF(H15="",E14,E14+1) -> 1 | F15: =IF(E15=E14,"",E15) | H15: =IF('1-Hull'!$A$23<>'1-Hull'!$S$50,IF('1-Hull'!C36=0,"","Combined Hull: ")&'1-Hull'!$A$23&": "&'1-Hull'!B23,IF('1-Hull'!C36=0,"",IF('1-Hull'!$D$23='1-Hull'!$S$50,"","Secondary Only: "&'1-Hull'!$D$23&": "&INDEX('1-Hull'!S50:AA51,MATCH('1-Hull'!D23,'1-Hull'!S50:S51,0),9)))) | I15: ='1-Hull'!H$23 -> 0 | J15: ='1-Hull'!F$23 -> 0 | K15: =IF(B15="","",IF(A15="",K14,K14+1)) -> 10
A16: =IF(MAX(F:F)<14,"",IF(INDEX(F:J,MATCH(14,F:F,0),2)=0,"",INDEX(F:J,MATCH(14,F:F,0),2))) | B16: =IF(MAX(F:F)<14,"",INDEX(F:J,MATCH(14,F:F,0),3)) -> Maintenance Cost | C16: =IF(MAX(F:F)<14,"",INDEX(F:J,MATCH(14,F:F,0),4)) | D16: =IF(MAX(F:F)<14,"",INDEX(F:J,MATCH(14,F:F,0),5)) -> 515 | E16: =IF(H16="",E15,E15+1) -> 1 | F16: =IF(E16=E15,"",E16) | H16: =IF('1-Hull'!$A$24='1-Hull'!$S$43,"",'1-Hull'!$A$24&" "&'1-Hull'!$D$24&"% Coverage Power:"&'1-Hull'!$K24*-1) | I16: ='1-Hull'!H$24 -> 0 | J16: ='1-Hull'!F$24 -> 0 | K16: =IF(B16="","",IF(A16="",K15,K15+1)) -> 10
A17: =IF(MAX(F:F)<15,"",IF(INDEX(F:J,MATCH(15,F:F,0),2)=0,"",INDEX(F:J,MATCH(15,F:F,0),2))) | B17: =IF(MAX(F:F)<15,"",INDEX(F:J,MATCH(15,F:F,0),3)) -> Life Support: | C17: =IF(MAX(F:F)<15,"",INDEX(F:J,MATCH(15,F:F,0),4)) | D17: =IF(MAX(F:F)<15,"",INDEX(F:J,MATCH(15,F:F,0),5)) -> 0 | E17: =IF(H17="",E16,E16+1) -> 1 | F17: =IF(E17=E16,"",E17) | H17: =IF('1-Hull'!$C$32=0,"",TEXT('1-Hull'!$C$32,"#,##0.00")&" Tons of Modular Sections") | I17: 0 | J17: =SUM('1-Hull'!F$32:F$34) -> 0 | K17: =IF(B17="","",IF(A17="",K16,K16+1)) -> 10
A18: =IF(MAX(F:F)<16,"",IF(INDEX(F:J,MATCH(16,F:F,0),2)=0,"",INDEX(F:J,MATCH(16,F:F,0),2))) | B18: =IF(MAX(F:F)<16,"",INDEX(F:J,MATCH(16,F:F,0),3)) -> Crew Salaries: | C18: =IF(MAX(F:F)<16,"",INDEX(F:J,MATCH(16,F:F,0),4)) | D18: =IF(MAX(F:F)<16,"",INDEX(F:J,MATCH(16,F:F,0),5)) -> 19000 | E18: =IF(H18="",E17,E17+1) -> 1 | F18: =IF(E18=E17,"",E18) | H18: =IF('1-Hull'!$C$36=0,"",TEXT('1-Hull'!$C$36,"#,##0.00")&" Dtons of Breakaway Hull(s)") | I18: ='1-Hull'!H$36 -> 0 | J18: ='1-Hull'!F$36 -> 0 | K18: =IF(B18="","",IF(A18="",K17,K17+1)) -> 10
A19: =IF(MAX(F:F)<17,"",IF(INDEX(F:J,MATCH(17,F:F,0),2)=0,"",INDEX(F:J,MATCH(17,F:F,0),2))) | B19: =IF(MAX(F:F)<17,"",INDEX(F:J,MATCH(17,F:F,0),3)) -> Fuel: | C19: =IF(MAX(F:F)<17,"",INDEX(F:J,MATCH(17,F:F,0),4)) | D19: =IF(MAX(F:F)<17,"",INDEX(F:J,MATCH(17,F:F,0),5)) -> 0 | E19: =IF(H19="",E18,E18+1) -> 1 | F19: =IF(E19=E18,"",E19) | H19: =IF('1-Hull'!$A$44='1-Hull'!$AC$58,"",'1-Hull'!$A$43&": "&TEXT('1-Hull'!$C$43,"#,##0.00")&" Dton Outer Hull") | I19: ='1-Hull'!H$43 -> 0 | J19: ='1-Hull'!F$46 -> 0 | K19: =IF(B19="","",IF(A19="",K18,K18+1)) -> 10
A20: =IF(MAX(F:F)<18,"",IF(INDEX(F:J,MATCH(18,F:F,0),2)=0,"",INDEX(F:J,MATCH(18,F:F,0),2))) | B20: =IF(MAX(F:F)<18,"",INDEX(F:J,MATCH(18,F:F,0),3)) -> Total Expenses: | C20: =IF(MAX(F:F)<18,"",INDEX(F:J,MATCH(18,F:F,0),4)) | D20: =IF(MAX(F:F)<18,"",INDEX(F:J,MATCH(18,F:F,0),5)) -> 45252.5 | E20: =IF(H20="",E19,E19+1) -> 1 | F20: =IF(E20=E19,"",E20) | H20: =IF('1-Hull'!$C$46=0,"",TEXT('1-Hull'!$C$46,"#,##0.00")&" Dtons of Hamster Cage(s)") | I20: ='1-Hull'!H$46 -> 0 | J20: ='1-Hull'!F$46 -> 0 | K20: =IF(B20="","",IF(A20="",K19,K19+1)) -> 10
A21: =IF(MAX(F:F)<19,"",IF(INDEX(F:J,MATCH(19,F:F,0),2)=0,"",INDEX(F:J,MATCH(19,F:F,0),2))) -> Ship Income | B21: =IF(MAX(F:F)<19,"",INDEX(F:J,MATCH(19,F:F,0),3)) -> Total Income: | C21: =IF(MAX(F:F)<19,"",INDEX(F:J,MATCH(19,F:F,0),4)) | D21: =IF(MAX(F:F)<19,"",INDEX(F:J,MATCH(19,F:F,0),5)) -> 0 | E21: =IF(H21="",E20,E20+1) -> 1 | F21: =IF(E21=E20,"",E21) | G21: =IF(J21=0,"","Armor") | H21: =IF('1-Hull'!$D$11=0,"",IF('1-Hull'!$B$10='1-Hull'!$S$18,"Intrinsic Armor",'1-Hull'!$B$10)&": "&'1-Hull'!$D$11)&IF('1-Hull'!C36=0,"",", 2ry "&IF('1-Hull'!D40='1-Hull'!S18,"",'1-Hull'!D40)&": "&'1-Hull'!G41) | I21: ='1-Hull'!$H$10 -> 0 | J21: ='1-Hull'!$F$10 -> 0 | K21: =IF(B21="","",IF(A21="",K20,K20+1)) -> 11
A22: =IF(MAX(F:F)<20,"",IF(INDEX(F:J,MATCH(20,F:F,0),2)=0,"",INDEX(F:J,MATCH(20,F:F,0),2))) | B22: =IF(MAX(F:F)<20,"",INDEX(F:J,MATCH(20,F:F,0),3)) -> Total Loss: | C22: =IF(MAX(F:F)<20,"",INDEX(F:J,MATCH(20,F:F,0),4)) | D22: =IF(MAX(F:F)<20,"",INDEX(F:J,MATCH(20,F:F,0),5)) -> -45252.5 | E22: =IF(H22="",E21,E21+1) -> 1 | F22: =IF(E22=E21,"",E22) | G22: =IF(H22="","","M-Drive") | H22: =IF('2-Drives'!$B$14='2-Drives'!$S$2,"",'2-Drives'!$S$91&" "&IF('2-Drives'!C11="No",""," @ "&TEXT('2-Drives'!BF25,"#,###")&" Tons")) | I22: =SUM('2-Drives'!H14:H21) -> 0 | J22: =SUM('2-Drives'!F14:F21) -> 0 | K22: =IF(B22="","",IF(A22="",K21,K21+1)) -> 11
A23: =IF(MAX(F:F)<21,"",IF(INDEX(F:J,MATCH(21,F:F,0),2)=0,"",INDEX(F:J,MATCH(21,F:F,0),2))) -> Crew | B23: =IF(MAX(F:F)<21,"",INDEX(F:J,MATCH(21,F:F,0),3)) -> 1x PILOT | C23: =IF(MAX(F:F)<21,"",INDEX(F:J,MATCH(21,F:F,0),4)) | D23: =IF(MAX(F:F)<21,"",INDEX(F:J,MATCH(21,F:F,0),5)) -> 6000 | E23: =IF(H23="",E22,E22+1) -> 1 | F23: =IF(E23=E22,"",E23) | G23: =IF(H23="","",IF(G22="","M-Drive","")) | H23: =IF('2-Drives'!$B$46='2-Drives'!$S$69,"",RIGHT('2-Drives'!$S$92,(LEN('2-Drives'!$S$92)-2))&IF('2-Drives'!C11="No",""," @ "&TEXT('2-Drives'!BF29,"#,###")&" Tons"))&IF('2-Drives'!C50="No","",", SDM") | I23: =SUM('2-Drives'!H46:H54) -> 0 | J23: =SUM('2-Drives'!F46:F54) -> 0 | K23: =IF(B23="","",IF(A23="",K22,K22+1)) -> 12
A24: =IF(MAX(F:F)<22,"",IF(INDEX(F:J,MATCH(22,F:F,0),2)=0,"",INDEX(F:J,MATCH(22,F:F,0),2))) | B24: =IF(MAX(F:F)<22,"",INDEX(F:J,MATCH(22,F:F,0),3)) -> 1x ENGINEER | C24: =IF(MAX(F:F)<22,"",INDEX(F:J,MATCH(22,F:F,0),4)) | D24: =IF(MAX(F:F)<22,"",INDEX(F:J,MATCH(22,F:F,0),5)) -> 4000 | E24: =IF(H24="",E23,E23+1) -> 1 | F24: =IF(E24=E23,"",E24) | H24: =IF('2-Drives'!BJ25="N/A","","Combined M-Drive Rating: "&'2-Drives'!BJ25&"G") | K24: =IF(B24="","",IF(A24="",K23,K23+1)) -> 12
A25: =IF(MAX(F:F)<23,"",IF(INDEX(F:J,MATCH(23,F:F,0),2)=0,"",INDEX(F:J,MATCH(23,F:F,0),2))) | B25: =IF(MAX(F:F)<23,"",INDEX(F:J,MATCH(23,F:F,0),3)) -> 1x MAINTENANCE | C25: =IF(MAX(F:F)<23,"",INDEX(F:J,MATCH(23,F:F,0),4)) | D25: =IF(MAX(F:F)<23,"",INDEX(F:J,MATCH(23,F:F,0),5)) -> 1000 | E25: =IF(H25="",E24,E24+1) -> 1 | F25: =IF(E25=E24,"",E25) | G25: =IF(H25="","","Reaction Drive") | H25: =IF('2-Drives'!$B$23='2-Drives'!$T$12,"",RIGHT('2-Drives'!$S$95,(LEN('2-Drives'!$S$95)-2))&IF('2-Drives'!C11="No",""," @ "&TEXT('2-Drives'!BF26,"#,###")&" Tons")) | I25: =SUM('2-Drives'!H23:H27) -> 0 | J25: =SUM('2-Drives'!F23:F27) -> 0 | K25: =IF(B25="","",IF(A25="",K24,K24+1)) -> 12
A26: =IF(MAX(F:F)<24,"",IF(INDEX(F:J,MATCH(24,F:F,0),2)=0,"",INDEX(F:J,MATCH(24,F:F,0),2))) | B26: =IF(MAX(F:F)<24,"",INDEX(F:J,MATCH(24,F:F,0),3)) -> 1x MEDIC | C26: =IF(MAX(F:F)<24,"",INDEX(F:J,MATCH(24,F:F,0),4)) | D26: =IF(MAX(F:F)<24,"",INDEX(F:J,MATCH(24,F:F,0),5)) -> 4000 | E26: =IF(H26="",E25,E25+1) -> 1 | F26: =IF(E26=E25,"",E26) | G26: =IF(H26="","","High Burn Thruster") | H26: =IF('2-Drives'!$B$37='2-Drives'!$S$14,"",RIGHT('2-Drives'!$S$96,(LEN('2-Drives'!$S$96)-2))&IF('2-Drives'!C11="No",""," @ "&TEXT('2-Drives'!BF30,"#,###")&" Tons")) | I26: =SUM('2-Drives'!H37:H41) -> 0 | J26: =SUM('2-Drives'!F37:F41) -> 0 | K26: =IF(B26="","",IF(A26="",K25,K25+1)) -> 12
A27: =IF(MAX(F:F)<25,"",IF(INDEX(F:J,MATCH(25,F:F,0),2)=0,"",INDEX(F:J,MATCH(25,F:F,0),2))) | B27: =IF(MAX(F:F)<25,"",INDEX(F:J,MATCH(25,F:F,0),3)) -> 1x SENSOP, 1 Sensor Actions per Round | C27: =IF(MAX(F:F)<25,"",INDEX(F:J,MATCH(25,F:F,0),4)) | D27: =IF(MAX(F:F)<25,"",INDEX(F:J,MATCH(25,F:F,0),5)) -> 4000 | E27: =IF(H27="",E26,E26+1) -> 1 | F27: =IF(E27=E26,"",E27) | G27: =IF(H27="","","Sails") | H27: =IF('2-Drives'!$H$44=0,"",'2-Drives'!$S$17 &" Thrust 0") | I27: ='2-Drives'!H44 -> 0 | J27: ='2-Drives'!F44 -> 0 | K27: =IF(B27="","",IF(A27="",K26,K26+1)) -> 12
A28: =IF(MAX(F:F)<26,"",IF(INDEX(F:J,MATCH(26,F:F,0),2)=0,"",INDEX(F:J,MATCH(26,F:F,0),2))) | B28: =IF(MAX(F:F)<26,"",INDEX(F:J,MATCH(26,F:F,0),3)) -> 5 TOTAL SOPHONT CREW | C28: =IF(MAX(F:F)<26,"",INDEX(F:J,MATCH(26,F:F,0),4)) | D28: =IF(MAX(F:F)<26,"",INDEX(F:J,MATCH(26,F:F,0),5)) | E28: =IF(H28="",E27,E27+1) -> 1 | F28: =IF(E28=E27,"",E28) | H28: =IF('2-Drives'!BJ26="N/A","","Combined Reaction Drive Rating: "&'2-Drives'!BJ26&"G") | K28: =IF(B28="","",IF(A28="",K27,K27+1)) -> 12
A29: =IF(MAX(F:F)<27,"",IF(INDEX(F:J,MATCH(27,F:F,0),2)=0,"",INDEX(F:J,MATCH(27,F:F,0),2))) -> Power | B29: =IF(MAX(F:F)<27,"",INDEX(F:J,MATCH(27,F:F,0),3)) -> Power Distribution: Normal (Battle Load) | C29: =IF(MAX(F:F)<27,"",INDEX(F:J,MATCH(27,F:F,0),4)) -> Available: | D29: =IF(MAX(F:F)<27,"",INDEX(F:J,MATCH(27,F:F,0),5)) -> 20 PP | E29: =IF(H29="",E28,E28+1) -> 1 | F29: =IF(E29=E28,"",E29) | G29: =IF(H29="","","FTL") | H29: =IF('2-Drives'!$B$29='2-Drives'!$S$5,"",'2-Drives'!$S$101&IF('2-Drives'!C11="No",""," @ "&TEXT('2-Drives'!BF27,"#,###")&" Tons")) | I29: =SUM('2-Drives'!H29:H34) -> 0 | J29: =SUM('2-Drives'!F29:F34) -> 0 | K29: =IF(B29="","",IF(A29="",K28,K28+1)) -> 13
A30: =IF(MAX(F:F)<28,"",IF(INDEX(F:J,MATCH(28,F:F,0),2)=0,"",INDEX(F:J,MATCH(28,F:F,0),2))) | B30: =IF(MAX(F:F)<28,"",INDEX(F:J,MATCH(28,F:F,0),3)) -> Basic/Hull | C30: =IF(MAX(F:F)<28,"",INDEX(F:J,MATCH(28,F:F,0),4)) | D30: =IF(MAX(F:F)<28,"",INDEX(F:J,MATCH(28,F:F,0),5)) -> 20/ (10) PP | E30: =IF(H30="",E29,E29+1) -> 1 | F30: =IF(E30=E29,"",E30) | G30: =IF(H30="","",IF(G29="","FTL","")) | H30: =IF('2-Drives'!$B$56='2-Drives'!$S$5,"",RIGHT('2-Drives'!$S$102,(LEN('2-Drives'!$S$102)-2))&IF('2-Drives'!C11="No",""," @ "&TEXT('2-Drives'!BF31,"#,###")&" Tons")) | I30: =SUM('2-Drives'!H56:H59) -> 0 | J30: =SUM('2-Drives'!F56:F61) -> 0 | K30: =IF(B30="","",IF(A30="",K29,K29+1)) -> 13
A31: =IF(MAX(F:F)<29,"",IF(INDEX(F:J,MATCH(29,F:F,0),2)=0,"",INDEX(F:J,MATCH(29,F:F,0),2))) | B31: =IF(MAX(F:F)<29,"",INDEX(F:J,MATCH(29,F:F,0),3)) -> Maximum Load (Battle Load) | C31: =IF(MAX(F:F)<29,"",INDEX(F:J,MATCH(29,F:F,0),4)) | D31: =IF(MAX(F:F)<29,"",INDEX(F:J,MATCH(29,F:F,0),5)) -> 20 (10) | E31: =IF(H31="",E30,E30+1) -> 1 | F31: =IF(E31=E30,"",E31) | H31: =IF('2-Drives'!BJ27="N/A","","Combined J-Drive Rating: J"&'2-Drives'!BJ27&IF('2-Drives'!BK27="","",", "&'2-Drives'!BK27)) | K31: =IF(B31="","",IF(A31="",K30,K30+1)) -> 13
A32: =IF(MAX(F:F)<30,"",IF(INDEX(F:J,MATCH(30,F:F,0),2)=0,"",INDEX(F:J,MATCH(30,F:F,0),2))) -> ERROR | B32: =IF(MAX(F:F)<30,"",INDEX(F:J,MATCH(30,F:F,0),3)) -> CREW/STATEROOMS ERROR | C32: =IF(MAX(F:F)<30,"",INDEX(F:J,MATCH(30,F:F,0),4)) | D32: =IF(MAX(F:F)<30,"",INDEX(F:J,MATCH(30,F:F,0),5)) | E32: =IF(H32="",E31,E31+1) -> 2 | F32: =IF(E32=E31,"",E32) -> 2 | G32: =IF(H32="","","Power Plant") -> Power Plant | H32: =IF('3-Pwr Plant'!$D$11=0,"",IF(AND('3-Pwr Plant'!C7='3-Pwr Plant'!S17,'Ship Info'!E6="Module"),"*","")&'3-Pwr Plant'!$B$11&" Output: "&TEXT('3-Pwr Plant'!$D$11+'3-Pwr Plant'!$L$12&" ","#,### ")&'3-Pwr Plant'!$Z$12)&IF(INDEX('3-Pwr Plant'!S2:Y10,MATCH('3-Pwr Plant'!B11,'3-Pwr Plant'!S2:S10,0),7)=0,"",", "&INDEX('3-Pwr Plant'!S2:Y10,MATCH('3-Pwr Plant'!B11,'3-Pwr Plant'!S2:S10,0),7)&" Year Life") -> TL 12 Fusion Output: 20 | I32: =SUM('3-Pwr Plant'!H11:H14) -> 1.3333333 | J32: =SUM('3-Pwr Plant'!F11:F14) -> 1333333.3 | K32: =IF(B32="","",IF(A32="",K31,K31+1)) -> 14
A33: =IF(MAX(F:F)<31,"",IF(INDEX(F:J,MATCH(31,F:F,0),2)=0,"",INDEX(F:J,MATCH(31,F:F,0),2))) | B33: =IF(MAX(F:F)<31,"",INDEX(F:J,MATCH(31,F:F,0),3)) | C33: =IF(MAX(F:F)<31,"",INDEX(F:J,MATCH(31,F:F,0),4)) | D33: =IF(MAX(F:F)<31,"",INDEX(F:J,MATCH(31,F:F,0),5)) | E33: =IF(H33="",E32,E32+1) -> 2 | F33: =IF(E33=E32,"",E33) | H33: =IF(OR('3-Pwr Plant'!$H$15=0,'3-Pwr Plant'!$H$15=""),"","Emergency Power System") | I33: ='3-Pwr Plant'!H15 | J33: ='3-Pwr Plant'!F15 | K33: =IF(B33="","",IF(A33="",K32,K32+1))
A34: =IF(MAX(F:F)<32,"",IF(INDEX(F:J,MATCH(32,F:F,0),2)=0,"",INDEX(F:J,MATCH(32,F:F,0),2))) | B34: =IF(MAX(F:F)<32,"",INDEX(F:J,MATCH(32,F:F,0),3)) | C34: =IF(MAX(F:F)<32,"",INDEX(F:J,MATCH(32,F:F,0),4)) | D34: =IF(MAX(F:F)<32,"",INDEX(F:J,MATCH(32,F:F,0),5)) | E34: =IF(H34="",E33,E33+1) -> 2 | F34: =IF(E34=E33,"",E34) | G34: =IF(G32="",IF(H34="","","Power Plant"),"") | H34: =IF('3-Pwr Plant'!$H$18=0,"",TEXT('3-Pwr Plant'!$D$18,"#,###")&"x "&'3-Pwr Plant'!$C$18&" Batteries - Power: "&TEXT('3-Pwr Plant'!$L$18,"#,###")) | I34: ='3-Pwr Plant'!H18 -> 0 | J34: ='3-Pwr Plant'!F18 -> 0 | K34: =IF(B34="","",IF(A34="",K33,K33+1))
A35: =IF(MAX(F:F)<33,"",IF(INDEX(F:J,MATCH(33,F:F,0),2)=0,"",INDEX(F:J,MATCH(33,F:F,0),2))) | B35: =IF(MAX(F:F)<33,"",INDEX(F:J,MATCH(33,F:F,0),3)) | C35: =IF(MAX(F:F)<33,"",INDEX(F:J,MATCH(33,F:F,0),4)) | D35: =IF(MAX(F:F)<33,"",INDEX(F:J,MATCH(33,F:F,0),5)) | E35: =IF(H35="",E34,E34+1) -> 2 | F35: =IF(E35=E34,"",E35) | G35: =IF(AND(G32="",G34=""),IF(H35="","","Power Plant"),"") | H35: =IF('3-Pwr Plant'!$H$20=0,"",TEXT('3-Pwr Plant'!$D$20,"#,###")&"x Jump Collectors") | I35: ='3-Pwr Plant'!H20 -> 0 | J35: ='3-Pwr Plant'!F20 -> 0 | K35: =IF(B35="","",IF(A35="",K34,K34+1))
A36: =IF(MAX(F:F)<34,"",IF(INDEX(F:J,MATCH(34,F:F,0),2)=0,"",INDEX(F:J,MATCH(34,F:F,0),2))) | B36: =IF(MAX(F:F)<34,"",INDEX(F:J,MATCH(34,F:F,0),3)) | C36: =IF(MAX(F:F)<34,"",INDEX(F:J,MATCH(34,F:F,0),4)) | D36: =IF(MAX(F:F)<34,"",INDEX(F:J,MATCH(34,F:F,0),5)) | E36: =IF(H36="",E35,E35+1) -> 2 | F36: =IF(E36=E35,"",E36) | G36: =IF(AND(G32="",G35="",G34=""),IF(H36="","","Power Plant"),"") | H36: =IF('3-Pwr Plant'!$H$22=0,"",TEXT('3-Pwr Plant'!$D$22,"#,###")&" Units of "&'3-Pwr Plant'!$C$22&" Solar Panels - Power: "&TEXT('3-Pwr Plant'!$L$22,"#,###")) | I36: ='3-Pwr Plant'!H22 -> 0 | J36: ='3-Pwr Plant'!F22 -> 0 | K36: =IF(B36="","",IF(A36="",K35,K35+1))
A37: =IF(MAX(F:F)<35,"",IF(INDEX(F:J,MATCH(35,F:F,0),2)=0,"",INDEX(F:J,MATCH(35,F:F,0),2))) | B37: =IF(MAX(F:F)<35,"",INDEX(F:J,MATCH(35,F:F,0),3)) | C37: =IF(MAX(F:F)<35,"",INDEX(F:J,MATCH(35,F:F,0),4)) | D37: =IF(MAX(F:F)<35,"",INDEX(F:J,MATCH(35,F:F,0),5)) | E37: =IF(H37="",E36,E36+1) -> 2 | F37: =IF(E37=E36,"",E37) | H37: =IF(OR('3-Pwr Plant'!$H$16=0,'3-Pwr Plant'!$H$16=""),"","Armored Bulkheads") | I37: ='3-Pwr Plant'!H16 | J37: ='3-Pwr Plant'!F16 | K37: =IF(B37="","",IF(A37="",K36,K36+1))
A38: =IF(MAX(F:F)<36,"",IF(INDEX(F:J,MATCH(36,F:F,0),2)=0,"",INDEX(F:J,MATCH(36,F:F,0),2))) | B38: =IF(MAX(F:F)<36,"",INDEX(F:J,MATCH(36,F:F,0),3)) | C38: =IF(MAX(F:F)<36,"",INDEX(F:J,MATCH(36,F:F,0),4)) | D38: =IF(MAX(F:F)<36,"",INDEX(F:J,MATCH(36,F:F,0),5)) | E38: =IF(H38="",E37,E37+1) -> 3 | F38: =IF(E38=E37,"",E38) -> 3 | G38: =IF(H38="","","Fuel") -> Fuel | H38: =IF('4-Fuel'!$H$10=0,"",IF('4-Fuel'!$B$9=0,"",'4-Fuel'!$B$9&" "&'4-Fuel'!A9&", ")&'4-Fuel'!$C$10&" Weeks of Operation"&IF('4-Fuel'!$C$5="Yes","*","")&IF('4-Fuel'!$B$8=0,"",", "&"Reaction Hours: "&'4-Fuel'!$B$8)&IF('4-Fuel'!C30='4-Fuel'!T9,"",", F/C Bay")) -> 4 Weeks of Operation* | I38: =SUM('4-Fuel'!H8:H10) -> 0.13333333 | J38: ="" | K38: =IF(B38="","",IF(A38="",K37,K37+1))
A39: =IF(MAX(F:F)<37,"",IF(INDEX(F:J,MATCH(37,F:F,0),2)=0,"",INDEX(F:J,MATCH(37,F:F,0),2))) | B39: =IF(MAX(F:F)<37,"",INDEX(F:J,MATCH(37,F:F,0),3)) | C39: =IF(MAX(F:F)<37,"",INDEX(F:J,MATCH(37,F:F,0),4)) | D39: =IF(MAX(F:F)<37,"",INDEX(F:J,MATCH(37,F:F,0),5)) | E39: =IF(H39="",E38,E38+1) -> 3 | F39: =IF(E39=E38,"",E39) | G39: =IF(G38="",IF(H39="","","Fuel"),"") | H39: =IF('4-Fuel'!$H$11=0,"","Additional Tons of Fuel") | I39: ='4-Fuel'!H11 -> 0 | J39: ="" | K39: =IF(B39="","",IF(A39="",K38,K38+1))
A40: =IF(MAX(F:F)<38,"",IF(INDEX(F:J,MATCH(38,F:F,0),2)=0,"",INDEX(F:J,MATCH(38,F:F,0),2))) | B40: =IF(MAX(F:F)<38,"",INDEX(F:J,MATCH(38,F:F,0),3)) | C40: =IF(MAX(F:F)<38,"",INDEX(F:J,MATCH(38,F:F,0),4)) | D40: =IF(MAX(F:F)<38,"",INDEX(F:J,MATCH(38,F:F,0),5)) | E40: =IF(H40="",E39,E39+1) -> 3 | F40: =IF(E40=E39,"",E40) | G40: =IF(AND(G38="",G39=""),IF(H40="","","Fuel"),"") | H40: =IF('4-Fuel'!$A$23='4-Fuel'!$S$15,"",TEXT('4-Fuel'!$C$23,"#,##0.00")&" Tons "&'4-Fuel'!$A$22&" (Min Cargo: "&TEXT('4-Fuel'!$C$23/100,"#,##0.00")&" Tons)") | J40: ='4-Fuel'!F23 -> 0 | K40: =IF(B40="","",IF(A40="",K39,K39+1))
A41: =IF(MAX(F:F)<39,"",IF(INDEX(F:J,MATCH(39,F:F,0),2)=0,"",INDEX(F:J,MATCH(39,F:F,0),2))) | B41: =IF(MAX(F:F)<39,"",INDEX(F:J,MATCH(39,F:F,0),3)) | C41: =IF(MAX(F:F)<39,"",INDEX(F:J,MATCH(39,F:F,0),4)) | D41: =IF(MAX(F:F)<39,"",INDEX(F:J,MATCH(39,F:F,0),5)) | E41: =IF(H41="",E40,E40+1) -> 3 | F41: =IF(E41=E40,"",E41) | G41: =IF(AND(G38="",G39="",G40=""),IF(H41="","","Fuel"),"") | H41: =IF('4-Fuel'!$A$26='4-Fuel'!$S$15,"",TEXT('4-Fuel'!$C$26,"#,###")&" "&'4-Fuel'!$C$25&" "&'4-Fuel'!$A$25) | J41: ='4-Fuel'!F26 -> 0 | K41: =IF(B41="","",IF(A41="",K40,K40+1))
A42: =IF(MAX(F:F)<40,"",IF(INDEX(F:J,MATCH(40,F:F,0),2)=0,"",INDEX(F:J,MATCH(40,F:F,0),2))) | B42: =IF(MAX(F:F)<40,"",INDEX(F:J,MATCH(40,F:F,0),3)) | C42: =IF(MAX(F:F)<40,"",INDEX(F:J,MATCH(40,F:F,0),4)) | D42: =IF(MAX(F:F)<40,"",INDEX(F:J,MATCH(40,F:F,0),5)) | E42: =IF(H42="",E41,E41+1) -> 3 | F42: =IF(E42=E41,"",E42) | G42: =IF(AND(G38="",G39="",G40="",G41=""),IF(H42="","","Fuel"),"") | H42: =IF('4-Fuel'!$B$29*'4-Fuel'!$C$29=0,"",'4-Fuel'!$A$28&" "&'4-Fuel'!$B$29&"x "&TEXT('4-Fuel'!$C$29,"#,##0.00")&" Ton Bay(s)") | I42: ='4-Fuel'!H29 -> 0 | J42: ='4-Fuel'!F29 -> 0 | K42: =IF(B42="","",IF(A42="",K41,K41+1))
A43: =IF(MAX(F:F)<41,"",IF(INDEX(F:J,MATCH(41,F:F,0),2)=0,"",INDEX(F:J,MATCH(41,F:F,0),2))) | B43: =IF(MAX(F:F)<41,"",INDEX(F:J,MATCH(41,F:F,0),3)) | C43: =IF(MAX(F:F)<41,"",INDEX(F:J,MATCH(41,F:F,0),4)) | D43: =IF(MAX(F:F)<41,"",INDEX(F:J,MATCH(41,F:F,0),5)) | E43: =IF(H43="",E42,E42+1) -> 3 | F43: =IF(E43=E42,"",E43) | H43: =IF('4-Fuel'!C31='4-Fuel'!$S$48,"",'4-Fuel'!A28&" "&'4-Fuel'!B31) | I43: ='4-Fuel'!H31 -> 0 | J43: ='4-Fuel'!F31 -> 0 | K43: =IF(B43="","",IF(A43="",K42,K42+1))
A44: =IF(MAX(F:F)<42,"",IF(INDEX(F:J,MATCH(42,F:F,0),2)=0,"",INDEX(F:J,MATCH(42,F:F,0),2))) | B44: =IF(MAX(F:F)<42,"",INDEX(F:J,MATCH(42,F:F,0),3)) | C44: =IF(MAX(F:F)<42,"",INDEX(F:J,MATCH(42,F:F,0),4)) | D44: =IF(MAX(F:F)<42,"",INDEX(F:J,MATCH(42,F:F,0),5)) | E44: =IF(H44="",E43,E43+1) -> 3 | F44: =IF(E44=E43,"",E44) | H44: =IF('4-Fuel'!C32='4-Fuel'!$S$48,"",'4-Fuel'!A28&" "&'4-Fuel'!B32) | I44: ='4-Fuel'!H32 -> 0 | J44: ='4-Fuel'!F32 -> 0 | K44: =IF(B44="","",IF(A44="",K43,K43+1))
A45: =IF(MAX(F:F)<43,"",IF(INDEX(F:J,MATCH(43,F:F,0),2)=0,"",INDEX(F:J,MATCH(43,F:F,0),2))) | B45: =IF(MAX(F:F)<43,"",INDEX(F:J,MATCH(43,F:F,0),3)) | C45: =IF(MAX(F:F)<43,"",INDEX(F:J,MATCH(43,F:F,0),4)) | D45: =IF(MAX(F:F)<43,"",INDEX(F:J,MATCH(43,F:F,0),5)) | E45: =IF(H45="",E44,E44+1) -> 3 | F45: =IF(E45=E44,"",E45) | H45: =IF('4-Fuel'!$A$36='4-Fuel'!$S$15,"",TEXT('4-Fuel'!$C$36,"#,##0.00")&" Ton "&'4-Fuel'!$A$35) | I45: ='4-Fuel'!H36 -> 0 | J45: ='4-Fuel'!F36 -> 0 | K45: =IF(B45="","",IF(A45="",K44,K44+1))
A46: =IF(MAX(F:F)<44,"",IF(INDEX(F:J,MATCH(44,F:F,0),2)=0,"",INDEX(F:J,MATCH(44,F:F,0),2))) | B46: =IF(MAX(F:F)<44,"",INDEX(F:J,MATCH(44,F:F,0),3)) | C46: =IF(MAX(F:F)<44,"",INDEX(F:J,MATCH(44,F:F,0),4)) | D46: =IF(MAX(F:F)<44,"",INDEX(F:J,MATCH(44,F:F,0),5)) | E46: =IF(H46="",E45,E45+1) -> 3 | F46: =IF(E46=E45,"",E46) | H46: =IF('4-Fuel'!$H$40=0,"",'4-Fuel'!$B$40) | I46: ='4-Fuel'!H40 -> 0 | J46: ='4-Fuel'!F40 -> 0 | K46: =IF(B46="","",IF(A46="",K45,K45+1))
A47: =IF(MAX(F:F)<45,"",IF(INDEX(F:J,MATCH(45,F:F,0),2)=0,"",INDEX(F:J,MATCH(45,F:F,0),2))) | B47: =IF(MAX(F:F)<45,"",INDEX(F:J,MATCH(45,F:F,0),3)) | C47: =IF(MAX(F:F)<45,"",INDEX(F:J,MATCH(45,F:F,0),4)) | D47: =IF(MAX(F:F)<45,"",INDEX(F:J,MATCH(45,F:F,0),5)) | E47: =IF(H47="",E46,E46+1) -> 3 | F47: =IF(E47=E46,"",E47) | H47: =IF('4-Fuel'!$C$12='4-Fuel'!$T$9,"","Armored Bulkheads") | I47: ='4-Fuel'!H12 -> 0 | J47: ='4-Fuel'!F12 | K47: =IF(B47="","",IF(A47="",K46,K46+1))
A48: =IF(MAX(F:F)<46,"",IF(INDEX(F:J,MATCH(46,F:F,0),2)=0,"",INDEX(F:J,MATCH(46,F:F,0),2))) | B48: =IF(MAX(F:F)<46,"",INDEX(F:J,MATCH(46,F:F,0),3)) | C48: =IF(MAX(F:F)<46,"",INDEX(F:J,MATCH(46,F:F,0),4)) | D48: =IF(MAX(F:F)<46,"",INDEX(F:J,MATCH(46,F:F,0),5)) | E48: =IF(H48="",E47,E47+1) -> 3 | F48: =IF(E48=E47,"",E48) | H48: =IF('4-Fuel'!C47=0,"","Custom: "&'4-Fuel'!B47&": "&'4-Fuel'!C47&"Tons/"&'4-Fuel'!C49+('4-Fuel'!C47*'4-Fuel'!B49)&" Cargo Used" ) | I48: ='4-Fuel'!H47 -> 0 | J48: ='4-Fuel'!F47 -> 0 | K48: =IF(B48="","",IF(A48="",K47,K47+1))
A49: =IF(MAX(F:F)<47,"",IF(INDEX(F:J,MATCH(47,F:F,0),2)=0,"",INDEX(F:J,MATCH(47,F:F,0),2))) | B49: =IF(MAX(F:F)<47,"",INDEX(F:J,MATCH(47,F:F,0),3)) | C49: =IF(MAX(F:F)<47,"",INDEX(F:J,MATCH(47,F:F,0),4)) | D49: =IF(MAX(F:F)<47,"",INDEX(F:J,MATCH(47,F:F,0),5)) | E49: =IF(H49="",E48,E48+1) -> 4 | F49: =IF(E49=E48,"",E49) -> 4 | G49: Bridge | H49: ='5-Bridge'!$A$9 -> Standard Bridge | I49: ='5-Bridge'!H9 -> 6 | J49: ='5-Bridge'!F9 -> 500000 | K49: =IF(B49="","",IF(A49="",K48,K48+1))
A50: =IF(MAX(F:F)<48,"",IF(INDEX(F:J,MATCH(48,F:F,0),2)=0,"",INDEX(F:J,MATCH(48,F:F,0),2))) | B50: =IF(MAX(F:F)<48,"",INDEX(F:J,MATCH(48,F:F,0),3)) | C50: =IF(MAX(F:F)<48,"",INDEX(F:J,MATCH(48,F:F,0),4)) | D50: =IF(MAX(F:F)<48,"",INDEX(F:J,MATCH(48,F:F,0),5)) | E50: =IF(H50="",E49,E49+1) -> 4 | F50: =IF(E50=E49,"",E50) | H50: =IF('5-Bridge'!$A$10='5-Bridge'!$S$16,'5-Bridge'!$A$8&" "&'5-Bridge'!$A$10,"") | J50: ='5-Bridge'!F10 -> 0 | K50: =IF(B50="","",IF(A50="",K49,K49+1))
A51: =IF(MAX(F:F)<49,"",IF(INDEX(F:J,MATCH(49,F:F,0),2)=0,"",INDEX(F:J,MATCH(49,F:F,0),2))) | B51: =IF(MAX(F:F)<49,"",INDEX(F:J,MATCH(49,F:F,0),3)) | C51: =IF(MAX(F:F)<49,"",INDEX(F:J,MATCH(49,F:F,0),4)) | D51: =IF(MAX(F:F)<49,"",INDEX(F:J,MATCH(49,F:F,0),5)) | E51: =IF(H51="",E50,E50+1) -> 4 | F51: =IF(E51=E50,"",E51) | H51: =IF('5-Bridge'!$C$17=0,"","Aux Con: "&'5-Bridge'!$A$17&" x"&'5-Bridge'!$C$17&IF('5-Bridge'!C20=0,"",", "&'5-Bridge'!C20&"x set as SCC's")) | I51: ='5-Bridge'!H17 -> 0 | J51: ='5-Bridge'!F17 -> 0 | K51: =IF(B51="","",IF(A51="",K50,K50+1))
A52: =IF(MAX(F:F)<50,"",IF(INDEX(F:J,MATCH(50,F:F,0),2)=0,"",INDEX(F:J,MATCH(50,F:F,0),2))) | B52: =IF(MAX(F:F)<50,"",INDEX(F:J,MATCH(50,F:F,0),3)) | C52: =IF(MAX(F:F)<50,"",INDEX(F:J,MATCH(50,F:F,0),4)) | D52: =IF(MAX(F:F)<50,"",INDEX(F:J,MATCH(50,F:F,0),5)) | E52: =IF(H52="",E51,E51+1) -> 4 | F52: =IF(E52=E51,"",E52) | H52: =IF('5-Bridge'!$A$18='5-Bridge'!$S$17,"","Aux Con: "&'5-Bridge'!$A$18) | J52: ='5-Bridge'!F18 -> 0 | K52: =IF(B52="","",IF(A52="",K51,K51+1))
A53: =IF(MAX(F:F)<51,"",IF(INDEX(F:J,MATCH(51,F:F,0),2)=0,"",INDEX(F:J,MATCH(51,F:F,0),2))) | B53: =IF(MAX(F:F)<51,"",INDEX(F:J,MATCH(51,F:F,0),3)) | C53: =IF(MAX(F:F)<51,"",INDEX(F:J,MATCH(51,F:F,0),4)) | D53: =IF(MAX(F:F)<51,"",INDEX(F:J,MATCH(51,F:F,0),5)) | E53: =IF(H53="",E52,E52+1) -> 4 | F53: =IF(E53=E52,"",E53) | H53: =IF('5-Bridge'!$A$13='5-Bridge'!$AA$5,"",IF('5-Bridge'!$C$13=0,"",'5-Bridge'!$C$13&"x "&'5-Bridge'!$A$13)) | I53: ='5-Bridge'!H13 -> 0 | J53: ='5-Bridge'!F13 -> 0 | K53: =IF(B53="","",IF(A53="",K52,K52+1))
A54: =IF(MAX(F:F)<52,"",IF(INDEX(F:J,MATCH(52,F:F,0),2)=0,"",INDEX(F:J,MATCH(52,F:F,0),2))) | B54: =IF(MAX(F:F)<52,"",INDEX(F:J,MATCH(52,F:F,0),3)) | C54: =IF(MAX(F:F)<52,"",INDEX(F:J,MATCH(52,F:F,0),4)) | D54: =IF(MAX(F:F)<52,"",INDEX(F:J,MATCH(52,F:F,0),5)) | E54: =IF(H54="",E53,E53+1) -> 4 | F54: =IF(E54=E53,"",E54) | H54: =IF('5-Bridge'!$A$18='5-Bridge'!$S$17,"","Command Bridge: "&'5-Bridge'!$A$18) | J54: ='5-Bridge'!F14 -> 0 | K54: =IF(B54="","",IF(A54="",K53,K53+1))
A55: =IF(MAX(F:F)<53,"",IF(INDEX(F:J,MATCH(53,F:F,0),2)=0,"",INDEX(F:J,MATCH(53,F:F,0),2))) | B55: =IF(MAX(F:F)<53,"",INDEX(F:J,MATCH(53,F:F,0),3)) | C55: =IF(MAX(F:F)<53,"",INDEX(F:J,MATCH(53,F:F,0),4)) | D55: =IF(MAX(F:F)<53,"",INDEX(F:J,MATCH(53,F:F,0),5)) | E55: =IF(H55="",E54,E54+1) -> 4 | F55: =IF(E55=E54,"",E55) | H55: =IF('5-Bridge'!$A$24='5-Bridge'!$S$50,"",'5-Bridge'!$A$24) | J55: ='5-Bridge'!F24 -> 0 | K55: =IF(B55="","",IF(A55="",K54,K54+1))
A56: =IF(MAX(F:F)<54,"",IF(INDEX(F:J,MATCH(54,F:F,0),2)=0,"",INDEX(F:J,MATCH(54,F:F,0),2))) | B56: =IF(MAX(F:F)<54,"",INDEX(F:J,MATCH(54,F:F,0),3)) | C56: =IF(MAX(F:F)<54,"",INDEX(F:J,MATCH(54,F:F,0),4)) | D56: =IF(MAX(F:F)<54,"",INDEX(F:J,MATCH(54,F:F,0),5)) | E56: =IF(H56="",E55,E55+1) -> 4 | F56: =IF(E56=E55,"",E56) | H56: ='5-Bridge'!$S$61 | J56: =SUM('5-Bridge'!F27,'5-Bridge'!F30) -> 0 | K56: =IF(B56="","",IF(A56="",K55,K55+1))
A57: =IF(MAX(F:F)<55,"",IF(INDEX(F:J,MATCH(55,F:F,0),2)=0,"",INDEX(F:J,MATCH(55,F:F,0),2))) | B57: =IF(MAX(F:F)<55,"",INDEX(F:J,MATCH(55,F:F,0),3)) | C57: =IF(MAX(F:F)<55,"",INDEX(F:J,MATCH(55,F:F,0),4)) | D57: =IF(MAX(F:F)<55,"",INDEX(F:J,MATCH(55,F:F,0),5)) | E57: =IF(H57="",E56,E56+1) -> 4 | F57: =IF(E57=E56,"",E57) | H57: =IF(OR('5-Bridge'!$C$22='5-Bridge'!$S$29,'5-Bridge'!A9='5-Bridge'!S12),"Armored Bulkheads","") | I57: ='5-Bridge'!H22 -> 0 | J57: ='5-Bridge'!F22 -> 0 | K57: =IF(B57="","",IF(A57="",K56,K56+1))
A58: =IF(MAX(F:F)<56,"",IF(INDEX(F:J,MATCH(56,F:F,0),2)=0,"",INDEX(F:J,MATCH(56,F:F,0),2))) | B58: =IF(MAX(F:F)<56,"",INDEX(F:J,MATCH(56,F:F,0),3)) | C58: =IF(MAX(F:F)<56,"",INDEX(F:J,MATCH(56,F:F,0),4)) | D58: =IF(MAX(F:F)<56,"",INDEX(F:J,MATCH(56,F:F,0),5)) | E58: =IF(H58="",E57,E57+1) -> 4 | F58: =IF(E58=E57,"",E58) | H58: =IF('7-Sensors'!$C$12=0,"",'7-Sensors'!$C$12&"x "&"Additional "&IF('7-Sensors'!$E$13="No","","Armored ")&"Sensor Stations") | I58: ='7-Sensors'!$H$12 -> 0 | J58: ='7-Sensors'!$F$12 -> 0 | K58: =IF(B58="","",IF(A58="",K57,K57+1))
A59: =IF(MAX(F:F)<57,"",IF(INDEX(F:J,MATCH(57,F:F,0),2)=0,"",INDEX(F:J,MATCH(57,F:F,0),2))) | B59: =IF(MAX(F:F)<57,"",INDEX(F:J,MATCH(57,F:F,0),3)) | C59: =IF(MAX(F:F)<57,"",INDEX(F:J,MATCH(57,F:F,0),4)) | D59: =IF(MAX(F:F)<57,"",INDEX(F:J,MATCH(57,F:F,0),5)) | E59: =IF(H59="",E58,E58+1) -> 5 | F59: =IF(E59=E58,"",E59) -> 5 | G59: =IF(H59="","","Computer") -> Computer | H59: ='6-Comp'!$B$9&IF('6-Comp'!$B$10='6-Comp'!$S$21,""," /bis")&IF('6-Comp'!$B$11='6-Comp'!$S$21,"","/fib")&IF('6-Comp'!$B$9="","",'6-Comp'!AB12) -> Comp/ 5 | J59: =SUM('6-Comp'!F9:F11) -> 30000 | K59: =IF(B59="","",IF(A59="",K58,K58+1))
A60: =IF(MAX(F:F)<58,"",IF(INDEX(F:J,MATCH(58,F:F,0),2)=0,"",INDEX(F:J,MATCH(58,F:F,0),2))) | B60: =IF(MAX(F:F)<58,"",INDEX(F:J,MATCH(58,F:F,0),3)) | C60: =IF(MAX(F:F)<58,"",INDEX(F:J,MATCH(58,F:F,0),4)) | D60: =IF(MAX(F:F)<58,"",INDEX(F:J,MATCH(58,F:F,0),5)) | E60: =IF(H60="",E59,E59+1) -> 5 | F60: =IF(E60=E59,"",E60) | H60: =IF('6-Comp'!$B$13="","","B/U "&'6-Comp'!$B$13&IF('6-Comp'!$B$14='6-Comp'!$S$21,""," /bis")&IF('6-Comp'!$B$15='6-Comp'!$S$21,"","/fib")&'6-Comp'!AB12) | J60: =SUM('6-Comp'!F13:F15) -> 0 | K60: =IF(B60="","",IF(A60="",K59,K59+1))
A61: =IF(MAX(F:F)<59,"",IF(INDEX(F:J,MATCH(59,F:F,0),2)=0,"",INDEX(F:J,MATCH(59,F:F,0),2))) | B61: =IF(MAX(F:F)<59,"",INDEX(F:J,MATCH(59,F:F,0),3)) | C61: =IF(MAX(F:F)<59,"",INDEX(F:J,MATCH(59,F:F,0),4)) | D61: =IF(MAX(F:F)<59,"",INDEX(F:J,MATCH(59,F:F,0),5)) | E61: =IF(H61="",E60,E60+1) -> 6 | F61: =IF(E61=E60,"",E61) -> 6 | G61: =IF(H61="","","Software") -> Software | H61: ='6-Comp'!B34&IF(Tech_Level>7,""," Prototype") -> Library | J61: 0 | K61: =IF(B61="","",IF(A61="",K60,K60+1))
A62: =IF(MAX(F:F)<60,"",IF(INDEX(F:J,MATCH(60,F:F,0),2)=0,"",INDEX(F:J,MATCH(60,F:F,0),2))) | B62: =IF(MAX(F:F)<60,"",INDEX(F:J,MATCH(60,F:F,0),3)) | C62: =IF(MAX(F:F)<60,"",INDEX(F:J,MATCH(60,F:F,0),4)) | D62: =IF(MAX(F:F)<60,"",INDEX(F:J,MATCH(60,F:F,0),5)) | E62: =IF(H62="",E61,E61+1) -> 7 | F62: =IF(E62=E61,"",E62) -> 7 | H62: ='6-Comp'!B35 -> Manoeuvre/0 | K62: =IF(B62="","",IF(A62="",K61,K61+1))
A63: =IF(MAX(F:F)<61,"",IF(INDEX(F:J,MATCH(61,F:F,0),2)=0,"",INDEX(F:J,MATCH(61,F:F,0),2))) | B63: =IF(MAX(F:F)<61,"",INDEX(F:J,MATCH(61,F:F,0),3)) | C63: =IF(MAX(F:F)<61,"",INDEX(F:J,MATCH(61,F:F,0),4)) | D63: =IF(MAX(F:F)<61,"",INDEX(F:J,MATCH(61,F:F,0),5)) | E63: =IF(H63="",E62,E62+1) -> 8 | F63: =IF(E63=E62,"",E63) -> 8 | H63: ='6-Comp'!B31 -> Intellect | K63: =IF(B63="","",IF(A63="",K62,K62+1))
A64: =IF(MAX(F:F)<62,"",IF(INDEX(F:J,MATCH(62,F:F,0),2)=0,"",INDEX(F:J,MATCH(62,F:F,0),2))) | B64: =IF(MAX(F:F)<62,"",INDEX(F:J,MATCH(62,F:F,0),3)) | C64: =IF(MAX(F:F)<62,"",INDEX(F:J,MATCH(62,F:F,0),4)) | D64: =IF(MAX(F:F)<62,"",INDEX(F:J,MATCH(62,F:F,0),5)) | E64: =IF(H64="",E63,E63+1) -> 8 | F64: =IF(E64=E63,"",E64) | H64: ='6-Comp'!B21 | J64: ='6-Comp'!F21 -> 0 | K64: =IF(B64="","",IF(A64="",K63,K63+1))
A65: =IF(MAX(F:F)<63,"",IF(INDEX(F:J,MATCH(63,F:F,0),2)=0,"",INDEX(F:J,MATCH(63,F:F,0),2))) | B65: =IF(MAX(F:F)<63,"",INDEX(F:J,MATCH(63,F:F,0),3)) | C65: =IF(MAX(F:F)<63,"",INDEX(F:J,MATCH(63,F:F,0),4)) | D65: =IF(MAX(F:F)<63,"",INDEX(F:J,MATCH(63,F:F,0),5)) | E65: =IF(H65="",E64,E64+1) -> 8 | F65: =IF(E65=E64,"",E65) | H65: ='6-Comp'!B22 | J65: ='6-Comp'!F22 -> 0 | K65: =IF(B65="","",IF(A65="",K64,K64+1))
A66: =IF(MAX(F:F)<64,"",IF(INDEX(F:J,MATCH(64,F:F,0),2)=0,"",INDEX(F:J,MATCH(64,F:F,0),2))) | B66: =IF(MAX(F:F)<64,"",INDEX(F:J,MATCH(64,F:F,0),3)) | C66: =IF(MAX(F:F)<64,"",INDEX(F:J,MATCH(64,F:F,0),4)) | D66: =IF(MAX(F:F)<64,"",INDEX(F:J,MATCH(64,F:F,0),5)) | E66: =IF(H66="",E65,E65+1) -> 8 | F66: =IF(E66=E65,"",E66) | H66: ='6-Comp'!B23 | J66: ='6-Comp'!F23 -> 0 | K66: =IF(B66="","",IF(A66="",K65,K65+1))
A67: =IF(MAX(F:F)<65,"",IF(INDEX(F:J,MATCH(65,F:F,0),2)=0,"",INDEX(F:J,MATCH(65,F:F,0),2))) | B67: =IF(MAX(F:F)<65,"",INDEX(F:J,MATCH(65,F:F,0),3)) | C67: =IF(MAX(F:F)<65,"",INDEX(F:J,MATCH(65,F:F,0),4)) | D67: =IF(MAX(F:F)<65,"",INDEX(F:J,MATCH(65,F:F,0),5)) | E67: =IF(H67="",E66,E66+1) -> 8 | F67: =IF(E67=E66,"",E67) | H67: ='6-Comp'!B24 | J67: ='6-Comp'!F24 -> 0 | K67: =IF(B67="","",IF(A67="",K66,K66+1))
A68: =IF(MAX(F:F)<66,"",IF(INDEX(F:J,MATCH(66,F:F,0),2)=0,"",INDEX(F:J,MATCH(66,F:F,0),2))) | B68: =IF(MAX(F:F)<66,"",INDEX(F:J,MATCH(66,F:F,0),3)) | C68: =IF(MAX(F:F)<66,"",INDEX(F:J,MATCH(66,F:F,0),4)) | D68: =IF(MAX(F:F)<66,"",INDEX(F:J,MATCH(66,F:F,0),5)) | E68: =IF(H68="",E67,E67+1) -> 8 | F68: =IF(E68=E67,"",E68) | H68: ='6-Comp'!B25 | J68: ='6-Comp'!F25 -> 0 | K68: =IF(B68="","",IF(A68="",K67,K67+1))
A69: =IF(MAX(F:F)<67,"",IF(INDEX(F:J,MATCH(67,F:F,0),2)=0,"",INDEX(F:J,MATCH(67,F:F,0),2))) | B69: =IF(MAX(F:F)<67,"",INDEX(F:J,MATCH(67,F:F,0),3)) | C69: =IF(MAX(F:F)<67,"",INDEX(F:J,MATCH(67,F:F,0),4)) | D69: =IF(MAX(F:F)<67,"",INDEX(F:J,MATCH(67,F:F,0),5)) | E69: =IF(H69="",E68,E68+1) -> 8 | F69: =IF(E69=E68,"",E69) | H69: ='6-Comp'!B26 | J69: ='6-Comp'!F26 -> 0 | K69: =IF(B69="","",IF(A69="",K68,K68+1))
A70: =IF(MAX(F:F)<68,"",IF(INDEX(F:J,MATCH(68,F:F,0),2)=0,"",INDEX(F:J,MATCH(68,F:F,0),2))) | B70: =IF(MAX(F:F)<68,"",INDEX(F:J,MATCH(68,F:F,0),3)) | C70: =IF(MAX(F:F)<68,"",INDEX(F:J,MATCH(68,F:F,0),4)) | D70: =IF(MAX(F:F)<68,"",INDEX(F:J,MATCH(68,F:F,0),5)) | E70: =IF(H70="",E69,E69+1) -> 8 | F70: =IF(E70=E69,"",E70) | H70: ='6-Comp'!B27 | J70: ='6-Comp'!F27 -> 0 | K70: =IF(B70="","",IF(A70="",K69,K69+1))
A71: =IF(MAX(F:F)<69,"",IF(INDEX(F:J,MATCH(69,F:F,0),2)=0,"",INDEX(F:J,MATCH(69,F:F,0),2))) | B71: =IF(MAX(F:F)<69,"",INDEX(F:J,MATCH(69,F:F,0),3)) | C71: =IF(MAX(F:F)<69,"",INDEX(F:J,MATCH(69,F:F,0),4)) | D71: =IF(MAX(F:F)<69,"",INDEX(F:J,MATCH(69,F:F,0),5)) | E71: =IF(H71="",E70,E70+1) -> 8 | F71: =IF(E71=E70,"",E71) | H71: ='6-Comp'!B28 | J71: ='6-Comp'!F28 -> 0 | K71: =IF(B71="","",IF(A71="",K70,K70+1))
A72: =IF(MAX(F:F)<70,"",IF(INDEX(F:J,MATCH(70,F:F,0),2)=0,"",INDEX(F:J,MATCH(70,F:F,0),2))) | B72: =IF(MAX(F:F)<70,"",INDEX(F:J,MATCH(70,F:F,0),3)) | C72: =IF(MAX(F:F)<70,"",INDEX(F:J,MATCH(70,F:F,0),4)) | D72: =IF(MAX(F:F)<70,"",INDEX(F:J,MATCH(70,F:F,0),5)) | E72: =IF(H72="",E71,E71+1) -> 8 | F72: =IF(E72=E71,"",E72) | H72: ='6-Comp'!B29 | J72: ='6-Comp'!F29 -> 0 | K72: =IF(B72="","",IF(A72="",K71,K71+1))
A73: =IF(MAX(F:F)<71,"",IF(INDEX(F:J,MATCH(71,F:F,0),2)=0,"",INDEX(F:J,MATCH(71,F:F,0),2))) | B73: =IF(MAX(F:F)<71,"",INDEX(F:J,MATCH(71,F:F,0),3)) | C73: =IF(MAX(F:F)<71,"",INDEX(F:J,MATCH(71,F:F,0),4)) | D73: =IF(MAX(F:F)<71,"",INDEX(F:J,MATCH(71,F:F,0),5)) | E73: =IF(H73="",E72,E72+1) -> 8 | F73: =IF(E73=E72,"",E73) | H73: ='6-Comp'!B30 | J73: ='6-Comp'!F30 -> 0 | K73: =IF(B73="","",IF(A73="",K72,K72+1))
A74: =IF(MAX(F:F)<72,"",IF(INDEX(F:J,MATCH(72,F:F,0),2)=0,"",INDEX(F:J,MATCH(72,F:F,0),2))) | B74: =IF(MAX(F:F)<72,"",INDEX(F:J,MATCH(72,F:F,0),3)) | C74: =IF(MAX(F:F)<72,"",INDEX(F:J,MATCH(72,F:F,0),4)) | D74: =IF(MAX(F:F)<72,"",INDEX(F:J,MATCH(72,F:F,0),5)) | E74: =IF(H74="",E73,E73+1) -> 8 | F74: =IF(E74=E73,"",E74) | H74: ='6-Comp'!B32&IF(SUM('2-Drives'!E32:E34)<0," Prototype","") | J74: ='6-Comp'!F32 -> 0 | K74: =IF(B74="","",IF(A74="",K73,K73+1))
A75: =IF(MAX(F:F)<73,"",IF(INDEX(F:J,MATCH(73,F:F,0),2)=0,"",INDEX(F:J,MATCH(73,F:F,0),2))) | B75: =IF(MAX(F:F)<73,"",INDEX(F:J,MATCH(73,F:F,0),3)) | C75: =IF(MAX(F:F)<73,"",INDEX(F:J,MATCH(73,F:F,0),4)) | D75: =IF(MAX(F:F)<73,"",INDEX(F:J,MATCH(73,F:F,0),5)) | E75: =IF(H75="",E74,E74+1) -> 8 | F75: =IF(E75=E74,"",E75) | H75: ='6-Comp'!B33 | J75: ='6-Comp'!F33 -> 0 | K75: =IF(B75="","",IF(A75="",K74,K74+1))
A76: =IF(MAX(F:F)<74,"",IF(INDEX(F:J,MATCH(74,F:F,0),2)=0,"",INDEX(F:J,MATCH(74,F:F,0),2))) | B76: =IF(MAX(F:F)<74,"",INDEX(F:J,MATCH(74,F:F,0),3)) | C76: =IF(MAX(F:F)<74,"",INDEX(F:J,MATCH(74,F:F,0),4)) | D76: =IF(MAX(F:F)<74,"",INDEX(F:J,MATCH(74,F:F,0),5)) | E76: =IF(H76="",E75,E75+1) -> 8 | F76: =IF(E76=E75,"",E76) | H76: ='6-Comp'!B36 | J76: ='6-Comp'!F36 -> 0 | K76: =IF(B76="","",IF(A76="",K75,K75+1))
A77: =IF(MAX(F:F)<75,"",IF(INDEX(F:J,MATCH(75,F:F,0),2)=0,"",INDEX(F:J,MATCH(75,F:F,0),2))) | B77: =IF(MAX(F:F)<75,"",INDEX(F:J,MATCH(75,F:F,0),3)) | C77: =IF(MAX(F:F)<75,"",INDEX(F:J,MATCH(75,F:F,0),4)) | D77: =IF(MAX(F:F)<75,"",INDEX(F:J,MATCH(75,F:F,0),5)) | E77: =IF(H77="",E76,E76+1) -> 8 | F77: =IF(E77=E76,"",E77) | H77: ='6-Comp'!B37 | J77: ='6-Comp'!F37 -> 0 | K77: =IF(B77="","",IF(A77="",K76,K76+1))
A78: =IF(MAX(F:F)<76,"",IF(INDEX(F:J,MATCH(76,F:F,0),2)=0,"",INDEX(F:J,MATCH(76,F:F,0),2))) | B78: =IF(MAX(F:F)<76,"",INDEX(F:J,MATCH(76,F:F,0),3)) | C78: =IF(MAX(F:F)<76,"",INDEX(F:J,MATCH(76,F:F,0),4)) | D78: =IF(MAX(F:F)<76,"",INDEX(F:J,MATCH(76,F:F,0),5)) | E78: =IF(H78="",E77,E77+1) -> 8 | F78: =IF(E78=E77,"",E78) | H78: =IF('6-Comp'!B39=0,"",'6-Comp'!B38&" Crew: "&'6-Comp'!B39) | J78: =IF('6-Comp'!B39=0,0,'6-Comp'!F38) -> 0 | K78: =IF(B78="","",IF(A78="",K77,K77+1))
A79: =IF(MAX(F:F)<77,"",IF(INDEX(F:J,MATCH(77,F:F,0),2)=0,"",INDEX(F:J,MATCH(77,F:F,0),2))) | B79: =IF(MAX(F:F)<77,"",INDEX(F:J,MATCH(77,F:F,0),3)) | C79: =IF(MAX(F:F)<77,"",INDEX(F:J,MATCH(77,F:F,0),4)) | D79: =IF(MAX(F:F)<77,"",INDEX(F:J,MATCH(77,F:F,0),5)) | E79: =IF(H79="",E78,E78+1) -> 8 | F79: =IF(E79=E78,"",E79) | H79: =IF('6-Comp'!B41=0,"",'6-Comp'!B40&" Gunners: "&'6-Comp'!B41) | J79: =IF('6-Comp'!B41=0,0,'6-Comp'!F40) -> 0 | K79: =IF(B79="","",IF(A79="",K78,K78+1))
A80: =IF(MAX(F:F)<78,"",IF(INDEX(F:J,MATCH(78,F:F,0),2)=0,"",INDEX(F:J,MATCH(78,F:F,0),2))) | B80: =IF(MAX(F:F)<78,"",INDEX(F:J,MATCH(78,F:F,0),3)) | C80: =IF(MAX(F:F)<78,"",INDEX(F:J,MATCH(78,F:F,0),4)) | D80: =IF(MAX(F:F)<78,"",INDEX(F:J,MATCH(78,F:F,0),5)) | E80: =IF(H80="",E79,E79+1) -> 8 | F80: =IF(E80=E79,"",E80) | H80: =IF('6-Comp'!C42=0,"",'6-Comp'!A42&" "&'6-Comp'!I42) | J80: ='6-Comp'!F42 -> 0 | K80: =IF(B80="","",IF(A80="",K79,K79+1))
A81: =IF(MAX(F:F)<79,"",IF(INDEX(F:J,MATCH(79,F:F,0),2)=0,"",INDEX(F:J,MATCH(79,F:F,0),2))) | B81: =IF(MAX(F:F)<79,"",INDEX(F:J,MATCH(79,F:F,0),3)) | C81: =IF(MAX(F:F)<79,"",INDEX(F:J,MATCH(79,F:F,0),4)) | D81: =IF(MAX(F:F)<79,"",INDEX(F:J,MATCH(79,F:F,0),5)) | E81: =IF(H81="",E80,E80+1) -> 8 | F81: =IF(E81=E80,"",E81) | H81: =IF('6-Comp'!B44='6-Comp'!S97,"",'6-Comp'!A44) | J81: ='6-Comp'!F44 -> 0 | K81: =IF(B81="","",IF(A81="",K80,K80+1))
A82: =IF(MAX(F:F)<80,"",IF(INDEX(F:J,MATCH(80,F:F,0),2)=0,"",INDEX(F:J,MATCH(80,F:F,0),2))) | B82: =IF(MAX(F:F)<80,"",INDEX(F:J,MATCH(80,F:F,0),3)) | C82: =IF(MAX(F:F)<80,"",INDEX(F:J,MATCH(80,F:F,0),4)) | D82: =IF(MAX(F:F)<80,"",INDEX(F:J,MATCH(80,F:F,0),5)) | E82: =IF(H82="",E81,E81+1) -> 8 | F82: =IF(E82=E81,"",E82) | H82: =IF('6-Comp'!B48="","",'6-Comp'!B48) | J82: ='6-Comp'!F48 -> 0 | K82: =IF(B82="","",IF(A82="",K81,K81+1))
A83: =IF(MAX(F:F)<81,"",IF(INDEX(F:J,MATCH(81,F:F,0),2)=0,"",INDEX(F:J,MATCH(81,F:F,0),2))) | B83: =IF(MAX(F:F)<81,"",INDEX(F:J,MATCH(81,F:F,0),3)) | C83: =IF(MAX(F:F)<81,"",INDEX(F:J,MATCH(81,F:F,0),4)) | D83: =IF(MAX(F:F)<81,"",INDEX(F:J,MATCH(81,F:F,0),5)) | E83: =IF(H83="",E82,E82+1) -> 8 | F83: =IF(E83=E82,"",E83) | H83: =IF('6-Comp'!B49="","",'6-Comp'!B49&", "&'6-Comp'!C49&" Iteration(s)") | J83: ='6-Comp'!F49 -> 0 | K83: =IF(B83="","",IF(A83="",K82,K82+1))
A84: =IF(MAX(F:F)<82,"",IF(INDEX(F:J,MATCH(82,F:F,0),2)=0,"",INDEX(F:J,MATCH(82,F:F,0),2))) | B84: =IF(MAX(F:F)<82,"",INDEX(F:J,MATCH(82,F:F,0),3)) | C84: =IF(MAX(F:F)<82,"",INDEX(F:J,MATCH(82,F:F,0),4)) | D84: =IF(MAX(F:F)<82,"",INDEX(F:J,MATCH(82,F:F,0),5)) | E84: =IF(H84="",E83,E83+1) -> 8 | F84: =IF(E84=E83,"",E84) | H84: =IF('6-Comp'!B50="","",'6-Comp'!B50&", "&'6-Comp'!C50&" Iteration(s)") | J84: ='6-Comp'!F50 -> 0 | K84: =IF(B84="","",IF(A84="",K83,K83+1))
A85: =IF(MAX(F:F)<83,"",IF(INDEX(F:J,MATCH(83,F:F,0),2)=0,"",INDEX(F:J,MATCH(83,F:F,0),2))) | B85: =IF(MAX(F:F)<83,"",INDEX(F:J,MATCH(83,F:F,0),3)) | C85: =IF(MAX(F:F)<83,"",INDEX(F:J,MATCH(83,F:F,0),4)) | D85: =IF(MAX(F:F)<83,"",INDEX(F:J,MATCH(83,F:F,0),5)) | E85: =IF(H85="",E84,E84+1) -> 8 | F85: =IF(E85=E84,"",E85) | H85: =IF('6-Comp'!B51="","",'6-Comp'!B51&", "&'6-Comp'!C51&" Iteration(s)") | J85: ='6-Comp'!F51 -> 0 | K85: =IF(B85="","",IF(A85="",K84,K84+1))
A86: =IF(MAX(F:F)<84,"",IF(INDEX(F:J,MATCH(84,F:F,0),2)=0,"",INDEX(F:J,MATCH(84,F:F,0),2))) | B86: =IF(MAX(F:F)<84,"",INDEX(F:J,MATCH(84,F:F,0),3)) | C86: =IF(MAX(F:F)<84,"",INDEX(F:J,MATCH(84,F:F,0),4)) | D86: =IF(MAX(F:F)<84,"",INDEX(F:J,MATCH(84,F:F,0),5)) | E86: =IF(H86="",E85,E85+1) -> 8 | F86: =IF(E86=E85,"",E86) | H86: =IF('6-Comp'!B52="","",'6-Comp'!B52&", "&'6-Comp'!C52&" Iteration(s)") | J86: ='6-Comp'!F52 -> 0 | K86: =IF(B86="","",IF(A86="",K85,K85+1))
A87: =IF(MAX(F:F)<85,"",IF(INDEX(F:J,MATCH(85,F:F,0),2)=0,"",INDEX(F:J,MATCH(85,F:F,0),2))) | B87: =IF(MAX(F:F)<85,"",INDEX(F:J,MATCH(85,F:F,0),3)) | C87: =IF(MAX(F:F)<85,"",INDEX(F:J,MATCH(85,F:F,0),4)) | D87: =IF(MAX(F:F)<85,"",INDEX(F:J,MATCH(85,F:F,0),5)) | E87: =IF(H87="",E86,E86+1) -> 8 | F87: =IF(E87=E86,"",E87) | H87: =IF('6-Comp'!B53="","",'6-Comp'!B53) | J87: ='6-Comp'!F53 -> 0 | K87: =IF(B87="","",IF(A87="",K86,K86+1))
A88: =IF(MAX(F:F)<86,"",IF(INDEX(F:J,MATCH(86,F:F,0),2)=0,"",INDEX(F:J,MATCH(86,F:F,0),2))) | B88: =IF(MAX(F:F)<86,"",INDEX(F:J,MATCH(86,F:F,0),3)) | C88: =IF(MAX(F:F)<86,"",INDEX(F:J,MATCH(86,F:F,0),4)) | D88: =IF(MAX(F:F)<86,"",INDEX(F:J,MATCH(86,F:F,0),5)) | E88: =IF(H88="",E87,E87+1) -> 8 | F88: =IF(E88=E87,"",E88) | H88: =IF('6-Comp'!F55=0,"",'6-Comp'!A55) | J88: ='6-Comp'!F55 -> 0 | K88: =IF(B88="","",IF(A88="",K87,K87+1))
A89: =IF(MAX(F:F)<87,"",IF(INDEX(F:J,MATCH(87,F:F,0),2)=0,"",INDEX(F:J,MATCH(87,F:F,0),2))) | B89: =IF(MAX(F:F)<87,"",INDEX(F:J,MATCH(87,F:F,0),3)) | C89: =IF(MAX(F:F)<87,"",INDEX(F:J,MATCH(87,F:F,0),4)) | D89: =IF(MAX(F:F)<87,"",INDEX(F:J,MATCH(87,F:F,0),5)) | E89: =IF(H89="",E88,E88+1) -> 9 | F89: =IF(E89=E88,"",E89) -> 9 | G89: =IF(H89="","","Sensors") -> Sensors | H89: =IF('7-Sensors'!C8=0,"","Main Sensor Array: "&'7-Sensors'!B8&" x"&'7-Sensors'!C8)&IF(Tech_Level=7," Prototype","") -> Main Sensor Array: Basic x1 | I89: ='7-Sensors'!H8 -> 0 | J89: ='7-Sensors'!F8 -> 0 | K89: =IF(B89="","",IF(A89="",K88,K88+1))
A90: =IF(MAX(F:F)<88,"",IF(INDEX(F:J,MATCH(88,F:F,0),2)=0,"",INDEX(F:J,MATCH(88,F:F,0),2))) | B90: =IF(MAX(F:F)<88,"",INDEX(F:J,MATCH(88,F:F,0),3)) | C90: =IF(MAX(F:F)<88,"",INDEX(F:J,MATCH(88,F:F,0),4)) | D90: =IF(MAX(F:F)<88,"",INDEX(F:J,MATCH(88,F:F,0),5)) | E90: =IF(H90="",E89,E89+1) -> 9 | F90: =IF(E90=E89,"",E90) | G90: =IF(H90="","",IF(G89="","Sensors","")) | H90: =IF(OR('7-Sensors'!B11="None",'7-Sensors'!C11=0),"","Aux Sensor Array: "&'7-Sensors'!B11&" x"&'7-Sensors'!C11) | I90: ='7-Sensors'!H11 -> 0 | J90: ='7-Sensors'!F11 -> 0 | K90: =IF(B90="","",IF(A90="",K89,K89+1))
A91: =IF(MAX(F:F)<89,"",IF(INDEX(F:J,MATCH(89,F:F,0),2)=0,"",INDEX(F:J,MATCH(89,F:F,0),2))) | B91: =IF(MAX(F:F)<89,"",INDEX(F:J,MATCH(89,F:F,0),3)) | C91: =IF(MAX(F:F)<89,"",INDEX(F:J,MATCH(89,F:F,0),4)) | D91: =IF(MAX(F:F)<89,"",INDEX(F:J,MATCH(89,F:F,0),5)) | E91: =IF(H91="",E90,E90+1) -> 9 | F91: =IF(E91=E90,"",E91) | G91: =IF(H91="","",IF(AND(G89="",,G90=""),"Sensors","")) | H91: =IF('7-Sensors'!B16=0,"",'7-Sensors'!B16&"x "&'7-Sensors'!A16) | I91: ='7-Sensors'!H16 -> 0 | J91: ='7-Sensors'!F16 -> 0 | K91: =IF(B91="","",IF(A91="",K90,K90+1))
A92: =IF(MAX(F:F)<90,"",IF(INDEX(F:J,MATCH(90,F:F,0),2)=0,"",INDEX(F:J,MATCH(90,F:F,0),2))) | B92: =IF(MAX(F:F)<90,"",INDEX(F:J,MATCH(90,F:F,0),3)) | C92: =IF(MAX(F:F)<90,"",INDEX(F:J,MATCH(90,F:F,0),4)) | D92: =IF(MAX(F:F)<90,"",INDEX(F:J,MATCH(90,F:F,0),5)) | E92: =IF(H92="",E91,E91+1) -> 9 | F92: =IF(E92=E91,"",E92) | G92: =IF(H92="","",IF(AND(G89="",G90="",G91=""),"Sensors","")) | H92: =IF('7-Sensors'!B17=0,"",'7-Sensors'!B17&"x "&'7-Sensors'!A17) | I92: ='7-Sensors'!H17 -> 0 | J92: ='7-Sensors'!F17 -> 0 | K92: =IF(B92="","",IF(A92="",K91,K91+1))
A93: =IF(MAX(F:F)<91,"",IF(INDEX(F:J,MATCH(91,F:F,0),2)=0,"",INDEX(F:J,MATCH(91,F:F,0),2))) | B93: =IF(MAX(F:F)<91,"",INDEX(F:J,MATCH(91,F:F,0),3)) | C93: =IF(MAX(F:F)<91,"",INDEX(F:J,MATCH(91,F:F,0),4)) | D93: =IF(MAX(F:F)<91,"",INDEX(F:J,MATCH(91,F:F,0),5)) | E93: =IF(H93="",E92,E92+1) -> 9 | F93: =IF(E93=E92,"",E93) | G93: =IF(H93="","",IF(AND(G89="",G90="",G92="",G91=""),"Sensors","")) | H93: =IF('7-Sensors'!B18=0,"",'7-Sensors'!B18&"x "&'7-Sensors'!A18) | I93: ='7-Sensors'!H18 -> 0 | J93: ='7-Sensors'!F18 -> 0 | K93: =IF(B93="","",IF(A93="",K92,K92+1))
A94: =IF(MAX(F:F)<92,"",IF(INDEX(F:J,MATCH(92,F:F,0),2)=0,"",INDEX(F:J,MATCH(92,F:F,0),2))) | B94: =IF(MAX(F:F)<92,"",INDEX(F:J,MATCH(92,F:F,0),3)) | C94: =IF(MAX(F:F)<92,"",INDEX(F:J,MATCH(92,F:F,0),4)) | D94: =IF(MAX(F:F)<92,"",INDEX(F:J,MATCH(92,F:F,0),5)) | E94: =IF(H94="",E93,E93+1) -> 9 | F94: =IF(E94=E93,"",E94) | G94: =IF(H94="","",IF(AND(G89="",G90="",G91="",G93="",G92=""),"Sensors","")) | H94: =IF('7-Sensors'!B19=0,"",'7-Sensors'!B19&"x "&'7-Sensors'!A19) | I94: ='7-Sensors'!H19 -> 0 | J94: ='7-Sensors'!F19 -> 0 | K94: =IF(B94="","",IF(A94="",K93,K93+1))
A95: =IF(MAX(F:F)<93,"",IF(INDEX(F:J,MATCH(93,F:F,0),2)=0,"",INDEX(F:J,MATCH(93,F:F,0),2))) | B95: =IF(MAX(F:F)<93,"",INDEX(F:J,MATCH(93,F:F,0),3)) | C95: =IF(MAX(F:F)<93,"",INDEX(F:J,MATCH(93,F:F,0),4)) | D95: =IF(MAX(F:F)<93,"",INDEX(F:J,MATCH(93,F:F,0),5)) | E95: =IF(H95="",E94,E94+1) -> 9 | F95: =IF(E95=E94,"",E95) | G95: =IF(H95="","",IF(AND(G89="",G90="",G91="",G92="",G94="",G93=""),"Sensors","")) | H95: =IF('7-Sensors'!B20=0,"",'7-Sensors'!B20&"x "&'7-Sensors'!A20) | I95: ='7-Sensors'!H20 -> 0 | J95: ='7-Sensors'!F20 -> 0 | K95: =IF(B95="","",IF(A95="",K94,K94+1))
A96: =IF(MAX(F:F)<94,"",IF(INDEX(F:J,MATCH(94,F:F,0),2)=0,"",INDEX(F:J,MATCH(94,F:F,0),2))) | B96: =IF(MAX(F:F)<94,"",INDEX(F:J,MATCH(94,F:F,0),3)) | C96: =IF(MAX(F:F)<94,"",INDEX(F:J,MATCH(94,F:F,0),4)) | D96: =IF(MAX(F:F)<94,"",INDEX(F:J,MATCH(94,F:F,0),5)) | E96: =IF(H96="",E95,E95+1) -> 9 | F96: =IF(E96=E95,"",E96) | G96: =IF(H96="","",IF(AND(G89="",G90="",G91="",G92="",G93="",G95="",G94=""),"Sensors","")) | H96: =IF('7-Sensors'!B21=0,"",'7-Sensors'!B21&"x "&'7-Sensors'!A21) | I96: ='7-Sensors'!H21 -> 0 | J96: ='7-Sensors'!F21 -> 0 | K96: =IF(B96="","",IF(A96="",K95,K95+1))
A97: =IF(MAX(F:F)<95,"",IF(INDEX(F:J,MATCH(95,F:F,0),2)=0,"",INDEX(F:J,MATCH(95,F:F,0),2))) | B97: =IF(MAX(F:F)<95,"",INDEX(F:J,MATCH(95,F:F,0),3)) | C97: =IF(MAX(F:F)<95,"",INDEX(F:J,MATCH(95,F:F,0),4)) | D97: =IF(MAX(F:F)<95,"",INDEX(F:J,MATCH(95,F:F,0),5)) | E97: =IF(H97="",E96,E96+1) -> 9 | F97: =IF(E97=E96,"",E97) | G97: =IF(H97="","",IF(AND(G89="",G90="",G91="",G92="",G93="",G94="",G96="",G95=""),"Sensors","")) | H97: =IF('7-Sensors'!B22=0,"",'7-Sensors'!B22&"x "&'7-Sensors'!A22) | I97: ='7-Sensors'!H22 -> 0 | J97: ='7-Sensors'!F22 -> 0 | K97: =IF(B97="","",IF(A97="",K96,K96+1))
A98: =IF(MAX(F:F)<96,"",IF(INDEX(F:J,MATCH(96,F:F,0),2)=0,"",INDEX(F:J,MATCH(96,F:F,0),2))) | B98: =IF(MAX(F:F)<96,"",INDEX(F:J,MATCH(96,F:F,0),3)) | C98: =IF(MAX(F:F)<96,"",INDEX(F:J,MATCH(96,F:F,0),4)) | D98: =IF(MAX(F:F)<96,"",INDEX(F:J,MATCH(96,F:F,0),5)) | E98: =IF(H98="",E97,E97+1) -> 9 | F98: =IF(E98=E97,"",E98) | G98: =IF(H98="","",IF(AND(G89="",G90="",G91="",G92="",G93="",G94="",G95="",G97="",G96=""),"Sensors","")) | H98: =IF('7-Sensors'!B23=0,"",'7-Sensors'!B23&"x "&'7-Sensors'!A23) | I98: ='7-Sensors'!H23 -> 0 | J98: ='7-Sensors'!F23 -> 0 | K98: =IF(B98="","",IF(A98="",K97,K97+1))
A99: =IF(MAX(F:F)<97,"",IF(INDEX(F:J,MATCH(97,F:F,0),2)=0,"",INDEX(F:J,MATCH(97,F:F,0),2))) | B99: =IF(MAX(F:F)<97,"",INDEX(F:J,MATCH(97,F:F,0),3)) | C99: =IF(MAX(F:F)<97,"",INDEX(F:J,MATCH(97,F:F,0),4)) | D99: =IF(MAX(F:F)<97,"",INDEX(F:J,MATCH(97,F:F,0),5)) | E99: =IF(H99="",E98,E98+1) -> 9 | F99: =IF(E99=E98,"",E99) | G99: =IF(H99="","",IF(AND(G89="",G90="",G91="",G92="",G93="",G94="",G95="",G96="",G98="",G97=""),"Sensors","")) | H99: =IF('7-Sensors'!B24=0,"",'7-Sensors'!B24&"x "&'7-Sensors'!A24) | I99: ='7-Sensors'!H24 -> 0 | J99: ='7-Sensors'!F24 -> 0 | K99: =IF(B99="","",IF(A99="",K98,K98+1))
A100: =IF(MAX(F:F)<98,"",IF(INDEX(F:J,MATCH(98,F:F,0),2)=0,"",INDEX(F:J,MATCH(98,F:F,0),2))) | B100: =IF(MAX(F:F)<98,"",INDEX(F:J,MATCH(98,F:F,0),3)) | C100: =IF(MAX(F:F)<98,"",INDEX(F:J,MATCH(98,F:F,0),4)) | D100: =IF(MAX(F:F)<98,"",INDEX(F:J,MATCH(98,F:F,0),5)) | E100: =IF(H100="",E99,E99+1) -> 9 | F100: =IF(E100=E99,"",E100) | G100: =IF(H100="","",IF(AND(G89="",G90="",G91="",G92="",G93="",G94="",G95="",G96="",G97="",G99="",G98=""),"Sensors","")) | H100: =IF('7-Sensors'!B25=0,"",'7-Sensors'!B25&"x "&'7-Sensors'!A25) | I100: ='7-Sensors'!H25 -> 0 | J100: ='7-Sensors'!F25 -> 0 | K100: =IF(B100="","",IF(A100="",K99,K99+1))
...

Sheet Profitability
A1: Ship's Expenses | E1: Monthly Report | J1: Variable Report | U1: <<<Edge | AA1: Edge>>>
A3: Mortgage: | B3: ='Ship Info'!B24 -> 25737.5 | E3: =IF(E4<0,"Loss","Profit") -> Loss | G3: Layover (days): | H3: 7 | K3: Time Period (Days): | L3: 14
A4: Maintenance Cost | B4: ='Ship Info'!B25 -> 515 | E4: =H6+H7 -> -45252.5 | G4: Jumps (4 weeks): | H4: =28/(7+H3) -> 2 | K4: Number of Jumps: | L4: 1
A5: Life Support: | B5: ='Ship Info'!B26 -> 0
A6: Crew Salaries: | B6: ='10-Crew'!G32 -> 19000 | G6: Total Income (4 weeks): | H6: =D40*H4 -> 0 | K6: Income: | L6: =L4*D40 -> 0
A7: Fuel: | B7: =IF(E7="No",0,IF(E7="Unrefined",('4-Fuel'!H9*Profitability!H4+('4-Fuel'!H10/'4-Fuel'!C10)*4)*100,(('4-Fuel'!H9+E8+('4-Fuel'!H10/'4-Fuel'!C10)*4)*Profitability!H4)*500)) -> 0 | D7: Buy Fuel? | E7: No | G7: Total Expenses (4 weeks): | H7: =('Ship Info'!B29*-1)-E8 -> -45252.5 | K7: Expenses: | L7: =-1*L3*B8/28 -> -22626.25
A8: Total Expenses: | B8: =SUM(B3:B7) -> 45252.5 | D8: Buy Additional Fuel? | E8: 0 | K8: =IF(L8<0,"Loss:","Profit:") -> Loss: | L8: =L6+L7 -> -22626.25
H9: Listed | J9: Externally Added/Unlisted
B10: Income | E10: Capacity | H10: Cargo from Modules, | J10: Cargo from Modules, | M10: Parsecs
A11: Cargo | B11: Tons | C11: Parsecs | D11: Payments Received | E11: Available | G11: Max | H11: Pods & Carried Ships | J11: Pods & Carried Ships | M11: 0 | N11: 1 | O11: 2 | P11: 3 | Q11: 4 | R11: 5 | S11: 6
A12: Freight | B12: 0 | C12: 0 | D12: =B12*INDEX(M11:S14,2,MATCH(C12,M11:S11,0)) -> 0 | E12: =G12-B12-B13-B14 -> #N/A | F12: of | G12: =IF(C12 > '2-Drives'!D29, 0, ('12-Cargo'!C18 * '12-Cargo'!D18) + ('12-Cargo'!C22 * '12-Cargo'!D22) + ('12-Cargo'!C26 * '12-Cargo'!D26) + '12-Cargo'!D30 + '12-Cargo'!D32 + IF(SUM(B19:B36)=0, '12-Cargo'!C35, 0) + IF(AND(C12 <> '4-Fuel'!B9, '4-Fuel'!B29 > 0), ('4-Fuel'!B9 - C12) * '4-Fuel'!C29, 0) + J12 + H12 + MIN('12-Cargo'!D11 + '12-Cargo'!D13, ABS(HLOOKUP(C12, '2-Drives'!$BC$8:$BT$14, 7, FALSE)) - '1-Hull'!B4) ) -> #N/A | H12: =SUMPRODUCT('9a-Optional'!P27:P56,'9a-Optional'!R27:R56) -> 0 | J12: 0 | L12: Per Ton | M12: 0 | N12: 1000 | O12: 1600 | P12: 2600 | Q12: 4400 | R12: 8500 | S12: 32000
A13: Mail | B13: 0 | C13: 0 | D13: =B13*INDEX(M11:S14,3,MATCH(C13,M11:S11,0)) -> 0 | M13: 0 | N13: 5000 | O13: 5000 | P13: 5000 | Q13: 5000 | R13: 5000 | S13: 5000
A14: Basic/Steerage (2 tons) | B14: 0 | C14: 0 | D14: =B14*INDEX(M11:S14,4,MATCH(C14,M11:S11,0)) -> 0 | M14: 0 | N14: 1000 | O14: 1500 | P14: 2500 | Q14: 4000 | R14: 7000 | S14: 27500
A15: Spec Trade | D15: 0
C16: Total Cargo Income: | D16: =SUM(D12:D15) -> 0 | H16: Listed | J16: Externally Added/Unlisted
E17: Capacity | H17: Staterooms from Modules, | J17: Staterooms from Modules, | M17: Parsecs
A18: Passengers | B18: Staterooms Filled | C18: Parsecs | D18: Payments Received | E18: Available | G18: Max | H18: Pods & Carried Ships | J18: Pods & Carried Ships | M18: 0 | N18: 1 | O18: 2 | P18: 3 | Q18: 4 | R18: 5 | S18: 6
A19: Low Berths | B19: 0 | C19: 0 | D19: =B19*INDEX($M$18:$S$28,2,MATCH(C19,$M$18:$S$18,0)) -> 0 | E19: =G19-B19 -> 0 | F19: of | G19: ='11-Staterooms'!C42+J19+H19 -> 0 | H19: =SUMPRODUCT('9a-Optional'!P27:P56,'9a-Optional'!S27:S56) -> 0 | J19: 0 | L19: Per SR | M19: 0 | N19: 700 | O19: 1300 | P19: 2200 | Q19: 3900 | R19: 7200 | S19: 27000 | T19: 1 low berth
A20: Basic | B20: 0 | C20: 0 | D20: =B20*INDEX($M$18:$S$28,3,MATCH(C20,$M$18:$S$18,0)) -> 0 | E20: =G20-B20-B22 -> 0 | F20: of | G20: ='11-Staterooms'!C46+J20+J22+H20 -> 0 | H20: =SUMPRODUCT('9a-Optional'!P27:P56,'9a-Optional'!T27:T56) -> 0 | J20: 0 | M20: 0 | N20: 4000 | O20: 6000 | P20: 10000 | Q20: 16000 | R20: 28000 | S20: 110000 | T20: (2 sophonts - use 0.5 for a single, or change SR to single occupancy for Middle passage)
A21: Middle Passage | B21: 0 | C21: 0 | D21: =B21*INDEX($M$18:$S$28,4,MATCH(C21,$M$18:$S$18,0)) -> 0 | E21: =G21-B21 -> 0 | F21: of | G21: ='11-Staterooms'!C45+J21+H21 -> 0 | H21: =SUMPRODUCT('9a-Optional'!P27:P56,'9a-Optional'!U27:U56) -> 0 | J21: 0 | M21: 0 | N21: 6500 | O21: 10000 | P21: 14000 | Q21: 23000 | R21: 40000 | S21: 130000 | T21: 1 Middle Passenger
A22: Middle Double Occupancy | B22: 0 | C22: 0 | D22: =B22*INDEX($M$18:$S$28,5,MATCH(C22,$M$18:$S$18,0)) -> 0 | E22: =G20-B20-B22 -> 0 | F22: of | G22: =G20 -> 0 | H22: =SUMPRODUCT('9a-Optional'!P27:P56,'9a-Optional'!V27:V56) -> 0 | J22: 0 | M22: 0 | N22: =1.5*N21 -> 9750 | O22: =1.5*O21 -> 15000 | P22: =1.5*P21 -> 21000 | Q22: =1.5*Q21 -> 34500 | R22: =1.5*R21 -> 60000 | S22: =1.5*S21 -> 195000 | T22: Switch SR to single occupancy for correct fee if not occupied by 2 sophonts
A23: High Passage | B23: 0 | C23: 0 | D23: =B23*INDEX($M$18:$S$28,6,MATCH(C23,$M$18:$S$18,0)) -> 0 | E23: =G23-B23-B25 -> 0 | F23: of | G23: ='11-Staterooms'!C47+J23+J25+H23 -> 0 | H23: =SUMPRODUCT('9a-Optional'!P27:P56,'9a-Optional'!W27:W56) -> 0 | J23: 0 | M23: 0 | N23: 9000 | O23: 14000 | P23: 21000 | Q23: 34000 | R23: 60000 | S23: 210000 | T23: 1 High Passenger
A24: High Double Occupancy | B24: 0 | C24: 0 | D24: =B24*INDEX($M$18:$S$28,7,MATCH(C24,$M$18:$S$18,0)) -> 0 | E24: =G24-B24-B26 -> 0 | F24: of | G24: ='11-Staterooms'!C48+J24+J26+H24 -> 0 | H24: =SUMPRODUCT('9a-Optional'!P27:P56,'9a-Optional'!X27:X56) -> 0 | J24: 0 | M24: 0 | N24: =1.5*N23 -> 13500 | O24: =1.5*O23 -> 21000 | P24: =1.5*P23 -> 31500 | Q24: =1.5*Q23 -> 51000 | R24: =1.5*R23 -> 90000 | S24: =1.5*S23 -> 315000 | T24: Switch SR to single occupancy for correct fee if not occupied by 2 sophonts
A25: Standby Luxury Passage | B25: 0 | C25: 0 | D25: =B25*INDEX($M$18:$S$28,6,MATCH(C25,$M$18:$S$18,0)) -> 0 | E25: =E23 -> 0 | F25: of | G25: =G23 -> 0 | J25: 0 | M25: 0 | N25: 15000 | O25: 20000 | P25: 50000 | Q25: 60000 | R25: 90000 | S25: 320000 | T25: 1 Standby Luxury Passenger
A26: Standby Luxury Double Occupancy | B26: 0 | C26: 0 | D26: =B26*INDEX($M$18:$S$28,7,MATCH(C26,$M$18:$S$18,0)) -> 0 | E26: =E24 -> 0 | F26: of | G26: =G24 -> 0 | J26: 0 | M26: 0 | N26: =1.5*N25 -> 22500 | O26: =1.5*O25 -> 30000 | P26: =1.5*P25 -> 75000 | Q26: =1.5*Q25 -> 90000 | R26: =1.5*R25 -> 135000 | S26: =1.5*S25 -> 480000 | T26: Switch SR to single occupancy for correct fee if not occupied by 2 sophonts
A27: Luxury Passage | B27: 0 | C27: 0 | D27: =B27*INDEX($M$18:$S$28,10,MATCH(C27,$M$18:$S$18,0)) -> 0 | E27: =G27-B27 -> 0 | F27: of | G27: ='11-Staterooms'!C49+J27+H27 -> 0 | H27: =SUMPRODUCT('9a-Optional'!P27:P56,'9a-Optional'!Y27:Y56) -> 0 | J27: 0 | M27: 0 | N27: 36000 | O27: 48000 | P27: 70000 | Q27: 125000 | R27: 200000 | S27: 750000 | T27: 1 Luxury Passenger
A28: Luxury Double Occupancy | B28: 0 | C28: 0 | D28: =B28*INDEX($M$18:$S$28,11,MATCH(C28,$M$18:$S$18,0)) -> 0 | E28: =G28-B28 -> 0 | F28: of | G28: ='11-Staterooms'!C50+J28+H28 -> 0 | H28: =SUMPRODUCT('9a-Optional'!P27:P56,'9a-Optional'!Z27:Z56) -> 0 | J28: 0 | M28: 0 | N28: =1.5*N27 -> 54000 | O28: =1.5*O27 -> 72000 | P28: =1.5*P27 -> 105000 | Q28: =1.5*Q27 -> 187500 | R28: =1.5*R27 -> 300000 | S28: =1.5*S27 -> 1125000 | T28: Switch SR to single occupancy for correct fee if not occupied by 2 sophonts
A29: (SOL) VIP Suite | B29: 0 | C29: 0 | D29: =B29*INDEX($M$18:$S$31,12,MATCH(C29,$M$18:$S$18,0)) -> 0 | E29: =G29-B29 -> 0 | F29: of | G29: ='11-Staterooms'!C51+J29+H29 -> 0 | H29: =SUMPRODUCT('9a-Optional'!P27:P56,'9a-Optional'!AA27:AA56) -> 0 | J29: 0 | M29: 0 | N29: =9000*'11-Staterooms'!M51 -> 36000 | O29: =O23*'11-Staterooms'!M51 -> 56000 | P29: =P23*'11-Staterooms'!M51 -> 84000 | Q29: =Q23*'11-Staterooms'!M51 -> 136000 | R29: =R23*'11-Staterooms'!M51 -> 240000 | S29: =S23*'11-Staterooms'!M51 -> 840000
A30: (SOL) High Passage Block | B30: 0 | C30: 0 | D30: =B30*INDEX($M$18:$S$31,13,MATCH(C30,$M$18:$S$18,0)) -> 0 | E30: =G30-B30 -> 0 | F30: of | G30: ='11-Staterooms'!C52+J30+H30 -> 0 | H30: =SUMPRODUCT('9a-Optional'!P27:P56,'9a-Optional'!AB27:AB56) -> 0 | J30: 0 | M30: 0 | N30: =N23*'11-Staterooms'!$M$52 -> 54000 | O30: =O23*'11-Staterooms'!$M$52 -> 84000 | P30: =P23*'11-Staterooms'!$M$52 -> 126000 | Q30: =Q23*'11-Staterooms'!$M$52 -> 204000 | R30: =R23*'11-Staterooms'!$M$52 -> 360000 | S30: =S23*'11-Staterooms'!$M$52 -> 1260000
A31: (SOL) Steerage Block | B31: 0 | C31: 0 | D31: =B31*INDEX($M$18:$S$31,14,MATCH(C31,$M$18:$S$18,0)) -> 0 | E31: =G31-B31 -> 0 | F31: of | G31: ='11-Staterooms'!C53+J31+H31 -> 0 | H31: =SUMPRODUCT('9a-Optional'!P27:P56,'9a-Optional'!AC27:AC56) -> 0 | J31: 0 | M31: 0 | N31: =N20/2*'11-Staterooms'!$M$53 -> 48000 | O31: =O20/2*'11-Staterooms'!$M$53 -> 72000 | P31: =P20/2*'11-Staterooms'!$M$53 -> 120000 | Q31: =Q20/2*'11-Staterooms'!$M$53 -> 192000 | R31: =R20/2*'11-Staterooms'!$M$53 -> 336000 | S31: =S20/2*'11-Staterooms'!$M$53 -> 1320000 | T31: Use decimals for partially filled Steerage Block
M33: Parsecs
E34: Passengers | G34: Max Passengers | M34: 0 | N34: 1 | O34: 2 | P34: 3 | Q34: 4 | R34: 5 | S34: 6 | T34: Single rates shown. Additional passengers in a single non-basic room add 50%
A35: ='11-Staterooms'!$B$54 | B35: 0 | C35: 1 | D35: =IF(V52=$U$45,MAX(B35,E35)*INDEX(M34:S35,2,MATCH(C35,M34:S34,0)),IF(V52=$U$46,MAX(B35,E35)*INDEX(M34:S35,2,MATCH(C35,M34:S34,0)),IF(E35<B35,B35*INDEX(M34:S35,2,MATCH(C35,M34:S34,0)),(B35+0.5*(E35-B35))*INDEX(M34:S35,2,MATCH(C35,M34:S34,0))))) -> 0 | E35: 0 | G35: =('11-Staterooms'!C54+J35)*'11-Staterooms'!D54 -> 0 | H35: =SUMPRODUCT('9a-Optional'!P27:P56,'9a-Optional'!AD27:AD56) -> 0 | J35: 0 | M35: 0 | N35: =IF(U52>0,U52*INDEX(U44:AA49,MATCH(V52,U44:U49,0),2),INDEX(U37:AA42,MATCH(V52,U37:U42,0),2)) -> 0 | O35: =IF(U52>0,U52*INDEX(U44:AA49,MATCH(V52,U44:U49,0),3),INDEX(U37:AA42,MATCH(V52,U37:U42,0),3)) -> 0 | P35: =IF(U52>0,U52*INDEX(U44:AA49,MATCH(V52,U44:U49,0),4),INDEX(U37:AA42,MATCH(V52,U37:U42,0),4)) -> 0 | Q35: =IF(U52>0,U52*INDEX(U44:AA49,MATCH(V52,U44:U49,0),5),INDEX(U37:AA42,MATCH(V52,U37:U42,0),5)) -> 0 | R35: =IF(U52>0,U52*INDEX(U44:AA49,MATCH(V52,U44:U49,0),6),INDEX(U37:AA42,MATCH(V52,U37:U42,0),6)) -> 0 | S35: =IF(U52>0,U52*INDEX(U44:AA49,MATCH(V52,U44:U49,0),7),INDEX(U37:AA42,MATCH(V52,U37:U42,0),7)) -> 0
A36: ='11-Staterooms'!$B$55 | B36: 0 | C36: 1 | D36: =IF(V52=$U$45,MAX(B36,E36)*INDEX(M34:S36,3,MATCH(C36,M34:S34,0)),IF(V52=$U$46,MAX(B36,E36)*INDEX(M34:S36,3,MATCH(C36,M34:S34,0)),IF(E36<B36,B36*INDEX(M34:S36,3,MATCH(C36,M34:S34,0)),(B36+0.5*(E36-B35))*INDEX(M34:S36,3,MATCH(C35,M34:S34,0))))) -> 0 | E36: 0 | G36: =('11-Staterooms'!C55+J36)*'11-Staterooms'!D55 -> 0 | H36: =SUMPRODUCT('9a-Optional'!P27:P56,'9a-Optional'!AE27:AE56) -> 0 | J36: 0 | M36: 0 | N36: =IF(U53>0,U53*INDEX(U44:AA49,MATCH(V53,U44:U49,0),2),INDEX(U37:AA42,MATCH(V53,U37:U42,0),2)) -> 0 | O36: =IF(U53>0,U53*INDEX(U44:AA49,MATCH(V53,U44:U49,0),3),INDEX(U37:AA42,MATCH(V53,U37:U42,0),3)) -> 0 | P36: =IF(U53>0,U53*INDEX(U44:AA49,MATCH(V53,U44:U49,0),4),INDEX(U37:AA42,MATCH(V53,U37:U42,0),4)) -> 0 | Q36: =IF(U53>0,U53*INDEX(U44:AA49,MATCH(V53,U44:U49,0),5),INDEX(U37:AA42,MATCH(V53,U37:U42,0),5)) -> 0 | R36: =IF(U53>0,U53*INDEX(U44:AA49,MATCH(V53,U44:U49,0),6),INDEX(U37:AA42,MATCH(V53,U37:U42,0),6)) -> 0 | S36: =IF(U53>0,U53*INDEX(U44:AA49,MATCH(V53,U44:U49,0),7),INDEX(U37:AA42,MATCH(V53,U37:U42,0),7)) -> 0 | V36: 1 | W36: 2 | X36: 3 | Y36: 4 | Z36: 5 | AA36: 6
C37: Total Passenger Income: | D37: =SUM(D19:D36) -> 0 | M37: Luxury Passages based on Singularity pricing | U37: ="" | V37: 0 | W37: 0 | X37: 0 | Y37: 0 | Z37: 0 | AA37: 0
M38: Double occupancy adds 50% for second sophont | U38: Low | V38: 700 | W38: 1300 | X38: 2200 | Y38: 3900 | Z38: 7200 | AA38: 27000
J39: This column increases the | U39: Basic | V39: 4000 | W39: 6000 | X39: 10000 | Y39: 16000 | Z39: 28000 | AA39: 110000
C40: Total Income: | D40: =D16+D37 -> 0 | J40: Max for Cargo and Stateroom | U40: Middle | V40: 6500 | W40: 10000 | X40: 14000 | Y40: 23000 | Z40: 40000 | AA40: 130000
J41: Capacity, allowing for situations | U41: High | V41: 9000 | W41: 14000 | X41: 21000 | Y41: 34000 | Z41: 60000 | AA41: 210000
A42: Basic and Middle Double Occupancy share Capacity | J42: not yet handled by the sheet. | U42: Luxury | V42: 36000 | W42: 48000 | X42: 70000 | Y42: 125000 | Z42: 200000 | AA42: 750000
A43: Standby and High Passage share Capacity | V43: 1 | W43: 2 | X43: 3 | Y43: 4 | Z43: 5 | AA43: 6
A44: Standby means a Luxury Passenger in a High Stateroom | U44: ="" | V44: 0 | W44: 0 | X44: 0 | Y44: 0 | Z44: 0 | AA44: 0
U45: Low | V45: 1 | W45: 1.857 | X45: 3.143 | Y45: 5.571 | Z45: 10.286 | AA45: 38.571
D46: =IF(V52=$U$45,MAX(B35,E35)*INDEX(M34:S35,2,MATCH(C35,M34:S34,0)),IF(V52=$U$46,MAX(B35,E35)*INDEX(M34:S35,2,MATCH(C35,M34:S34,0)),IF(E35<B35,B35*INDEX(M34:S35,2,MATCH(C35,M34:S34,0)),(B35+0.5*(E35-B35))*INDEX(M34:S35,2,MATCH(C35,M34:S34,0))))) -> 0 | U46: Basic | V46: 1 | W46: 1.5 | X46: 2.5 | Y46: 4 | Z46: 7 | AA46: 27.5
U47: Middle | V47: 1 | W47: 1.538 | X47: 2.154 | Y47: 3.538 | Z47: 6.154 | AA47: 20
U48: High | V48: 1 | W48: 1.556 | X48: 2.333 | Y48: 3.778 | Z48: 6.667 | AA48: 23.333
U49: Luxury | V49: 1 | W49: 1.333 | X49: 1.944 | Y49: 3.472 | Z49: 5.556 | AA49: 20.833
U51: Base Price | V51: Type | X51: MaxSR
U52: =IF('11-Staterooms'!C54=0,0,INDEX('11-Staterooms'!B116:L119,MATCH(Profitability!A35,'11-Staterooms'!B116:B119,0),10)) -> 0 | V52: =IF('11-Staterooms'!C54=0,"",INDEX('11-Staterooms'!B116:L119,MATCH(Profitability!A35,'11-Staterooms'!B116:B119,0),11)) | X52: =J35+'11-Staterooms'!C54 -> 0
U53: =IF('11-Staterooms'!C55=0,0,INDEX('11-Staterooms'!B116:L119,MATCH(Profitability!A36,'11-Staterooms'!B116:B119,0),10)) -> 0 | V53: =IF('11-Staterooms'!C55=0,"",INDEX('11-Staterooms'!B116:L119,MATCH(Profitability!A36,'11-Staterooms'!B116:B119,0),11)) | X53: =J36+'11-Staterooms'!C55 -> 0

Sheet Ship Info
A1: =IF($F$5,"Ship's Class Name",IF($F$6,"Station's Class Name",IF($F$7,"Module's Class Name","Ship's Class Name"))) -> Ship's Class Name | G1: Cost | I1: Available Space | L1: Required Power | S1: No
A2: Class Role | E2: Tech Level: | F2: 12 | G2: =W30*SUM('1-Hull'!F4,'2-Drives'!F5,'3-Pwr Plant'!F5,'4-Fuel'!F5,'5-Bridge'!F5,'6-Comp'!F5,'7-Sensors'!F5,'8a-Weapons'!L5,'8b-Screens'!F5,'9a-Optional'!F5,'9b-Optional'!F5,'11-Staterooms'!F5,'12-Cargo'!F5)*IF(F3="No",1,0.9)+IF('10-Crew'!Q34="Yes",SUM('10-Crew'!S40:T49),0) -> 6177000 | I2: Unused | J2: Max | L2: Unused | M2: Max | S2: Yes
E3: Standard Design? | F3: Yes | G3: First in Class Cost | I3: =ROUND(J3-'1-Hull'!S63-'2-Drives'!S63-'3-Pwr Plant'!S41-'4-Fuel'!S24-'5-Bridge'!S20-'7-Sensors'!S14-'8a-Weapons'!N9-'8b-Screens'!S44-'9a-Optional'!AG29-'9b-Optional'!S10-'11-Staterooms'!S35-'12-Cargo'!S19,2)-IF('1-Hull'!C34="No",'1-Hull'!C32,0) -> 92.53 | J3: ='1-Hull'!I6 -> 100 | L3: =M3-'2-Drives'!S66-'7-Sensors'!S17-'8a-Weapons'!Q9-'8b-Screens'!S47-'1-Hull'!T63-'9a-Optional'!AG32-'9b-Optional'!S13-'11-Staterooms'!S39-'12-Cargo'!S22-'4-Fuel'!S27-'6-Comp'!S101 -> 0 | M3: ='3-Pwr Plant'!L6 -> 20
A4: =IF($F$5,"Ship's Name",IF($F$6,"Station's Name",IF($F$7,"Base Ship's Class Name","Ship's Name"))) -> Ship's Name | F4: =IF(E6="Pod",1,0) -> 0 | G4: =W30*SUM('1-Hull'!F4,'2-Drives'!F5,'3-Pwr Plant'!F5,'4-Fuel'!F5,'5-Bridge'!F5,'6-Comp'!F5,'7-Sensors'!F5,'8a-Weapons'!L5,'8b-Screens'!F5,'9a-Optional'!F5,'9b-Optional'!F5,'11-Staterooms'!F5,'12-Cargo'!F5)*1.01+IF('10-Crew'!Q34="Yes",SUM('10-Crew'!S40:T49),0) -> 6931966.7 | L4: EMER: | M4: ='3-Pwr Plant'!L15
B5: Base Class Usable Hull in Dtons (total with modules): | C5: 1500 | E5: Design is: | F5: =IF(E6="Ship",1,0) -> 1 | L5: BATTERY: | M5: ='3-Pwr Plant'!L18 -> 0 | V5: <<<Edge | X5: Edge>>>
B6: Hardpoints/Firmpoints on Base Class Without Any Modules: | C6: 6 | E6: Ship | F6: =IF(E6="Station",1,0) -> 0 | H6: ="* Is module a fully spaceworthy pod?" -> * Is module a fully spaceworthy pod? | I6: No
A7: Narrative Description | F7: =IF(E6="Module",1,0) -> 0 | G7: Overview
E8: Tab | G8: Cost | H8: Tons | I8: Power | K8: Station | L8: Station Quality Chart
E9: Hull | G9: ='1-Hull'!F4 -> 5000000 | H9: ='1-Hull'!S63 -> 0 | I9: ='1-Hull'!T63 -> 20 | K9: Class
E10: Drives | G10: ='2-Drives'!F5 -> 0 | H10: ='2-Drives'!S63 -> 0 | I10: ='2-Drives'!S66 -> 0 | K10: =IF(K21=5,"*A*","A") -> A
E11: Power Plant | G11: ='3-Pwr Plant'!F5 -> 1333333.3 | H11: ='3-Pwr Plant'!S41 -> 1.3333333 | I11: - | K11: =IF(K21=4,"*B*","B") -> B
E12: Fuel | G12: ='4-Fuel'!F5 -> 0 | H12: ='4-Fuel'!S24 -> 0.13333333 | I12: ='4-Fuel'!S27 -> 0 | K12: =IF(K21=3,"*C*","C") -> C
E13: Bridge | G13: ='5-Bridge'!F5 -> 500000 | H13: ='5-Bridge'!S20 -> 6 | I13: 0 | K13: =IF(K21=2,"*D*","D") -> D
E14: Computer | G14: ='6-Comp'!F5 -> 30000 | H14: 0 | I14: 0 | K14: =IF(K21=1,"*E*","E") -> *E*
E15: Sensors | G15: ='7-Sensors'!F5 -> 0 | H15: ='7-Sensors'!S14 -> 0 | I15: ='7-Sensors'!S17 -> 0 | L15: Sensors | M15: Docking | N15: Refined Fuel/Day | O15: Commercial Zones | P15: Residential Zones | Q15: Shipyard Capacity
E16: Weapons | G16: ='8a-Weapons'!L5 -> 0 | H16: ='8a-Weapons'!N9 -> 0 | I16: ='8a-Weapons'!Q9 -> 0
E17: Screen | G17: ='8b-Screens'!F5 -> 0 | H17: ='8b-Screens'!S44 -> 0 | I17: ='8b-Screens'!S47 -> 0
E18: Optional | G18: ='9a-Optional'!F5+'9b-Optional'!F5 -> 0 | H18: ='9a-Optional'!AG29+'9b-Optional'!S10 -> 0 | I18: ='9a-Optional'!AG32+'9b-Optional'!S13 -> 0
E19: Staterooms | G19: ='11-Staterooms'!F5 -> 0 | H19: ='11-Staterooms'!S35 -> 0 | I19: ='11-Staterooms'!S39 -> 0
E20: Cargo | G20: ='12-Cargo'!F5 -> 0 | H20: ='12-Cargo'!S19 -> 0 | I20: ='12-Cargo'!S22 -> 0
K21: =MIN(L21:Q21) -> 1 | L21: ='7-Sensors'!W41 -> 2 | M21: ='9b-Optional'!T180 -> 1 | N21: ='9b-Optional'!T187 -> 3 | O21: ='9b-Optional'!T177 -> 1 | P21: ='9b-Optional'!T173 -> 2 | Q21: ='9b-Optional'!T194 -> 2
A22: Ship's Expenses | E22: Automation Level: | G22: Standard Automation | V22: New | W22: 1 | X22: 0
G23: Cost Multiplier | H23: Crew Multiplier | P23: Construction Time: | Q23: =TEXT(ROUNDUP((G2/1000000)*(1-(Q25/100))*(1-IF(Tech_Level<12,0,IF(Tech_Level>16,0.5,(Tech_Level-11)*0.1))),0),"#,###")&" Days" -> 6 Days | V23: ="6-10" -> 6-10 | W23: 0.95 | X23: 1
A24: Mortgage: | B24: =IF(C31="Yes",0,IF(S67="No",G2/240,O70/240)) -> 25737.5 | E24: Crew-Intensive | G24: 0.6 | H24: 2 | I24: DM-4 for all shipboard tasks | V24: ="11-15" -> 11-15 | W24: 0.9 | X24: 2
A25: Maintenance Cost | B25: =IF('10-Crew'!Q34="No",ROUND(G2/W30/12/1000,0),ROUND((G2-SUM('10-Crew'!S40:T49))/W30/12/1000,0))+SUM('10-Crew'!AA40:AA49) -> 515 | E25: Low Automation | G25: 0.8 | H25: 1.4 | I25: DM-1 for all shipboard tasks after 1 week in space | P25: Modular Construction %: | Q25: 0 | V25: ="16-25" -> 16-25 | W25: 0.85 | X25: 3
A26: Life Support: | B26: ='11-Staterooms'!F7 -> 0 | E26: Standard Automation | G26: 1 | H26: 1 | I26: ="" | V26: ="26-50" -> 26-50 | W26: 0.8 | X26: 4
A27: Crew Salaries: | B27: ='10-Crew'!G32 -> 19000 | E27: Enhanced Automation | G27: 1.25 | H27: 0.9 | I27: ="" | O27: Construction Time rounded up to whole days | V27: ="51-100" -> 51-100 | W27: 0.75 | X27: 6
A28: Fuel: | B28: =Profitability!B7 -> 0 | E28: Advanced Automation | G28: 1.5 | H28: 0.75 | I28: DM+1 on all shipboard tasks | V28: ="101-250" -> 101-250 | W28: 0.7 | X28: 8
A29: Total Expenses: | B29: =SUM(B24:B28) -> 45252.5 | E29: High Automation | G29: 2 | H29: 0.6 | I29: DM+2 on all shipboard tasks | O29: Outdated/Used Ships | R29: =IF(W30=1,"",(1-W30)*100&"% Discount") | V29: ="251+" -> 251+ | W29: 0.6 | X29: 10
V30: Used: | W30: =INDEX(V22:X29,MATCH(P31,V22:V29,0),2) -> 1 | X30: =INDEX(V22:X29,MATCH(P31,V22:V29,0),3) -> 0
B31: Has the mortgage on this ship been completely paid off? | C31: No | E31: Active labels: | G31: =INDEX(E24:I29,MATCH(G22,E24:E29,0),3) -> 1 | H31: =INDEX(E24:I29,MATCH(G22,E24:E29,0),4) -> 1 | I31: =INDEX(E24:I29,MATCH(G22,E24:E29,0),5) | O31: Age: | P31: New | Q31: =IF(P31="New","","Years Old") | V31: =""
O32: Quirks | V32: Black-listed: DM-1 Broker
B33: Toggle for Section Shading in the Summary Tab is: | C33: On | E33: NOTE: Automation is an optional rule from the Traveller Companion. Standard Automation is HG2022 Compliant | V33: Severely Damaged: -1 Hull
V34: Leaky Reactor Core: Jump on 12, 2Dx20 Rads
B35: Toggle for Unused Space Notification in Summary Tab: | C35: Off | E35: * Making a module fully spaceworthy lets you bypass installing a bridge while having a pod that can survive space on its own. | V35: Well Maintained: 50% Maintenance Costs
B36: Minimum Notification Setpoint: | C36: 0.01 | E36: A Pod can have its own power plant. A Pod can have a bridge or control center other than an SCC, but not under the Main Bridge. | V36: Upgraded Sensors
E37: Instead, these are selected in the Auxilliary Control Room Menu. | V37: Luxurious: DM+1 Steward
A38: =LEFT(A8,C38)&E38 | C38: =IF(MID(A8,D38,1)=" ",D38,IF(MID(A8,D38-1,1)=" ",D38-1,IF(MID(A8,D38-2,1)=" ",D38-2,IF(MID(A8,D38-3,1)=" ",D38-3,IF(MID(A8,D38-4,1)=" ",D38-4,IF(MID(A8,D38-5,1)=" ",D38-5,IF(MID(A8,D38-6,1)=" ",D38-6,IF(MID(A8,D38-7,1)=" ",D38-7,IF(MID(A8,D38-8,1)=" ",D38-8,IF(MID(A8,D38-9,1)=" ",D38-9,IF(MID(A8,D38-10,1)=" ",D38-10,D38-1))))))))))) -> 57 | D38: 58 | E38: =IF(D38>LEN($A$8),"",IF(RIGHT(LEFT($A$8,C38),1)=" ","","-"))
A39: =MID($A$8,C38+1,C39-C38)&E39 | C39: =IF(MID($A$8,D39,1)=" ",D39,IF(MID($A$8,D39-1,1)=" ",D39-1,IF(MID($A$8,D39-2,1)=" ",D39-2,IF(MID($A$8,D39-3,1)=" ",D39-3,IF(MID($A$8,D39-4,1)=" ",D39-4,IF(MID($A$8,D39-5,1)=" ",D39-5,IF(MID($A$8,D39-6,1)=" ",D39-6,IF(MID($A$8,D39-7,1)=" ",D39-7,IF(MID($A$8,D39-8,1)=" ",D39-8,IF(MID($A$8,D39-9,1)=" ",D39-9,IF(MID($A$8,D39-10,1)=" ",D39-10,D39-1))))))))))) -> 115 | D39: =$D$38+C38+1 -> 116 | E39: =IF(D39>LEN($A$8),"",IF(RIGHT(LEFT($A$8,C39),1)=" ","","-"))
A40: =MID($A$8,C39+1,C40-C39)&E40 | C40: =IF(MID($A$8,D40,1)=" ",D40,IF(MID($A$8,D40-1,1)=" ",D40-1,IF(MID($A$8,D40-2,1)=" ",D40-2,IF(MID($A$8,D40-3,1)=" ",D40-3,IF(MID($A$8,D40-4,1)=" ",D40-4,IF(MID($A$8,D40-5,1)=" ",D40-5,IF(MID($A$8,D40-6,1)=" ",D40-6,IF(MID($A$8,D40-7,1)=" ",D40-7,IF(MID($A$8,D40-8,1)=" ",D40-8,IF(MID($A$8,D40-9,1)=" ",D40-9,IF(MID($A$8,D40-10,1)=" ",D40-10,D40-1))))))))))) -> 173 | D40: =$D$38+C39+1 -> 174 | E40: =IF(D40>LEN($A$8),"",IF(RIGHT(LEFT($A$8,C40),1)=" ","","-"))
A41: =MID($A$8,C40+1,C41-C40)&E41 | C41: =IF(MID($A$8,D41,1)=" ",D41,IF(MID($A$8,D41-1,1)=" ",D41-1,IF(MID($A$8,D41-2,1)=" ",D41-2,IF(MID($A$8,D41-3,1)=" ",D41-3,IF(MID($A$8,D41-4,1)=" ",D41-4,IF(MID($A$8,D41-5,1)=" ",D41-5,IF(MID($A$8,D41-6,1)=" ",D41-6,IF(MID($A$8,D41-7,1)=" ",D41-7,IF(MID($A$8,D41-8,1)=" ",D41-8,IF(MID($A$8,D41-9,1)=" ",D41-9,IF(MID($A$8,D41-10,1)=" ",D41-10,D41-1))))))))))) -> 231 | D41: =$D$38+C40+1 -> 232 | E41: =IF(D41>LEN($A$8),"",IF(RIGHT(LEFT($A$8,C41),1)=" ","","-"))
A42: =MID($A$8,C41+1,C42-C41)&E42 | C42: =IF(MID($A$8,D42,1)=" ",D42,IF(MID($A$8,D42-1,1)=" ",D42-1,IF(MID($A$8,D42-2,1)=" ",D42-2,IF(MID($A$8,D42-3,1)=" ",D42-3,IF(MID($A$8,D42-4,1)=" ",D42-4,IF(MID($A$8,D42-5,1)=" ",D42-5,IF(MID($A$8,D42-6,1)=" ",D42-6,IF(MID($A$8,D42-7,1)=" ",D42-7,IF(MID($A$8,D42-8,1)=" ",D42-8,IF(MID($A$8,D42-9,1)=" ",D42-9,IF(MID($A$8,D42-10,1)=" ",D42-10,D42-1))))))))))) -> 289 | D42: =$D$38+C41+1 -> 290 | E42: =IF(D42>LEN($A$8),"",IF(RIGHT(LEFT($A$8,C42),1)=" ","","-"))
A43: =MID($A$8,C42+1,C43-C42)&E43 | C43: =IF(MID($A$8,D43,1)=" ",D43,IF(MID($A$8,D43-1,1)=" ",D43-1,IF(MID($A$8,D43-2,1)=" ",D43-2,IF(MID($A$8,D43-3,1)=" ",D43-3,IF(MID($A$8,D43-4,1)=" ",D43-4,IF(MID($A$8,D43-5,1)=" ",D43-5,IF(MID($A$8,D43-6,1)=" ",D43-6,IF(MID($A$8,D43-7,1)=" ",D43-7,IF(MID($A$8,D43-8,1)=" ",D43-8,IF(MID($A$8,D43-9,1)=" ",D43-9,IF(MID($A$8,D43-10,1)=" ",D43-10,D43-1))))))))))) -> 347 | D43: =$D$38+C42+1 -> 348 | E43: =IF(D43>LEN($A$8),"",IF(RIGHT(LEFT($A$8,C43),1)=" ","","-"))
A44: =MID($A$8,C43+1,C44-C43)&E44 | C44: =IF(MID($A$8,D44,1)=" ",D44,IF(MID($A$8,D44-1,1)=" ",D44-1,IF(MID($A$8,D44-2,1)=" ",D44-2,IF(MID($A$8,D44-3,1)=" ",D44-3,IF(MID($A$8,D44-4,1)=" ",D44-4,IF(MID($A$8,D44-5,1)=" ",D44-5,IF(MID($A$8,D44-6,1)=" ",D44-6,IF(MID($A$8,D44-7,1)=" ",D44-7,IF(MID($A$8,D44-8,1)=" ",D44-8,IF(MID($A$8,D44-9,1)=" ",D44-9,IF(MID($A$8,D44-10,1)=" ",D44-10,D44-1))))))))))) -> 405 | D44: =$D$38+C43+1 -> 406 | E44: =IF(D44>LEN($A$8),"",IF(RIGHT(LEFT($A$8,C44),1)=" ","","-"))
A45: =MID($A$8,C44+1,C45-C44)&E45 | C45: =IF(MID($A$8,D45,1)=" ",D45,IF(MID($A$8,D45-1,1)=" ",D45-1,IF(MID($A$8,D45-2,1)=" ",D45-2,IF(MID($A$8,D45-3,1)=" ",D45-3,IF(MID($A$8,D45-4,1)=" ",D45-4,IF(MID($A$8,D45-5,1)=" ",D45-5,IF(MID($A$8,D45-6,1)=" ",D45-6,IF(MID($A$8,D45-7,1)=" ",D45-7,IF(MID($A$8,D45-8,1)=" ",D45-8,IF(MID($A$8,D45-9,1)=" ",D45-9,IF(MID($A$8,D45-10,1)=" ",D45-10,D45-1))))))))))) -> 463 | D45: =$D$38+C44+1 -> 464 | E45: =IF(D45>LEN($A$8),"",IF(RIGHT(LEFT($A$8,C45),1)=" ","","-"))
A46: =MID($A$8,C45+1,C46-C45)&E46 | C46: =IF(MID($A$8,D46,1)=" ",D46,IF(MID($A$8,D46-1,1)=" ",D46-1,IF(MID($A$8,D46-2,1)=" ",D46-2,IF(MID($A$8,D46-3,1)=" ",D46-3,IF(MID($A$8,D46-4,1)=" ",D46-4,IF(MID($A$8,D46-5,1)=" ",D46-5,IF(MID($A$8,D46-6,1)=" ",D46-6,IF(MID($A$8,D46-7,1)=" ",D46-7,IF(MID($A$8,D46-8,1)=" ",D46-8,IF(MID($A$8,D46-9,1)=" ",D46-9,IF(MID($A$8,D46-10,1)=" ",D46-10,D46-1))))))))))) -> 521 | D46: =$D$38+C45+1 -> 522 | E46: =IF(D46>LEN($A$8),"",IF(RIGHT(LEFT($A$8,C46),1)=" ","","-"))
A47: =MID($A$8,C46+1,C47-C46)&E47 | C47: =IF(MID($A$8,D47,1)=" ",D47,IF(MID($A$8,D47-1,1)=" ",D47-1,IF(MID($A$8,D47-2,1)=" ",D47-2,IF(MID($A$8,D47-3,1)=" ",D47-3,IF(MID($A$8,D47-4,1)=" ",D47-4,IF(MID($A$8,D47-5,1)=" ",D47-5,IF(MID($A$8,D47-6,1)=" ",D47-6,IF(MID($A$8,D47-7,1)=" ",D47-7,IF(MID($A$8,D47-8,1)=" ",D47-8,IF(MID($A$8,D47-9,1)=" ",D47-9,IF(MID($A$8,D47-10,1)=" ",D47-10,D47-1))))))))))) -> 579 | D47: =$D$38+C46+1 -> 580 | E47: =IF(D47>LEN($A$8),"",IF(RIGHT(LEFT($A$8,C47),1)=" ","","-"))
A48: =MID($A$8,C47+1,C48-C47)&E48 | C48: =IF(MID($A$8,D48,1)=" ",D48,IF(MID($A$8,D48-1,1)=" ",D48-1,IF(MID($A$8,D48-2,1)=" ",D48-2,IF(MID($A$8,D48-3,1)=" ",D48-3,IF(MID($A$8,D48-4,1)=" ",D48-4,IF(MID($A$8,D48-5,1)=" ",D48-5,IF(MID($A$8,D48-6,1)=" ",D48-6,IF(MID($A$8,D48-7,1)=" ",D48-7,IF(MID($A$8,D48-8,1)=" ",D48-8,IF(MID($A$8,D48-9,1)=" ",D48-9,IF(MID($A$8,D48-10,1)=" ",D48-10,D48-1))))))))))) -> 637 | D48: =$D$38+C47+1 -> 638 | E48: =IF(D48>LEN($A$8),"",IF(RIGHT(LEFT($A$8,C48),1)=" ","","-"))
A49: =MID($A$8,C48+1,C49-C48)&E49 | C49: =IF(MID($A$8,D49,1)=" ",D49,IF(MID($A$8,D49-1,1)=" ",D49-1,IF(MID($A$8,D49-2,1)=" ",D49-2,IF(MID($A$8,D49-3,1)=" ",D49-3,IF(MID($A$8,D49-4,1)=" ",D49-4,IF(MID($A$8,D49-5,1)=" ",D49-5,IF(MID($A$8,D49-6,1)=" ",D49-6,IF(MID($A$8,D49-7,1)=" ",D49-7,IF(MID($A$8,D49-8,1)=" ",D49-8,IF(MID($A$8,D49-9,1)=" ",D49-9,IF(MID($A$8,D49-10,1)=" ",D49-10,D49-1))))))))))) -> 695 | D49: =$D$38+C48+1 -> 696 | E49: =IF(D49>LEN($A$8),"",IF(RIGHT(LEFT($A$8,C49),1)=" ","","-"))
A50: =MID($A$8,C49+1,C50-C49)&E50 | C50: =IF(MID($A$8,D50,1)=" ",D50,IF(MID($A$8,D50-1,1)=" ",D50-1,IF(MID($A$8,D50-2,1)=" ",D50-2,IF(MID($A$8,D50-3,1)=" ",D50-3,IF(MID($A$8,D50-4,1)=" ",D50-4,IF(MID($A$8,D50-5,1)=" ",D50-5,IF(MID($A$8,D50-6,1)=" ",D50-6,IF(MID($A$8,D50-7,1)=" ",D50-7,IF(MID($A$8,D50-8,1)=" ",D50-8,IF(MID($A$8,D50-9,1)=" ",D50-9,IF(MID($A$8,D50-10,1)=" ",D50-10,D50-1))))))))))) -> 753 | D50: =$D$38+C49+1 -> 754 | E50: =IF(D50>LEN($A$8),"",IF(RIGHT(LEFT($A$8,C50),1)=" ","","-"))
... A57: =MID($A$8,C56+1,C57-C56)&E57 | C57: =IF(MID($A$8,D57,1)=" ",D57,IF(MID($A$8,D57-1,1)=" ",D57-1,IF(MID($A$8,D57-2,1)=" ",D57-2,IF(MID($A$8,D57-3,1)=" ",D57-3,IF(MID($A$8,D57-4,1)=" ",D57-4,IF(MID($A$8,D57-5,1)=" ",D57-5,IF(MID($A$8,D57-6,1)=" ",D57-6,IF(MID($A$8,D57-7,1)=" ",D57-7,IF(MID($A$8,D57-8,1)=" ",D57-8,IF(MID($A$8,D57-9,1)=" ",D57-9,IF(MID($A$8,D57-10,1)=" ",D57-10,D57-1))))))))))) -> 1159 | D57: =$D$38+C56+1 -> 1160 | E57: =IF(D57>LEN($A$8),"",IF(RIGHT(LEFT($A$8,C57),1)=" ","","-"))
B58: Show Errors on Summary? | C58: Yes | V58: Concealed Compartments
V59: Extra Turret if possible
B60: Show Grid Lines on Summary? | C60: Yes | V60: Library computer erroneous
V61: Tainted Cargo Bay
V62: Notorious Battle: Enemies
J63: Enable User Defined Quirks? | K63: No | N63: User Defined 1: | O63: ="" | V63: Disturbing Psionic Echoes
N64: User Defined 2: | O64: ="" | V64: Damaged Sensors: DM-1 Electronics(Sensors)
V65: DM-1 to all Repair attempts
O66: Used Ship Trade-Ins/Negotiations | V66: Double Maintenance Costs
O67: Override Purchase Price for Mortgage? | S67: No | V67: Severely Damaged: -10% Hull
V68: Damaged Thrusters: DM-1 Pilot
P69: Revised Purchase Price | V69: Famous Ship: Good Reputation
O70: 0 | V70: Served with Distinction: Good Navy rep
V71: Library contains secret/unusual information
V72: Upgraded Computer
V73: Add a weapon up to MCr2

Sheet 1-Hull
A1: ='Ship Info'!A1 -> Ship's Class Name | B1: ='Ship Info'!B1 -> 0 | F1: Cost | S1: Hull Configuration | T1: Streamlined? | U1: Hull Points | V1: Cost | W1: Space | X1: Armor | Y1: ArmSpc | Z1: solar | AA1: Description | AE1: Edge>>>
A2: Class Role | B2: ='Ship Info'!B2 -> 0 | D2: Tech Level: | E2: ='Ship Info'!F2 -> 12 | F2: ='Ship Info'!G2 -> 6177000 | S2: Buffered Planetoid | T2: Unstreamlined | U2: 1.5 | V2: 0.08 | W2: 0.65 | X2: 4 | Y2: 1 | Z2: 0 | AA2: 5 | AC2: value | AD2: Test
B3: ='Ship Info'!G22&" - Costs x "&'Ship Info'!G31 -> Standard Automation - Costs x 1 | F3: Page Totals | H3: =S63 -> 0 | K3: =T63 -> 20 | S3: Close Structure | T3: Partial | U3: 1 | V3: 0.8 | W3: 1 | X3: =IF($A$21=$S$42,4,0) -> 0 | Y3: 1.5 | Z3: 0.5 | AA3: 4 | AB3: TL | AC3: =E10 -> 0 | AD3: =IF(AC3>E2,1,0) -> 0
A4: Tonnage | B4: 100 | F4: =SUM(F6:F50) -> 5000000 | H4: Available Space | K4: Required Power | S4: Dispersed Structure | T4: Unstreamlined | U4: 0.9 | V4: 0.5 | W4: 1 | X4: 0 | Y4: 2 | Z4: 0.5 | AA4: 2 | AB4: Max Armor | AC4: =D10 -> 0 | AD4: =IF(AC4>INDEX(S18:W22,MATCH(B10,S18:S22,0),5),1,0) -> 0
C5: Artificial Gravity (Standard)? | D5: Yes | H5: Unused | I5: Max | K5: Unused | L5: Max | S5: Planetoid | T5: Unstreamlined | U5: 1.25 | V5: 0.08 | W5: 0.8 | X5: 2 | Y5: 1 | Z5: 0 | AA5: 5 | AB5: TL 2ry | AC5: =E40 -> 0
A6: Hull Configuration | B6: Standard | C6: Hull Type | D6: Standard Hull | F6: =IF(AND(D5=D37,B6=D38,D6=D39),B4*IF(AND('Ship Info'!F7=1,'Ship Info'!I6="No"),25000,Y14*(INDEX(S2:Y8,MATCH(B6,S2:S8,0),4))*(INDEX(S13:U15,MATCH(D6,S13:S15,0),3))),(B4-C36)*IF(AND('Ship Info'!F7=1,'Ship Info'!I6="No"),25000,Y14*(INDEX(S2:Y8,MATCH(B6,S2:S8,0),4))*(INDEX(S13:U15,MATCH(D6,S13:S15,0),3)))+C36*IF(AND('Ship Info'!F7=1,'Ship Info'!I6="No"),25000,Z14*(INDEX(S2:Y8,MATCH(D38,S2:S8,0),4))*(INDEX(S13:U15,MATCH(D39,S13:S15,0),3))))*'Ship Info'!G31 -> 5000000 | H6: ='Ship Info'!I3 -> 92.53 | I6: =IF('Ship Info'!F7,Tonnage,Tonnage*INDEX(S2:W11,MATCH(B6,S2:S11,0),5)) -> 100 | K6: ='Ship Info'!L3 -> 0 | L6: ='3-Pwr Plant'!L6 -> 20 | S6: Sphere | T6: Partial | U6: 1 | V6: 1.1 | W6: 1 | X6: =IF($A$21=$S$42,4,0) -> 0 | Y6: 0.9 | Z6: 1 | AA6: 3 | AB6: Max Armor 2ry | AC6: =D41 -> 0
A7: Hull Description | C7: Hull Points | D7: =IF(C36=0,INT(B4/IF(B4>99999.9,1.5,IF(B4>24999.9,2,2.5))*INDEX(S2:U8,MATCH(B6,S2:S8,0),3)*INDEX(S13:T15,MATCH(D6,S13:S15,0),2)),INT((B4-C36)/IF((B4-C36)>99999.9,1.5,IF((B4-C36)>24999.9,2,2.5))*INDEX(S2:U8,MATCH(B6,S2:S8,0),3)*INDEX(S13:T15,MATCH(D6,S13:S15,0),2))+INT(C36/IF(B4>99999.9,1.5,IF(C36>24999.9,2,2.5))*INDEX(S2:U8,MATCH(D38,S2:S8,0),3)*INDEX(S13:T15,MATCH(D39,S13:S15,0),2))) -> 40 | E7: TL | S7: Standard | T7: Partial | U7: 1 | V7: 1 | W7: 1 | X7: =IF($A$21=$S$42,4,0) -> 0 | Y7: 1 | Z7: 1 | AA7: 4 | AB7: Error | AD7: =SUM(AD3:AD6) -> 0
A8: Streamlined? | B8: =INDEX(S2:T11,MATCH(B6,S2:S11,0),2) -> Partial | S8: Streamlined | T8: Streamlined | U8: 1 | V8: 1.2 | W8: 1 | X8: =IF($A$21=$S$42,4,0) -> 0 | Y8: 1.2 | Z8: 0 | AA8: 1
B9: Military Hull: | C9: No | F9: =IF(C9=W13,0,0.25*B4*Y14)*'Ship Info'!G31 -> 0 | H9: Item Tons
A10: Armor Type | B10: No Armor | C10: Armor Value | D10: 0 | E10: =INDEX(S18:V22,MATCH(B10,S18:S22,0),4) -> 0 | F10: =(INDEX(S18:U22,MATCH(B10,S18:S22,0),3)*AB17+INDEX(S18:U22,MATCH(D40,S18:S22,0),3)*AB18)*'Ship Info'!G31 -> 0 | H10: =INDEX(S18:T22,MATCH(B10,S18:S22,0),2)*(B4-C36)*(D11-Z17)*INDEX(S2:Y8,MATCH(B6,S2:S8,0),7)*FtrArmr+IF(C36=0,0,INDEX(S18:T22,MATCH(D40,S18:S22,0),2)*(C36)*(G41-Z18)*INDEX(S2:Y8,MATCH(D38,S2:S8,0),7)*AA18) -> 0
B11: =IF(E2>15,"Molecular Bonded available",IF(E2>13,"Bonded Superdense available",IF(E2>9,"Crystaliron Available",IF(E2>6,"Titanium Steel available","No Armor available")))) -> Crystaliron Available | C11: Armor Total: | D11: =IF(D10=0,Z17,IF(AC4+Z17>Y17,Y17,AC4+Z17)) -> 0 | J11: Basic Ops: | K11: =IF('Ship Info'!E6="Module",0,0.2*B4*T16) -> 20
C12: ="Max Armor = "&Y17 -> Max Armor = 0 | S12: Hull Type | T12: Hull Points | U12: Cost | Z12: =INDEX(S2:Z8,MATCH(B6,S2:S8,0),8) -> 1 | AA12: < Check hull config for solar
A13: Hull Options (Total Hull) | D13: Breakaway Secondary Hull Only | S13: Light Hull | T13: 0.9 | U13: 0.75 | W13: No | X13: 25000 | Z13: 2ry | AC13: =IF(AND(L33="No",U77=1),S15,S13) -> Light Hull
A14: None | B14: =IF(AND(A14=S25,D14=S26),"2ry Hull: "&INDEX($S$25:$AC$26,MATCH(D14,$S$25:$S$26,0),9),INDEX($S$25:$AC$26,MATCH(A14,$S$25:$S$26,0),9)) -> Aerofins | D14: None | E14: =MAX(INDEX($S$25:$AC$26,MATCH(A14,$S$25:$S$26,0),6),INDEX($S$25:$AC$26,MATCH(D14,$S$25:$S$26,0),6)) -> 0 | F14: =MAX(INDEX($S$25:$AC$26,MATCH(A14,$S$25:$S$26,0),3),INDEX($S$25:$AC$26,MATCH(D14,$S$25:$S$26,0),5))*'Ship Info'!G31 -> 0 | H14: =MAX(INDEX($S$25:$AC$26,MATCH(A14,$S$25:$S$26,0),2),INDEX($S$25:$AC$26,MATCH(D14,$S$25:$S$26,0),4)) -> 0 | K14: =INDEX($S$25:$AC$26,MATCH(A14,$S$25:$S$26,0),7) -> 0 | S14: Reinforced Hull | T14: 1.1 | U14: 1.5 | W14: Yes | X14: 50000 | Y14: =INDEX(W13:X14,MATCH(D5,W13:W14,0),2) -> 50000 | Z14: =INDEX(W13:X14,MATCH(D37,W13:W14,0),2) -> 50000 | AC14: =IF(AND(L33="No",U77=1),S15,S14) -> Reinforced Hull
A15: None | B15: =IF(AND(A15=S27,D15=S28),"2ry Hull: "&INDEX($S$27:$AC$28,MATCH(D15,$S$27:$S$28,0),9),INDEX($S$27:$AC$28,MATCH(A15,$S$27:$S$28,0),9)) -> Reflec | D15: None | E15: =MAX(INDEX($S$27:$AC$28,MATCH(A15,$S$27:$S$28,0),6),INDEX($S$27:$AC$28,MATCH(D15,$S$27:$S$28,0),6)) -> 0 | F15: =MAX(INDEX($S$27:$AC$28,MATCH(A15,$S$27:$S$28,0),3),INDEX($S$27:$AC$28,MATCH(D15,$S$27:$S$28,0),5))*'Ship Info'!G31 -> 0 | H15: =MAX(INDEX($S$27:$AC$28,MATCH(A15,$S$27:$S$28,0),2),INDEX($S$27:$AC$28,MATCH(D15,$S$27:$S$28,0),4)) -> 0 | K15: =INDEX($S$27:$AC$28,MATCH(A15,$S$27:$S$28,0),7) -> 0 | S15: Standard Hull | T15: 1 | U15: 1 | Z15: CfgArmr | AA15: FtrArmr | AC15: =S15 -> Standard Hull
A16: None | B16: =IF(AND(A16=S29,D16<>S29),"2ry Hull: "&INDEX($S$29:$AC$30,MATCH(D16,$S$29:$S$30,0),9),INDEX($S$29:$AC$30,MATCH(A16,$S$29:$S$30,0),9)) -> Heat Shielding | D16: None | E16: =MAX(INDEX($S$29:$AC$30,MATCH(A16,$S$29:$S$30,0),6),INDEX($S$29:$AC$30,MATCH(D16,$S$29:$S$30,0),6)) -> 0 | F16: =MAX(INDEX($S$29:$AC$30,MATCH(A16,$S$29:$S$30,0),3),INDEX($S$29:$AC$30,MATCH(D16,$S$29:$S$30,0),5))*'Ship Info'!G31 -> 0 | H16: =MAX(INDEX($S$29:$AC$30,MATCH(A16,$S$29:$S$30,0),2),INDEX($S$29:$AC$30,MATCH(D16,$S$29:$S$30,0),4)) -> 0 | K16: =INDEX($S$29:$AC$30,MATCH(A16,$S$29:$S$30,0),7) -> 0 | S16: Gravity | T16: =IF(D5=W14,1,0.5) -> 1
A17: None | B17: =IF(AND(A17=S48,D17<>S48),"2ry Hull: "&INDEX($S$48:$AC$49,MATCH(D17,$S$48:$S$49,0),9),INDEX($S$48:$AC$49,MATCH(A17,$S$48:$S$49,0),9)) -> Hostile Environment Operations Package | D17: None | E17: =MAX(INDEX($S$48:$AC$49,MATCH(A17,$S$48:$S$49,0),6),INDEX($S$48:$AC$49,MATCH(D17,$S$48:$S$49,0),6)) -> 0 | F17: =(INDEX($S$48:$AC$49,MATCH(A17,$S$48:$S$49,0),3)+IF(INDEX($S$48:$AC$49,MATCH(A17,$S$48:$S$49,0),3)=0,INDEX($S$48:$AC$49,MATCH(D17,$S$48:$S$49,0),5),0))*'Ship Info'!G31 -> 0 | H17: =MAX(INDEX($S$48:$AC$49,MATCH(A17,$S$48:$S$49,0),2),INDEX($S$48:$AC$49,MATCH(D17,$S$48:$S$49,0),4)) -> 0 | K17: =INDEX($S$48:$AC$49,MATCH(A17,$S$48:$S$49,0),7) -> 0 | S17: Armor Type | T17: Tonnage | U17: Cost | V17: TL | W17: Max | X17: =IF('Ship Info'!F7,0,INDEX(S18:V22,MATCH(B10,S18:S22,0),4)) -> 0 | Y17: =IF('Ship Info'!F7,0,INDEX(S18:W22,MATCH(B10,S18:S22,0),5)) -> 0 | Z17: =MAX(INDEX(S2:Y11,MATCH(B6,S2:S11,0),6),IF(AC42,4,0))+X96 -> 0 | AA17: =IF(Tonnage<15.01,4,IF(Tonnage<25.01,3,IF(Tonnage<99.99,2,1))) -> 1 | AB17: =INDEX(S18:T22,MATCH(B10,S18:S22,0),2)*(B4-C36)*(D11-Z17)*INDEX(S2:Y8,MATCH(B6,S2:S8,0),7)*FtrArmr -> 0
A18: None | B18: =IF(AND(A18=S31,D18<>S31),"2ry Hull: "&INDEX($S$31:$AC$32,MATCH(D18,$S$31:$S$32,0),9),INDEX($S$31:$AC$32,MATCH(A18,$S$31:$S$32,0),9)) -> Holographic Hull | D18: None | E18: =MAX(INDEX($S$31:$AC$32,MATCH(A18,$S$31:$S$32,0),6),INDEX($S$31:$AC$32,MATCH(D18,$S$31:$S$32,0),6)) -> 0 | F18: =(INDEX($S$31:$AC$32,MATCH(A18,$S$31:$S$32,0),3)+IF(INDEX($S$31:$AC$32,MATCH(A18,$S$31:$S$32,0),3)=0,INDEX($S$31:$AC$32,MATCH(D18,$S$31:$S$32,0),5),0))*'Ship Info'!G31 -> 0 | H18: =INDEX($S$31:$AC$32,MATCH(A18,$S$31:$S$32,0),2) -> 0 | K18: =MAX(INDEX($S$31:$AC$32,MATCH(A18,$S$31:$S$32,0),7),INDEX($S$31:$AC$32,MATCH(D18,$S$31:$S$32,0),8)) -> 0 | S18: No Armor | T18: 0 | U18: 0 | V18: 0 | W18: 0 | X18: =IF('Ship Info'!F7,0,INDEX(S18:V22,MATCH(D40,S18:S22,0),4)) -> 0 | Y18: =IF('Ship Info'!F7,0,INDEX(S18:W22,MATCH(D40,S18:S22,0),5)) -> 0 | Z18: =MAX(INDEX(S2:Y11,MATCH(D38,S2:S11,0),6),IF(AC42,4,0)) -> 0 | AA18: =IF(C36<15.01,4,IF(C36<25.01,3,IF(C36<99.99,2,1))) -> 4 | AB18: =IF(C36=0,0,INDEX(S18:T22,MATCH(D40,S18:S22,0),2)*(C36)*(G41-Z18)*INDEX(S2:Y8,MATCH(D38,S2:S8,0),7)*AA18) -> 0
A19: None | B19: =IF(AND(A19=S33,D19<>S33),"2ry Hull: "&INDEX($S$33:$AC$37,MATCH(D19,$S$33:$S$37,0),9),INDEX($S$33:$AC$37,MATCH(A19,$S$33:$S$37,0),9)) -> Stealth | D19: None | E19: =MAX(INDEX($S$33:$AC$37,MATCH(A19,$S$33:$S$37,0),6),INDEX($S$33:$AC$37,MATCH(D19,$S$33:$S$37,0),6)) -> 0 | F19: =(INDEX($S$33:$AC$37,MATCH(A19,$S$33:$S$37,0),3)+IF(INDEX($S$33:$AC$37,MATCH(A19,$S$33:$S$37,0),3)=0,INDEX($S$33:$AC$37,MATCH(D19,$S$33:$S$37,0),5),0))*'Ship Info'!G31 -> 0 | H19: =MAX(INDEX($S$33:$AC$37,MATCH(A19,$S$33:$S$37,0),2),INDEX($S$33:$AC$37,MATCH(D19,$S$33:$S$37,0),4)) -> 0 | K19: =INDEX($S$33:$AC$37,MATCH(A19,$S$33:$S$37,0),5) -> 0 | S19: Titanium Steel | T19: 0.025 | U19: 50000 | V19: 7 | W19: =IF($E$2<9,$E$2,9)*IF($C$9=$W$14,2,1) -> 9
A20: None | B20: =IF(AND(A20=S38,D20<>S38),"2ry Hull: "&INDEX($S$38:$AC$40,MATCH(D20,$S$38:$S$40,0),9),INDEX($S$38:$AC$40,MATCH(A20,$S$38:$S$40,0),9)) -> Adjustable Hull | D20: None | E20: =MAX(INDEX($S$38:$AC$40,MATCH(A20,$S$38:$S$40,0),6),INDEX($S$38:$AC$40,MATCH(D20,$S$38:$S$40,0),6)) -> 0 | F20: =(INDEX($S$38:$AC$40,MATCH(A20,$S$38:$S$40,0),3)+IF(INDEX($S$38:$AC$40,MATCH(A20,$S$38:$S$40,0),3)=0,INDEX($S$38:$AC$40,MATCH(D20,$S$38:$S$40,0),5),0))*'Ship Info'!G31 -> 0 | H20: =MAX(INDEX($S$38:$AC$40,MATCH(A20,$S$38:$S$40,0),2),INDEX($S$38:$AC$40,MATCH(D20,$S$38:$S$40,0),4)) -> 0 | K20: =INDEX($S$38:$AC$40,MATCH(A20,$S$38:$S$40,0),7) -> 0 | S20: Crystaliron | T20: 0.0125 | U20: 200000 | V20: 10 | W20: =IF($E$2<13,$E$2,13)*IF($C$9=$W$14,2,1) -> 12
A21: None | B21: =IF(AND(A21=S41,D21<>S41),"2ry Hull: "&INDEX($S$41:$AC$42,MATCH(D21,$S$41:$S$42,0),9),INDEX($S$41:$AC$42,MATCH(A21,$S$41:$S$42,0),9)) -> Pressure Hull | D21: None | E21: =MAX(INDEX($S$41:$AC$42,MATCH(A21,$S$41:$S$42,0),6),INDEX($S$41:$AC$42,MATCH(D21,$S$41:$S$42,0),6)) -> 0 | F21: =(INDEX($S$41:$AC$42,MATCH(A21,$S$41:$S$42,0),3)+IF(INDEX($S$41:$AC$42,MATCH(A21,$S$41:$S$42,0),3)=0,INDEX($S$41:$AC$42,MATCH(D21,$S$41:$S$42,0),5),0))*'Ship Info'!G31 -> 0 | H21: =MAX(INDEX($S$41:$AC$42,MATCH(A21,$S$41:$S$42,0),2),INDEX($S$41:$AC$42,MATCH(D21,$S$41:$S$42,0),4)) -> 0 | K21: =INDEX($S$41:$AC$42,MATCH(A21,$S$41:$S$42,0),7) -> 0 | S21: Bonded Superdense | T21: 0.008 | U21: 500000 | V21: 14 | W21: =$E$2*IF($C$9=$W$14,2,1) -> 12
A22: None | B22: =IF(AND(A22=S46,D22<>S46),"2ry Hull: "&INDEX($S$46:$AA$47,MATCH(D22,$S$46:$S$47,0),9),INDEX($S$46:$AA$47,MATCH(A22,$S$46:$S$47,0),9)) -> Radiation Shielding | D22: None | E22: =MAX(INDEX($S$46:$AC$47,MATCH(A22,$S$46:$S$47,0),6),INDEX($S$46:$AC$47,MATCH(D22,$S$46:$S$47,0),6)) -> 0 | F22: =(INDEX(S46:AA47,MATCH(A22,S46:S47,0),3)+IF(INDEX($S$46:$AC$47,MATCH(A22,$S$46:$S$47,0),3)=0,INDEX($S$46:$AC$47,MATCH(D22,$S$46:$S$47,0),5),0))*'Ship Info'!G31 -> 0 | H22: =INDEX(S46:AA47,MATCH(A22,S46:S47,0),2) -> 0 | K22: =INDEX(S46:Y47,MATCH(A22,S46:S47,0),7) -> 0 | S22: Molecular Bonded | T22: 0.005 | U22: 1500000 | V22: 16 | W22: =($E$2+4)*IF($C$9=$W$14,2,1) -> 16
A23: None | B23: =IF(AND(A23=S50,D23<>S50),"2ry Hull: "&INDEX($S$50:$AA$51,MATCH(D23,$S$50:$S$51,0),9),INDEX($S$50:$AA$51,MATCH(A23,$S$50:$S$51,0),9)) -> Self Maintenance Mod | D23: None | E23: 0 | F23: =(INDEX(S50:Y51,MATCH(A23,S50:S51,0),3)+INDEX(S50:Y51,MATCH(D23,S50:S51,0),5))*'Ship Info'!G31 -> 0 | H23: 0 | K23: 0
A24: None | B24: =INDEX($S$43:$AC$45,MATCH(A24,$S$43:$S$45,0),9) -> Solar Coating | C24: % of Hull: | D24: 40 | E24: =INDEX($S$43:$AC$45,MATCH(A24,$S$43:$S$45,0),6) -> 0 | F24: =INDEX($S$43:$AC$45,MATCH(A24,$S$43:$S$45,0),3)*'Ship Info'!G31 -> 0 | H24: =INDEX($S$43:$AC$45,MATCH(A24,$S$43:$S$45,0),2) -> 0 | K24: =INDEX($S$43:$AC$45,MATCH(A24,$S$43:$S$45,0),7)*$D$24/100*Tonnage*INDEX($S$2:$Z$11,MATCH($B6,$S$2:$S$11,0),8) -> 0 | S24: Hull Options | T24: Tonnage | U24: Cost | V24: Tonnage | W24: Cost | X24: TL | Y24: Power | Z24: Power
A25: Note: Column A: Hull Options will cover both primary and secondary hulls | D25: (0 - 40 %) | S25: None | T25: 0 | U25: 0 | V25: 0 | W25: 0 | X25: 0 | Y25: 0 | AA25: Aerofins
S26: Aerofins | T26: =0.05*I6 -> 5 | U26: =T26*100000 -> 500000 | V26: =0.05*C36 -> 0 | W26: =V26*100000 -> 0 | X26: 7 | Y26: 0 | AA26: DM +2 to Atmospheric Pilot Checks | AC26: =OR(A14=S26,A15=S26,A16=S26,A18=S26,A19=S26,A20=S26) -> FALSE | AD26: =COUNTIF(AC49:AC51,TRUE)+COUNTIF(AC26:AC42,TRUE) -> 0 | AE26: option count
A27: Droyne Hull | B27: *Cost reflects amount paid above for Hull. | S27: None | T27: 0 | U27: 0 | V27: 0 | W27: 0 | X27: 0 | Y27: 0 | AA27: Reflec
F28: =INDEX(S85:W92,MATCH(B28,S85:S92,0),5)*Tonnage -> 0 | H28: =INDEX(S85:W92,MATCH(B28,S85:S92,0),3)*Tonnage -> 0 | S28: Reflec | T28: 0 | U28: =Tonnage*100000 -> 10000000 | V28: 0 | W28: =C36*100000 -> 0 | X28: 10 | Y28: 0 | AA28: Protection +3 vs Lasers | AC28: =OR(A14=S28,A15=S28,A16=S28,A18=S28,A19=S28,A20=S28) -> FALSE
B29: =INDEX(S85:X92,MATCH(B28,S85:S92,0),6) | S29: None | T29: 0 | U29: 0 | V29: 0 | W29: 0 | X29: 0 | Y29: 0 | AA29: Heat Shielding
S30: Heat Shielding | T30: 0 | U30: =Tonnage*100000 -> 10000000 | V30: 0 | W30: =C36*100000 -> 0 | X30: 6 | Y30: 0 | AA30: Unpowered reentry | AC30: =OR(A14=S30,A15=S30,A16=S30,A18=S30,A19=S30,A20=S30) -> FALSE
A31: Modular Hull | K31: Planetoid House Rules | S31: None | T31: 0 | U31: 0 | V31: 0 | W31: 0 | X31: 0 | Y31: 0 | AA31: Holographic Hull
B32: Total Tonnage of Modular Section(s): | C32: 0 | F32: =IF(C32>0,F6*C32/B4,0)*'Ship Info'!G31 -> 0 | K32: Use Total Tons for Modular Section Limit: | L32: No | S32: Holographic Hull | T32: 0 | U32: =Tonnage*100000 -> 10000000 | V32: 0 | W32: =C36*100000 -> 0 | X32: 10 | Y32: =B4/2 -> 50 | Z32: =C36/2 -> 0 | AA32: Programmable Hull Paint Scheme | AC32: =OR(A14=S32,A15=S32,A16=S32,A18=S32,A19=S32,A20=S32) -> FALSE
B33: ="Limit: "&TEXT(IF('Ship Info'!F7,'Ship Info'!C5*0.75,ROUNDDOWN(T56,1))*IF(L32="Yes",1,INDEX(S2:W11,MATCH(B6,S2:S11,0),5)),"#,###")&" Tons" -> Limit: 75 Tons | K33: Allow Specialized Hull Types | L33: No | S33: None | T33: 0 | U33: 0 | V33: 0 | W33: 0 | X33: 0 | Y33: 0 | Z33: 0 | AA33: Stealth
B34: Calculate cost as if module installed? | C34: No | F34: =1*IF(C34="No",0,C32*25000)*'Ship Info'!G31 -> 0 | K34: Allow Additional Hull Types | L34: No | S34: Basic Stealth | T34: =0.02*Tonnage -> 2 | U34: =40000*Tonnage -> 4000000 | V34: =0.02*C36 -> 0 | W34: =40000*C36 -> 0 | X34: 8 | Y34: 0 | AA34: DM-2 Electronics (Sensors) | AC34: =OR(A14=S34,A15=S34,A16=S34,A18=S34,A19=S34,A20=S34) -> FALSE | AD34: =COUNTIF(AC34:AC37,TRUE) -> 0 | AE34: Stealth count
A35: Special Hulls | B35: Minimal implementation. Cost and space accounted for. | S35: Improved Stealth | T35: 0 | U35: =Tonnage*100000 -> 10000000 | V35: 0 | W35: =100000*C36 -> 0 | X35: 10 | Y35: 0 | AA35: DM-2 Electronics (Sensors) | AC35: =OR(A14=S35,A15=S35,A16=S35,A18=S35,A19=S35,A20=S35) -> FALSE
A36: Breakaway Hulls | B36: Total of Secondary Hull(s) in Dtons: | C36: 0 | F36: =2000000*H36*'Ship Info'!G31 -> 0 | H36: =IF(C36>0,0.02*Tonnage,0) -> 0 | S36: Enhanced Stealth | T36: 0 | U36: =Tonnage*500000 -> 50000000 | V36: 0 | W36: =C36*500000 -> 0 | X36: 12 | Y36: 0 | AA36: DM-4 Electronics (Sensors) | AC36: =OR(A14=S36,A15=S36,A16=S36,A18=S36,A19=S36,A20=S36) -> FALSE
A37: >>Use B/U Drives for secondary hull | C37: Gravity? | D37: Yes | S37: Advanced Stealth | T37: 0 | U37: =Tonnage*1000000 -> 100000000 | V37: 0 | W37: =C36*1000000 -> 0 | X37: 14 | Y37: 0 | AA37: DM-6 Electronics (Sensors) | AC37: =OR(A14=S37,A15=S37,A16=S37,A18=S37,A19=S37,A20=S37) -> FALSE
A38: >>Calculate total power needed for both ships | C38: Configuration | D38: Standard | S38: None | T38: 0 | U38: 0 | V38: 0 | W38: 0 | X38: 0 | Y38: 0 | AA38: Adjustable Hull
A39: and enter that into Power Plant. | C39: Hull Type | D39: Standard Hull | S39: Adjustable Hull TL 12 | T39: =0.05*Tonnage -> 5 | U39: =0.1*F6 -> 500000 | V39: =0.05*C36 -> 0 | W39: =0.1*C36*IF(AND('Ship Info'!F7=1,'Ship Info'!I6="No"),25000,Z14*(INDEX(S2:Y8,MATCH(D38,S2:S8,0),4))*(INDEX(S13:U15,MATCH(D39,S13:S15,0),3))) -> 0 | X39: 12 | Y39: 0 | AA39: Mimics other hull shapes | AC39: =OR(A15=S39,A16=S39,A18=S39,A19=S39,A20=S39,A14=S39) -> FALSE
A40: >>Split tonnage as appropriate on plans. | C40: Armour Type | D40: No Armor | E40: =INDEX(S18:V22,MATCH(D40,S18:S22,0),4) -> 0 | G40: 2ry Armour Total | S40: Adjustable Hull TL 15 | T40: =0.01*Tonnage -> 1 | U40: =F6 -> 5000000 | V40: =0.01*C36 -> 0 | W40: =C36*IF(AND('Ship Info'!F7=1,'Ship Info'!I6="No"),25000,Z14*(INDEX(S2:Y8,MATCH(D38,S2:S8,0),4))*(INDEX(S13:U15,MATCH(D39,S13:S15,0),3))) -> 0 | X40: 15 | Y40: 0 | AA40: Mimics other hull shapes | AC40: =OR(A16=S40,A18=S40,A19=S40,A20=S40,A15=S40,A14=S40) -> FALSE
A41: >>Denote stats of separate and combined ships | C41: Armour Value | D41: 0 | G41: =IF(D41=0,Z18,IF(AC6+Z18>Y18,Y18,AC6+Z18)) -> 0 | S41: None | T41: 0 | U41: 0 | V41: 0 | W41: 0 | X41: 0 | Y41: 0 | AA41: Pressure Hull
A42: in the Narrative Description (Ship Info Tab) | C42: Military Hull | D42: No | S42: Pressure Hull | T42: =0.25*Tonnage -> 25 | U42: =9*F6 -> 45000000 | V42: =0.25*C36 -> 0 | W42: =9*C36*IF(AND('Ship Info'!F7=1,'Ship Info'!I6="No"),25000,Z14*(INDEX(S2:Y8,MATCH(D38,S2:S8,0),4))*(INDEX(S13:U15,MATCH(D39,S13:S15,0),3))) -> 0 | X42: 4 | Y42: 0 | AA42: Extreme Deeps ops, +4 armor | AC42: =OR(A18=S42,A19=S42,A20=S42,A16=S42,A15=S42,A14=S42) -> FALSE
A43: Double Hull | B43: Outer Hull in Dtons: | C43: 60 | F43: =IF(H43>0,ROUNDDOWN(C43/Tonnage*100,0)*0.01*F6,0)*'Ship Info'!G31 -> 0 | H43: =IF(T58,0.1*C43,0) -> 0 | S43: None | T43: 0 | U43: 0 | V43: 0 | W43: 0 | X43: 0 | Y43: 0 | AA43: Solar Coating
A44: No Double Hull | C44: (Minimum 60 Dtons) | S44: Enhanced Solar Coating | T44: 0 | U44: =300000*D24/100*Tonnage -> 12000000 | V44: 0 | W44: =300000*D24/100*C36 -> 0 | X44: 10 | Y44: -0.1 | AA44: Produces power | AC44: =OR(A24=S44) -> FALSE | AD44: =COUNTIF(AC44:AC45,TRUE) -> 0 | AE44: Solar Coat Count
S45: Advanced Solar Coating | T45: 0 | U45: =400000*D24/100*Tonnage -> 16000000 | V45: 0 | W45: =400000*D24/100*C36 -> 0 | X45: 12 | Y45: -0.2 | AA45: Produces power | AC45: =OR(A24=S45) -> FALSE
A46: Hamster Cage | B46: Total Volume of Rings in Dtons: | C46: 0 | F46: =IF(H46>0,ROUNDDOWN(C46/Tonnage*100,0)*0.02*F6,0)*'Ship Info'!G31 -> 0 | H46: =0.1*C46 -> 0 | S46: None | T46: 0 | U46: 0 | V46: 0 | W46: 0 | X46: 0 | Y46: 0 | AA46: Radiation Shielding
S47: Radiation Shielding | T47: 0 | U47: =Tonnage*25000 -> 2500000 | V47: 0 | W47: =C36*25000 -> 0 | X47: 7 | Y47: 0 | AA47: Reduce Rads by 1,000 | AC47: =OR(A22=S47) -> FALSE
B48: Ring Tonnage calculator | C48: Meters | D48: Squares | S48: None | T48: 0 | U48: 0 | V48: 0 | W48: 0 | X48: 0 | Y48: 0 | AA48: Hostile Environment Operations Package
B49: Diameter in meters (min 30m/20sq) | C49: 15 | D49: =ROUNDUP(C49/1.5,0) -> 10 | S49: Hostile Environment Ops | T49: =0.05*Tonnage -> 5 | U49: =100000*Tonnage -> 10000000 | V49: =0.05*C36 -> 0 | W49: =100000*C36 -> 0 | X49: 7 | Y49: 0 | AA49: Resist Hazardous Atmospheres | AC49: =OR(A17=S49) -> FALSE
B50: Ring width in meters (1.5m=1sq) | C50: 7.5 | D50: =ROUNDUP(C50/1.5,0) -> 5 | S50: None | T50: 0 | U50: 0 | V50: 0 | W50: 0 | X50: 0 | Y50: 0 | AA50: Self Maintenance Mod
B51: Inner (ceiling) circumference | C51: =ROUNDUP(C49*PI(),0) -> 48 | D51: =ROUNDUP(D49*PI(),0) -> 32 | S51: Self-Maintenance Mod | T51: 0 | U51: =100000*Tonnage -> 10000000 | V51: 0 | W51: =100000*C36 -> 0 | X51: 0 | Y51: 0 | AA51: Conduct Repairs in Deep Space | AC51: =OR(A23=S51) -> FALSE
B52: Ring tonnage: | C52: =TEXT(D52/2,"#,###")&" Dtons" -> 79 Dtons | D52: =ROUNDUP(D49*PI()*D50,0) -> 158
B54: >>Multi level rings can be calculated by adding 6m to the previous level's diameter and adding the total to the previous level(s)
S56: Modular Limit | T56: =0.750001*B4 -> 75.0001
S57: Special Hulls | AC57: Double Hull Installed
S58: Double Hull | T58: =IF(A44=AC57,TRUE,FALSE) -> FALSE | U58: =C43 -> 60 | V58: =IF(T58,1,0) -> 0 | AC58: No Double Hull
S59: Hamster Cages | T59: =C46 -> 0
S60: Breakaway Hulls | T60: =C36 -> 0
S62: Page Tonnage | T62: Page Energy
S63: =SUM(H10:H55) -> 0 | T63: =SUM(K11:K22) -> 20
S65: =B4&" tons, "&B8&" "&B6&", "&IF(D5="Yes","","Non-Gravitic ")&D6&IF(C9=W14,", Military Hull","") &""&IF(A14=S25,"",", "&A14)&""&IF(A15=S25,"",", "&A15)&""&IF(A16=S25,"",", "&A16)&""&IF(A17=S25,"",", "&A17)&""&IF(A18=S25,"",", "&A18)&""&IF(A19=S25,"",", "&A19)&""&IF(A20=S25,"",", "&A20)&""&IF(A22=S46,"",", "&A22)&""&IF(A24=S43,"",", "&A24)&IF(C32=0,"",", "&C32&" tons of Modular Section(s)")&IF(C36=0,"",", "&C36&" tons of Breakaway Hull(s)")&IF(T58=FALSE,"",", "&C43&" tons of Double Hull")&IF(C46=0,"",", "&C46&" tons of Hamster Cages") -> 100 tons, Partial Standard, Standard Hull
S66: =IF(D7<10560,D7,IF(D7<105600,D7/10,IF(D7<1056000,D7/100,D7/1000))) -> 40
S67: 10 | T67: 20 | U67: 30 | V67: 40 | W67: 50 | X67: 60 | Y67: 70 | Z67: 80 | AA67: 90
S68: =ROUNDUP(0.1*S66,0) -> 4 | T68: =ROUNDUP(0.2*S66,0) -> 8 | U68: =ROUNDUP(0.3*S66,0) -> 12 | V68: =ROUNDUP(0.4*S66,0) -> 16 | W68: =ROUNDUP(0.5*S66,0) -> 20 | X68: =ROUNDUP(0.6*S66,0) -> 24 | Y68: =ROUNDUP(0.7*S66,0) -> 28 | Z68: =ROUNDUP(0.8*S66,0) -> 32 | AA68: =ROUNDUP(0.9*S66,0) -> 36
S70: SSD Aerofins: | T70: =IF(OR(A14=S26,A15=S26,A16=S26,A18=S26,A19=S26,A20=S26),"/Atm+2","")
Z71: =INDEX(S2:AA8,MATCH(B6,S2:S8,0),9) -> 4 | AA71: Hull Description
S72: Hull tonnage | Z72: Current | AA72: Streamlined | AB72: Dispersed | AC72: Sphere | AD72: Partial | AE72: Planetoid
S73: =SUM(H14:H24) -> 0 | Z73: ="" | AA73: ="" | AB73: ="" | AC73: ="" | AD73: ="" | AE73: =""
S74: Hull tonnage exceeded | T74: =IF(H6<0,1,0) -> 0 | Y74: 1 | Z74: {=INDEX($AA$74:$AE$81,Y74,$Z$71)} -> Boxy | AA74: Cone | AB74: Trussed | AC74: Round | AD74: Boxy | AE74: Lumpy
S75: Modular Hull Error | T75: =IF(C32>T56,1,0) -> 0 | Y75: 2 | Z75: {=INDEX($AA$74:$AE$81,Y75,$Z$71)} -> Rounded | AA75: Rounded Cylinder | AB75: Ringed | AC75: Oval | AD75: Rounded | AE75: Rounded
S76: TL Error | T76: =IF(U76>E2,1,0) -> 0 | U76: =MAX(E14:E24,E40) -> 0 | Y76: 3 | Z76: {=INDEX($AA$74:$AE$81,Y76,$Z$71)} -> Flat Cylinder | AA76: Disc | AB76: Ad-Hoc | AC76: Teardrop | AD76: Flat Cylinder | AE76: =""
S77: Planetoid/Additional | T77: =IF(AND(U77>0,L34="No",SUM(V58,T59,T60)>0),1,0) -> 0 | U77: =IF(OR(B6=S2,B6=S5),1,0) -> 0 | V77: Hull | W77: Mil | X77: Grav | Y77: 4 | Z77: {=INDEX($AA$74:$AE$81,Y77,$Z$71)} | AA77: Lifting Body | AB77: Connected Pods | AC77: Hemisphere | AD77: ="" | AE77: =""
S78: Planetoid/Specialized | T78: =IF(AND(U78=1,SUM(V78:X78)>0),1,0) -> 0 | U78: =IF(AND(L33="No",OR(B6=S2,B6=S5)),1,0) -> 0 | V78: =IF(INDEX(S13:T15,MATCH(D6,S13:S15,0),2)=1,0,1) -> 0 | W78: =IF(C9="No",0,1) -> 0 | X78: =IF(D5="Yes",0,1) -> 0 | Y78: 5 | Z78: {=INDEX($AA$74:$AE$81,Y78,$Z$71)} | AA78: Needle | AB78: Irregular Shape | AC78: ="" | AD78: ="" | AE78: =""
S79: Military Hull Error | T79: =IF(AND(B4<5000,C9=W14),1,0)+IF(AND(C36<5000,D42=W14),1,0) -> 0 | Y79: 6 | Z79: {=INDEX($AA$74:$AE$81,Y79,$Z$71)} | AA79: Wedge | AB79: ="" | AC79: ="" | AD79: ="" | AE79: =""
S80: Solar plus anything | T80: =IF(AND($AD$44=1,$AD$26>0),1,0) -> 0 | Y80: 7 | Z80: {=INDEX($AA$74:$AE$81,Y80,$Z$71)} | AA80: Losenge | AB80: ="" | AC80: ="" | AD80: ="" | AE80: =""
S81: Error | T81: =SUM(T74:T80) -> 0 | Y81: 8 | Z81: {=INDEX($AA$74:$AE$81,Y81,$Z$71)} | AA81: Rounded Nose | AB81: ="" | AC81: ="" | AD81: ="" | AE81: =""
S84: Droyne | U84: Tons | W84: Cost
S85: ="" | U85: 0 | W85: 0 | X85: =""
S86: Droyne Hull | U86: 0 | W86: =100000-X14 -> 50000 | X86: Impressively Decorated
S87: Auspicious of Jump | U87: 0.04 | W87: =250000-X14 -> 200000 | X87: DM+1 Jump Checks; -10% Jump Fuel
S88: Auspicious of Manoeuvre | U88: 0.01 | W88: =150000-X14 -> 100000 | X88: DM+1 Pilot Checks
S89: Auspicious of Seeking | U89: 0.02 | W89: =200000-X14 -> 150000 | X89: DM+1 Sensors/Astrogation
S90: Auspicious of Leading | U90: 0.01 | W90: =200000-X14 -> 150000 | X90: DM+1 Appeal/Leadership/Tactics
S91: Auspicious of Battling | U91: 0.03 | W91: =300000-X14 -> 250000 | X91: DM+1 Gunner; +2 Armour
S92: Auspicious of Communicating | U92: 0.02 | W92: =250000-X14 -> 200000 | X92: DM+1 Diplomacy/Broker
S93: 1 | T93: 2 | U93: 3 | V93: 4 | W93: 5 | X93: 6
T95: Fuel | U95: Pilot | V95: Sensors | W95: Gunner | X95: Armor
T96: =IF(B28=S87,0.1,0) -> 0 | U96: =IF(B28=S88,1,0) -> 0 | V96: =IF(B28=S89,1,0) -> 0 | W96: =IF(B28=S91,1,0) -> 0 | X96: =IF(B28=S91,2,0) -> 0
T97: Goes to Drives | X97: Acts as intrinsic
T98: AC47

Sheet 2-Drives
A1: ='Ship Info'!A1 -> Ship's Class Name | B1: ='Ship Info'!B1 -> 0 | F1: Cost | S1: Engine Type | T1: Tonnage | U1: Cost | V1: TL | W1: Power | Z1: DSMS TL Limiter: | AA1: =MIN(17,E2) -> 12 | AE1: Rating | AF1: 0 | AG1: 1 | AH1: 2 | AI1: 3 | AJ1: 4 | AK1: 5 | AL1: 6 | AM1: 7 | AN1: 8 | AO1: 9 | AP1: 10 | AQ1: 11 | AR1: 12 | AS1: 13 | AT1: 14 | AU1: 15 | AV1: 16 | AZ1: Adjusted | BA1: BU | BB1: T+S:+S:BBBBL Max
A2: Class Role | B2: ='Ship Info'!B2 -> 0 | D2: Tech Level: | E2: =Tech_Level -> 12 | F2: ='Ship Info'!G2 -> 6177000 | S2: No Drive | T2: 0 | U2: 0 | V2: 0 | W2: 0 | Y2: Mod Price modifier | AE2: Manoeuvre | AF2: =IF('Ship Info'!E6="Station",0.0025,0.005) -> 0.005 | AG2: 0.01 | AH2: 0.02 | AI2: 0.03 | AJ2: 0.04 | AK2: 0.05 | AL2: 0.06 | AM2: 0.07 | AN2: 0.08 | AO2: 0.09 | AP2: 0.1 | AQ2: 0.11 | AR2: 1 | AS2: 1 | AT2: 1 | AU2: 1 | AV2: 1 | AX2: Man Mdrv | AZ2: =IF(P8=0,ROUNDDOWN(H14/C4,2),ROUNDDOWN(H14/P8,2)) -> 0 | BA2: =IF(P8=0,ROUNDDOWN(H46/C4,2),ROUNDDOWN(H46/P8,2)) -> 0 | BB2: =IF(E2<9,0,IF(E2<10,1,IF(E2<11,3,IF(E2<12,5,IF(E2<13,7,IF(E2<14,9,IF(E2<17,10,11))))))) -> 7
B3: ='1-Hull'!B3 -> Standard Automation - Costs x 1 | H3: =S63 -> 0 | K3: =S66 -> 0 | S3: Manoeuvre Drive | T3: =T20*INDEX(AF1:AQ3,2,MATCH(D14,AF1:AQ1,0)) -> 0.5 | U3: =2000000*(T3) -> 1000000 | V3: =INDEX(AF1:AQ3,3,MATCH(D14,AF1:AQ1,0)) -> 9 | W3: =IF(D14>0,D14*0.1*U107,0.1*U107*0.25) -> 2.5 | Y3: 0 | AA3: 0 | AE3: TL | AF3: 9 | AG3: 9 | AH3: 10 | AI3: 10 | AJ3: 11 | AK3: 11 | AL3: 12 | AM3: 13 | AN3: 14 | AO3: 15 | AP3: 16 | AQ3: 17 | AR3: 99 | AS3: 99 | AT3: 99 | AU3: 99 | AV3: 99 | AX3: Reaction | AZ3: =IF(P8=0,ROUNDDOWN(H23/C4,2),ROUNDDOWN(H23/P8,2)) -> 0 | BA3: =IF(P8=0,ROUNDDOWN(H37/C4,2),ROUNDDOWN(H37/P8,2)) -> 0 | BB3: =IF(E2<7,0,IF(E2<8,3,IF(E2<9,6,IF(E2<10,9,IF(E2<11,12,IF(E2<12,15,16)))))) -> 16
A4: Tonnage | B4: ='1-Hull'!B4 -> 100 | F4: Page Total | H4: Available Space | K4: Power | S4: Reaction Drive | T4: =U20*INDEX(AF1:AV5,4,MATCH(D23,AF1:AV1,0)) -> 1 | U4: =200000*(T4) -> 200000 | V4: =INDEX(AF1:AV5,5,MATCH(D23,AF1:AV1,0)) -> 7 | W4: 0 | Y4: 1 | AA4: 0.1 | AE4: Reaction | AF4: 0.01 | AG4: 0.02 | AH4: 0.04 | AI4: 0.06 | AJ4: 0.08 | AK4: 0.1 | AL4: 0.12 | AM4: 0.14 | AN4: 0.16 | AO4: 0.18 | AP4: 0.2 | AQ4: 0.22 | AR4: 0.24 | AS4: 0.26 | AT4: 0.28 | AU4: 0.3 | AV4: 0.32 | AX4: FTL | AZ4: =IF(P8=0,ROUNDDOWN((H29-5)/C4,3),ROUNDDOWN((H29-5)/P8,3)) -> -0.05 | BA4: =IF(P8=0,ROUNDDOWN(H56/C4,2),ROUNDDOWN(H56/P8,2)) -> 0 | BB4: =IF(E2<9,0,IF(E2<10,1,IF(E2<12,2,IF(E2<13,3,IF(E2<14,4,IF(E2<15,5,IF(E2<16,6,IF(E2<17,7,IF(E2<18,8,9))))))))) -> 3 | BE4: Note: This chart does not combine main and secondary drives
B5: Optional Rules | F5: =SUM(F14:F61) -> 0 | H5: Unused | I5: Max | K5: Unused | L5: Max | S5: No FTL | T5: 0 | U5: 0 | V5: 0 | W5: 0 | Y5: 2 | AA5: 0.25 | AE5: TL | AF5: 7 | AG5: 7 | AH5: 7 | AI5: 7 | AJ5: 8 | AK5: 8 | AL5: 8 | AM5: 9 | AN5: 9 | AO5: 9 | AP5: 10 | AQ5: 10 | AR5: 10 | AS5: 11 | AT5: 11 | AU5: 11 | AV5: 12
B6: Base Fuel Calculations on: | C6: Mains | H6: ='Ship Info'!I3 -> 92.53 | I6: ='1-Hull'!I6 -> 100 | K6: ='Ship Info'!L3 -> 0 | L6: ='3-Pwr Plant'!L6 -> 20 | M6: Check Performance at Varied Hull Displacement | S6: Hyperdrive | T6: =V20*INDEX(AF6:AO8,2,MATCH(D29,AF6:AO6,0)) -> 0 | U6: =2000000*(T6) -> 0 | V6: =INDEX($AF$6:$AO$8,3,MATCH($D29,$AF$6:$AO$6,0)) -> 0 | W6: =T6+H32 -> 0 | Y6: 3 | AA6: 0.5 | AE6: Rating | AF6: 0 | AG6: 1 | AH6: 2 | AI6: 3 | AJ6: 4 | AK6: 5 | AL6: 6 | AM6: 7 | AN6: 8 | AO6: 9 | AX6: No FTL | AZ6: 0 | BA6: 0 | BC6: Maximum Tonnage Allowed for Listed Performance With Current Engines
B7: Allow FTL on craft smaller than 100 Dtons? | C7: No | H7: Item Tons | M7: Adjusted Displacement | S7: Jump Drive | T7: =IF((V20*INDEX(AF6:AO16,4,MATCH(D29,AF6:AO6,0))+5)<10,10,V20*INDEX(AF6:AO16,4,MATCH(D29,AF6:AO6,0))+5) -> 10 | U7: =1500000*(T7) -> 15000000 | V7: =INDEX($AF$6:$AO$10,5,MATCH($D29,$AF$6:$AO$6,0)) -> 0 | W7: =0.1*U113*D29 -> 0 | AE7: Hyperdrive/Warp | AF7: 0 | AG7: 0.1 | AH7: 0.12 | AI7: 0.14 | AJ7: 0.16 | AK7: 0.18 | AL7: 0.2 | AM7: 0.22 | AN7: 0.24 | AO7: 0.26 | AX7: Hyperdrive | AZ7: =IF(AZ4>0.259,9,IF(AZ4>0.239,8,IF(AZ4>0.219,7,IF(AZ4>0.199,6,IF(AZ4>0.179,5,IF(AZ4>0.159,4,IF(AZ4>0.139,3,IF(AZ4>0.119,2,IF(AZ4>0.099,1,0))))))))) -> 0 | BA7: =IF(BA4>0.259,9,IF(BA4>0.239,8,IF(BA4>0.219,7,IF(BA4>0.199,6,IF(BA4>0.179,5,IF(BA4>0.159,4,IF(BA4>0.139,3,IF(BA4>0.119,2,IF(BA4>0.099,1,0))))))))) -> 0
B8: Reduce TL on Non-Jump FTL? | C8: No | M8: Manuever | P8: 100 | S8: Jump Drive (Hop) | T8: =IF((V20*INDEX(AF6:AO16,6,MATCH(D29,AF6:AO6,0))+5)<10,10,V20*INDEX(AF6:AO16,6,MATCH(D29,AF6:AO6,0))+5) -> 10 | U8: =15000000*T8 -> 150000000 | V8: =INDEX($AF$6:$AO$12,7,MATCH($D29,$AF$6:$AO$6,0)) -> 0 | W8: =0.1*U113*D29 -> 0 | AA8: TL Toggle | AE8: TL | AF8: 0 | AG8: =17+AA9 -> 17 | AH8: =19+AA9 -> 19 | AI8: =20+AA9 -> 20 | AJ8: =21+AA9 -> 21 | AK8: =22+AA9 -> 22 | AL8: =23+AA9 -> 23 | AM8: =24+AA9 -> 24 | AN8: =25+AA9 -> 25 | AO8: =26+AA9 -> 26 | AX8: Jump Drive | AZ8: =IF(AZ4>0.224,9,IF(AZ4>0.199,8,IF(AZ4>0.174,7,IF(AZ4>0.149,6,IF(AZ4>0.124,5,IF(AZ4>0.099,4,IF(AZ4>0.074,3,IF(AZ4>0.049,2,IF(AZ4>0.024,1,0))))))))) -> 0 | BA8: =IF(BA4>0.224,9,IF(BA4>0.199,8,IF(BA4>0.174,7,IF(BA4>0.149,6,IF(BA4>0.124,5,IF(BA4>0.099,4,IF(BA4>0.074,3,IF(BA4>0.049,2,IF(BA4>0.024,1,0))))))))) -> 0 | BC8: 1 | BE8: 2 | BG8: 3 | BI8: 4 | BK8: 5 | BM8: 6 | BO8: 7 | BQ8: 8 | BS8: 9 | BU8: 10 | BW8: 11 | BY8: 12 | CA8: 13 | CC8: 14 | CE8: 15 | CG8: 16
A9: Main Drive(s) | B9: Calculate Drives on: | C9: Actual Dtons | E9: TL | H9: =IF(OR('Ship Info'!F7,'Ship Info'!F4),"Pods/Modules Cannot Have Drives","Station with Drive > 0") -> Station with Drive > 0 | M9: Reaction/Solar | P9: 100 | S9: Jump Drive (Skip) | T9: =IF((V20*INDEX(AF6:AO16,8,MATCH(D29,AF6:AO6,0))+5)<10,10,V20*INDEX(AF6:AO16,8,MATCH(D29,AF6:AO6,0))+5) -> 10 | U9: =150000000*T9 -> 1500000000 | V9: =INDEX($AF$6:$AO$14,9,MATCH($D29,$AF$6:$AO$6,0)) -> 0 | W9: =0.1*U113*D29 -> 0 | AA9: =IF(C8=S13,-8,0) -> 0 | AE9: Jump Drive | AF9: 0 | AG9: 0.025 | AH9: 0.05 | AI9: 0.075 | AJ9: 0.1 | AK9: 0.125 | AL9: 0.15 | AM9: 0.175 | AN9: 0.2 | AO9: 0.225 | AX9: Jump Drive (Hop) | AZ9: =IF(AZ4>0.224,9,IF(AZ4>0.199,8,IF(AZ4>0.174,7,IF(AZ4>0.149,6,IF(AZ4>0.124,5,IF(AZ4>0.099,4,IF(AZ4>0.074,3,IF(AZ4>0.049,2,IF(AZ4>0.024,1,0))))))))) -> 0 | BA9: =IF(BA4>0.224,9,IF(BA4>0.199,8,IF(BA4>0.174,7,IF(BA4>0.149,6,IF(BA4>0.124,5,IF(BA4>0.099,4,IF(BA4>0.074,3,IF(BA4>0.049,2,IF(BA4>0.024,1,0))))))))) -> 0
M10: Jump/FTL | P10: 100 | S10: Space Folding Drive | T10: =IF(V20*INDEX(AF6:AO16,10,MATCH(D29,AF6:AO6,0))<20,20,V20*INDEX(AF6:AO16,10,MATCH(D29,AF6:AO6,0))) -> 20 | U10: =(T10)*3000000 -> 60000000 | V10: =INDEX($AF$6:$AO$16,11,MATCH($D29,$AF$6:$AO$6,0)) -> 0 | W10: =0.5*U113*D29 -> 0 | X10: No FTL | Y10: 0 | Z10: 0 | AA10: 0 | AB10: 0 | AC10: 2 | AE10: TL | AF10: 0 | AG10: 9 | AH10: 11 | AI10: 12 | AJ10: 13 | AK10: 14 | AL10: 15 | AM10: 16 | AN10: 17 | AO10: 18 | AX10: Jump Drive (Skip) | AZ10: =IF(AZ4>0.224,9,IF(AZ4>0.199,8,IF(AZ4>0.174,7,IF(AZ4>0.149,6,IF(AZ4>0.124,5,IF(AZ4>0.099,4,IF(AZ4>0.074,3,IF(AZ4>0.049,2,IF(AZ4>0.024,1,0))))))))) -> 0 | BA10: =IF(BA4>0.224,9,IF(BA4>0.199,8,IF(BA4>0.174,7,IF(BA4>0.149,6,IF(BA4>0.124,5,IF(BA4>0.099,4,IF(BA4>0.074,3,IF(BA4>0.049,2,IF(BA4>0.024,1,0))))))))) -> 0 | BC10: =$H$14/0.01 -> 0 | BE10: =H14/0.02 -> 0 | BG10: =$H$14/0.03 -> 0 | BI10: =$H$14/0.04 -> 0 | BK10: =$H$14/0.05 -> 0 | BM10: =$H$14/0.06 -> 0 | BO10: =$H$14/0.07 -> 0 | BQ10: =$H$14/0.08 -> 0 | BS10: =$H$14/0.09 -> 0 | BU10: =$H$14/0.1 -> 0 | BW10: =$H$14/0.11 -> 0
B11: Calculate Performance on Combined Breakaway Ship Drives? | C11: No | D11: =" - Use Breakaway Section to allocate Tonnage to Main and B/U Drives" -> - Use Breakaway Section to allocate Tonnage to Main and B/U Drives | S11: Warp Drive | T11: =V20*INDEX(AF6:AO8,2,MATCH(D29,AF6:AO6,0)) -> 0 | U11: =2000000*(T11) -> 0 | V11: =INDEX($AF$6:$AO$8,3,MATCH($D29,$AF$6:$AO$6,0)) -> 0 | W11: =T11+H32 -> 0 | X11: Hyperdrive | Y11: =V21*INDEX(AF6:AO8,2,MATCH(D56,AF6:AO6,0)) -> 0 | Z11: =2000000*(Y11+H59) -> 0 | AA11: =INDEX($AF$6:$AO$8,3,MATCH($D56,$AF$6:$AO$6,0)) -> 0 | AB11: =Y11+H59 -> 0 | AC11: 1 | AE11: Jump Drive (Hop) | AF11: 0 | AG11: 0.025 | AH11: 0.05 | AI11: 0.075 | AJ11: 0.1 | AK11: 0.125 | AL11: 0.15 | AM11: 0.175 | AN11: 0.2 | AO11: 0.225 | AX11: Space Folding Drive | AZ11: =IF(AZ4>0.224,9,IF(AZ4>0.199,8,IF(AZ4>0.174,7,IF(AZ4>0.149,6,IF(AZ4>0.124,5,IF(AZ4>0.099,4,IF(AZ4>0.074,3,IF(AZ4>0.049,2,IF(AZ4>0.024,1,0))))))))) -> 0 | BA11: =IF(BA4>0.224,9,IF(BA4>0.199,8,IF(BA4>0.174,7,IF(BA4>0.149,6,IF(BA4>0.124,5,IF(BA4>0.099,4,IF(BA4>0.074,3,IF(BA4>0.049,2,IF(BA4>0.024,1,0))))))))) -> 0
D12: =" - Enter the rating of the largest section in Main drives, and smaller section(s) in Secondary" -> - Enter the rating of the largest section in Main drives, and smaller section(s) in Secondary | M12: ADJ Main Drive Thrust | P12: =MIN(IF(AZ2<0.01,0,INDEX(AG2:AQ17,16,MATCH(AZ2,AG2:AQ2,0))),BB2) -> 0 | S12: No | T12: No Drive | X12: Jump Drive | Y12: =IF((V21*INDEX(AF6:AO16,4,MATCH(D56,AF6:AO6,0))+5)<10,10,V21*INDEX(AF6:AO16,4,MATCH(D56,AF6:AO6,0))+5) -> 10 | Z12: =1500000*(Y12+H59) -> 15000000 | AA12: =INDEX($AF$6:$AO$10,5,MATCH($D56,$AF$6:$AO$6,0)) -> 0 | AB12: =0.1*U113*D56 -> 0 | AC12: 2 | AE12: TL | AF12: 0 | AG12: 17 | AH12: 18 | AI12: 19 | AJ12: 20 | AK12: 21 | AL12: 22 | AM12: 23 | AN12: 24 | AO12: 25 | AX12: Warp Drive | AZ12: =IF(AZ4>0.259,9,IF(AZ4>0.239,8,IF(AZ4>0.219,7,IF(AZ4>0.199,6,IF(AZ4>0.179,5,IF(AZ4>0.159,4,IF(AZ4>0.139,3,IF(AZ4>0.119,2,IF(AZ4>0.099,1,0))))))))) -> 0 | BA12: =IF(BA4>0.259,9,IF(BA4>0.239,8,IF(BA4>0.219,7,IF(BA4>0.199,6,IF(BA4>0.179,5,IF(BA4>0.159,4,IF(BA4>0.139,3,IF(BA4>0.119,2,IF(BA4>0.099,1,0))))))))) -> 0 | BC12: =$H$23/0.02 -> 0 | BE12: =$H$23/0.04 -> 0 | BG12: =$H$23/0.06 -> 0 | BI12: =$H$23/0.08 -> 0 | BK12: =$H$23/0.1 -> 0 | BM12: =$H$23/0.12 -> 0 | BO12: =$H$23/0.14 -> 0 | BQ12: =$H$23/0.16 -> 0 | BS12: =$H$23/0.18 -> 0 | BU12: =$H$23/0.2 -> 0 | BW12: =$H$23/0.22 -> 0 | BY12: =$H$23/0.24 -> 0 | CA12: =$H$23/0.26 -> 0 | CC12: =$H$23/0.28 -> 0 | CE12: =$H$23/0.3 -> 0 | CG12: =$H$23/0.32 -> 0
G13: * Indicates a non-MgT2-standard Mod | S13: Yes | T13: Reaction Drive | X13: Jump Drive (Hop) | Y13: =IF((V21*INDEX(AF6:AO16,6,MATCH(D56,AF6:AO6,0))+5)<10,10,V21*INDEX(AF6:AO16,6,MATCH(D56,AF6:AO6,0))+5) -> 10 | Z13: =15000000*Y13 -> 150000000 | AA13: =INDEX($AF$6:$AO$12,7,MATCH($D56,$AF$6:$AO$6,0)) -> 0 | AB13: =0.1*U113*D29 -> 0 | AC13: 2 | AE13: Jump Drive (Skip) | AF13: 0 | AG13: 0.025 | AH13: 0.05 | AI13: 0.075 | AJ13: 0.1 | AK13: 0.125 | AL13: 0.15 | AM13: 0.175 | AN13: 0.2 | AO13: 0.225
A14: M-Drive | B14: No Drive | C14: Rating | D14: 0 | E14: =INDEX(S2:V4,MATCH(B14,S2:S4,0),4)+SUM(E19:E21) -> 0 | F14: =INDEX(S2:U4,MATCH(B14,S2:S4,0),3)*'Ship Info'!G31 -> 0 | H14: =INDEX(S2:T4,MATCH(B14,S2:S4,0),2) -> 0 | K14: =INDEX(S2:W4,MATCH(B14,S2:S4,0),5) -> 0 | M14: ADJ Reaction Rating | P14: =INDEX(AP56:AQ88,MATCH(AZ3,AP56:AP88,0),2) -> 0 | S14: ="No High Burn Thruster" -> No High Burn Thruster | T14: 0 | U14: 0 | V14: 0 | X14: Jump Drive (Skip) | Y14: =IF((V21*INDEX(AF6:AO16,8,MATCH(D56,AF6:AO6,0))+5)<10,10,V21*INDEX(AF6:AO16,8,MATCH(D56,AF6:AO6,0))+5) -> 10 | Z14: =150000000*Y14 -> 1500000000 | AA14: =INDEX($AF$6:$AO$14,9,MATCH($D56,$AF$6:$AO$6,0)) -> 0 | AB14: =0.1*U113*D29 -> 0 | AC14: 2 | AE14: TL | AF14: 0 | AG14: 20 | AH14: 21 | AI14: 22 | AJ14: 23 | AK14: 24 | AL14: 25 | AM14: 26 | AN14: 27 | AO14: 28 | AX14: Reaction | BC14: =($H$29-5)/0.025 -> -200 | BE14: =($H$29-5)/0.05 -> -100 | BG14: =($H$29-5)/0.075 -> -66.666667 | BI14: =($H$29-5)/0.1 -> -50 | BK14: =($H$29-5)/0.125 -> -40 | BM14: =($H$29-5)/0.15 -> -33.333333 | BO14: =($H$29-5)/0.175 -> -28.571429 | BQ14: =($H$29-5)/0.2 -> -25 | BS14: =($H$29-5)/0.225 -> -22.222222
B15: EMP Hardened? | C15: No | F15: =IF(C15=S13,0.5*(SUM(F14,F17,F19))," ") | S15: High Burn Thruster | T15: =U21*INDEX(AF1:AV5,4,MATCH(D37,AF1:AV1,0)) -> 1 | U15: =200000*(T15+H39) -> 200000 | V15: =INDEX(AF1:AV5,5,MATCH(D37,AF1:AV1,0)) -> 7 | W15: 0 | X15: Space Folding Drive | Y15: =IF(V21*INDEX(AF6:AO16,10,MATCH(D56,AF6:AO6,0))<20,20,V21*INDEX(AF6:AO16,10,MATCH(D56,AF6:AO6,0))) -> 20 | Z15: =(Y15+H59)*3000000 -> 60000000 | AA15: =INDEX($AF$6:$AO$16,11,MATCH($D56,$AF$6:$AO$6,0)) -> 0 | AB15: =0.5*U113*D29 -> 0 | AC15: 2 | AE15: Space Folding Drive | AF15: 0 | AG15: 0.025 | AH15: 0.05 | AI15: 0.075 | AJ15: 0.1 | AK15: 0.125 | AL15: 0.15 | AM15: 0.175 | AN15: 0.2 | AO15: 0.225
B16: Armored Bulkheads? | C16: No | F16: =IF(C16=S13,200000*H16," ") | H16: =IF(C16=S13,0.1*(SUM(H14,H17,H19))," ") | M16: ADJ FTL Rating | P16: =MIN(IF(H29<10.000001,MIN(D29,INDEX(AX6:AZ12,MATCH(B29,AX6:AX12,0),3)),INDEX(AX6:AZ12,MATCH(B29,AX6:AX12,0),3)),BB4) -> 0 | S16: ="No Solar Sails" -> No Solar Sails | T16: 0 | U16: 0 | X16: Warp Drive | Y16: =V21*INDEX(AF6:AO8,2,MATCH(D56,AF6:AO6,0)) -> 0 | Z16: =2000000*(Y16+H59) -> 0 | AA16: =INDEX($AF$6:$AO$8,3,MATCH($D56,$AF$6:$AO$6,0)) -> 0 | AB16: =T11+H59 -> 0 | AC16: 1 | AE16: TL | AF16: 0 | AG16: =17+AA9 -> 17 | AH16: =18+AA9 -> 18 | AI16: =18+AA9 -> 18 | AJ16: =19+AA9 -> 19 | AK16: =19+AA9 -> 19 | AL16: =20+AA9 -> 20 | AM16: =21+AA9 -> 21 | AN16: =22+AA9 -> 22 | AO16: =23+AA9 -> 23 | BC16: =$H$37/(2*0.01*BC8) -> 0 | BE16: =$H$37/(2*0.01*BE8) -> 0 | BG16: =$H$37/(2*0.01*BG8) -> 0 | BI16: =$H$37/(2*0.01*BI8) -> 0 | BK16: =$H$37/(2*0.01*BK8) -> 0 | BM16: =$H$37/(2*0.01*BM8) -> 0 | BO16: =$H$37/(2*0.01*BO8) -> 0 | BQ16: =$H$37/(2*0.01*BQ8) -> 0 | BS16: =$H$37/(2*0.01*BS8) -> 0 | BU16: =$H$37/(2*0.01*BU8) -> 0 | BW16: =$H$37/(2*0.01*BW8) -> 0 | BY16: =$H$37/(2*0.01*BY8) -> 0 | CA16: =$H$37/(2*0.01*CA8) -> 0 | CC16: =$H$37/(2*0.01*CC8) -> 0 | CE16: =$H$37/(2*0.01*CE8) -> 0 | CG16: =$H$37/(2*0.01*CG8) -> 0
B17: Deep Space Manoeuvering System? | C17: No | D17: =IF(C17=S13,(AA1-8)*5&"% Efficiency","") | F17: =IF(C17=S13,0.6*SUM(F14,F19:F21)," ") | H17: =IF(C17=S13,SUM(H14,H19:H21)*((200-((AA1-9)*25))/100),0) -> 0 | K17: =IF(C17=S13,SUM(K14,K19:K21)*3,"") | S17: Solar Sails | T17: =0.05*W21 -> 5 | U17: =200000*T17 -> 1000000 | W17: 0 | AF17: 0 | AG17: 1 | AH17: 2 | AI17: 3 | AJ17: 4 | AK17: 5 | AL17: 6 | AM17: 7 | AN17: 8 | AO17: 9 | AP17: 10 | AQ17: 11 | AR17: 12 | AS17: 13 | AT17: 14 | AU17: 15 | AV17: 16
B18: Variable Emission Drive? | C18: No | F18: =IF(C18="No",0,4*SUM(F14,F17,F19)) -> 0 | H18: =IF(C18="No",0,0.2*SUM(H14,H17,H19)) -> 0 | M18: ADJ High Burn Thruster | P18: =INDEX(AP56:AQ88,MATCH(BA3,AP56:AP88,0),2) -> 0 | BC18: =$H$46/(0.01*BC8) -> 0 | BE18: =$H$46/(0.01*BE8) -> 0 | BG18: =$H$46/(0.01*BG8) -> 0 | BI18: =$H$46/(0.01*BI8) -> 0 | BK18: =$H$46/(0.01*BK8) -> 0 | BM18: =$H$46/(0.01*BM8) -> 0 | BO18: =$H$46/(0.01*BO8) -> 0 | BQ18: =$H$46/(0.01*BQ8) -> 0 | BS18: =$H$46/(0.01*BS8) -> 0 | BU18: =$H$46/(0.01*BU8) -> 0 | BW18: =$H$46/(0.01*BW8) -> 0
A19: M-Drive Mods: | B19: A Standard (None) | E19: =INDEX(S24:W48,MATCH(B19,S24:S48,0),4) -> 0 | F19: =IF(B14=S2,0,U49) -> 0 | H19: =IF(B14=S2,0,INDEX(S24:W48,MATCH(B19,S24:S48,0),2)+INDEX(S24:W48,MATCH(B20,S24:S48,0),2)+INDEX(S24:W48,MATCH(B21,S24:S48,0),2)) -> 0 | K19: =IF(B14=S2,0,INDEX(S24:W48,MATCH(B19,S24:S48,0),5)+INDEX(S24:W48,MATCH(B20,S24:S48,0),5)+INDEX(S24:W48,MATCH(B21,S24:S48,0),5)) -> 0 | T19: M-Drive | U19: Reaction | V19: FTL | W19: Solar | X19: Combine | Y19: M-Drive | Z19: Reaction | AA19: FTL | AB19: Solar | AE19: M | AF19: =Tonnage*AF2 -> 0.5 | AG19: =Tonnage*AG2 -> 1 | AH19: =Tonnage*AH2 -> 2 | AI19: =Tonnage*AI2 -> 3 | AJ19: =Tonnage*AJ2 -> 4 | AK19: =Tonnage*AK2 -> 5 | AL19: =Tonnage*AL2 -> 6 | AM19: =Tonnage*AM2 -> 7 | ... AQ19: =Tonnage*AQ2 -> 11
B20: A Standard (None) | D20: Effective # Mods | E20: =INDEX(S24:W48,MATCH(B20,S24:S48,0),4) -> 0 | M20: ADL B/U M-Drive | P20: =MIN(IF(BA2<0.01,0,INDEX(AG2:AQ17,16,MATCH(BA2,AG2:AQ2,0))),BB2) -> 0 | S20: Main Tonnage | T20: =IF(C11="No",U107,BF25) -> 100 | U20: =IF(C11="No",U110,BF26) -> 100 | V20: =IF(C11="No",U113,BF27) -> 100 | Y20: =INDEX(S2:T4,MATCH(B14,S2:S4,0),2)+INDEX(S69:T70,MATCH(B46,S69:S70,0),2) -> 0 | Z20: =INDEX(S2:T4,MATCH(B23,S2:S4,0),2)+INDEX(S14:T15,MATCH(B37,S14:S15,0),2) -> 0 | AA20: =INDEX(S5:T11,MATCH(B29,S5:S11,0),2)+INDEX(S5:T11,MATCH(B56,S5:S11,0),2)-IF(D29=0,0,5)-IF(D56=0,0,5) -> 0 | AE20: R | AF20: =Tonnage*AF4 -> 1 | AG20: =Tonnage*AG4 -> 2 | AH20: =Tonnage*AH4 -> 4 | AI20: =Tonnage*AI4 -> 6 | AJ20: =Tonnage*AJ4 -> 8 | AK20: =Tonnage*AK4 -> 10 | AL20: =Tonnage*AL4 -> 12 | AM20: =Tonnage*AM4 -> 14 | ... AV20: =Tonnage*AV4 -> 32 | BC20: =($H$56-5)/(0.025*BC8) -> -200 | BE20: =($H$56-5)/(0.025*BE8) -> -100 | BG20: =($H$56-5)/(0.025*BG8) -> -66.666667 | BI20: =($H$56-5)/(0.025*BI8) -> -50 | BK20: =($H$56-5)/(0.025*BK8) -> -40 | BM20: =($H$56-5)/(0.025*BM8) -> -33.333333 | BO20: =($H$56-5)/(0.025*BO8) -> -28.571429 | BQ20: =($H$56-5)/(0.025*BQ8) -> -25 | BS20: =($H$56-5)/(0.025*BS8) -> -22.222222
B21: A Standard (None) | D21: =INDEX(S24:AA49,MATCH(B19,S24:S49,0),9)+INDEX(S24:AA49,MATCH(B20,S24:S49,0),9)+INDEX(S24:AA49,MATCH(B21,S24:S49,0),9) -> 0 | E21: =INDEX(S24:W48,MATCH(B21,S24:S48,0),4) -> 0 | S21: Secondary Tonnage | T21: =IF(C11="No",U107,BF29) -> 100 | U21: =IF(C11="No",U110,BF30) -> 100 | V21: =IF(C11="No",U113,BF31) -> 100 | W21: =IF(C11="No",U110,BF32) -> 100 | AB21: Jump software: | AC21: =IF(RIGHT('6-Comp'!B32,1)="",0,RIGHT('6-Comp'!B32,1)) -> 0 | AD21: =INDEX(X10:AC16,MATCH(B29,X10:X16,0),6) -> 2 | AE21: F | AF21: 0 | AG21: =IF(AD21=1,Tonnage*AG7,MAX(10,(Tonnage*AG9))) -> 10 | AH21: =IF(AE21=1,Tonnage*AH7,MAX(10,(Tonnage*AH9))) -> 10 | AI21: =IF(AF21=1,Tonnage*AI7,MAX(10,(Tonnage*AI9))) -> 10 | AJ21: =IF(AG21=1,Tonnage*AJ7,MAX(10,(Tonnage*AJ9))) -> 10 | AK21: =IF(AH21=1,Tonnage*AK7,MAX(10,(Tonnage*AK9))) -> 12.5 | AL21: =IF(AI21=1,Tonnage*AL7,MAX(10,(Tonnage*AL9))) -> 15 | AM21: =IF(AJ21=1,Tonnage*AM7,MAX(10,(Tonnage*AM9))) -> 17.5 | AN21: =IF(AK21=1,Tonnage*AN7,MAX(10,(Tonnage*AN9))) -> 20 | AO21: =IF(AL21=1,Tonnage*AO7,MAX(10,(Tonnage*AO9))) -> 22.5 | AP21: =AC21-BJ27 -> #VALUE!
M22: ADJ B/U FTL | P22: =MIN(IF(H56<10.000001,MIN(D56,INDEX(AX6:BA12,MATCH(B56,AX6:AX12,0),3)),INDEX(AX6:BA12,MATCH(B56,AX6:AX12,0),3)),BB4) -> 0 | X22: Backup M | AB22: Jump | AK22: Backup Jump | AS22: Reaction | AX22: High Thrust
A23: Reaction Drive | B23: No Drive | C23: Rating | D23: 0 | E23: =INDEX(S2:V4,MATCH(B23,S2:S4,0),4)+SUM(E25:E27) -> 0 | F23: =INDEX(S2:U4,MATCH(B23,S2:S4,0),3)*'Ship Info'!G31 -> 0 | H23: =INDEX(S2:T4,MATCH(B23,S2:S4,0),2) -> 0 | S23: Thrust Mods | T23: Tonnage | U23: Cost | V23: TL | W23: Pwr | X23: Tons | Y23: cost | Z23: pwr | AA23: Mod Pt | AB23: Mods | AE23: Tons | AF23: Cost | AG23: Fuel | AH23: TL | AI23: Pwr | AJ23: Mod | AK23: Tons | AL23: Cost | AM23: Power | AN23: Mods | AS23: Tons | AT23: cost | AU23: Fuel | AV23: TL | AW23: Mods | AX23: Tons | AY23: Cost | AZ23: Fuel | BD23: Breakaway Drive Allocatioin
B24: Armored Bulkheads? | C24: No | F24: =IF(C24=S13,200000*H24," ") | H24: =IF(C24=S13,0.1*(H23+H25)," ") | M24: User Defined Mod | S24: A Standard (None) | T24: 0 | U24: 0 | V24: 0 | W24: 0 | X24: 0 | Y24: 0 | Z24: 0 | AA24: 0 | AB24: A Standard (None) | AE24: 0 | AF24: 0 | AG24: 0 | AH24: 0 | AI24: 0 | AJ24: 0 | AK24: 0 | AL24: 0 | AM24: 0 | AN24: A Standard (None) | AS24: 0 | AT24: 0 | AU24: 0 | AV24: 0 | AW24: 0 | AX24: 0 | AY24: 0 | AZ24: 0 | BG24: Main Hull Tons | BJ24: Combined Rating
A25: Reaction Mods Mods: | B25: A Standard (None) | E25: =INDEX(AN24:AZ42,MATCH(B25,AN24:AN42,0),9) -> 0 | F25: =IF(B23=T12,0,AT47) -> 0 | H25: =IF(B23=T12,0,INDEX(AN24:AZ42,MATCH(B25,AN24:AN42,0),6)+INDEX(AN24:AZ42,MATCH(B26,AN24:AN42,0),6)+INDEX(AN24:AZ42,MATCH(B27,AN24:AN42,0),6)) -> 0 | M25: X1 | S25: B1 Budget - Increased Size | T25: =0.25*T3 -> 0.125 | U25: =-0.25*F14 -> 0 | V25: 0 | W25: 0 | X25: =0.25*T70 -> 0.125 | Y25: =-0.25*(F46+F50) -> 0 | Z25: 0 | AA25: 3 | AB25: B1 Budget - Increased Size | AE25: =0.25*INDEX(S5:W11,MATCH(B29,S5:S11,0),2) -> 0 | AF25: =-0.25*F29 -> 0 | AG25: 0 | AH25: 0 | AI25: 0 | AJ25: 3 | AK25: =0.25*INDEX(X10:AB16,MATCH(B56,X10:X16,0),2) -> 0 | AL25: =-0.25*F56 -> 0 | AM25: 0 | AN25: B1 Budget - Increased Size | AS25: =0.25*T4 -> 0.25 | AT25: =-0.25*U4 -> -50000 | AU25: 0 | AV25: 0 | AW25: 3 | AX25: =0.25*T15 -> 0.25 | AY25: =-0.25*U15 -> -50000 | AZ25: 0 | BE25: Main M-Drive | BF25: 0 | BJ25: =IF(C11="No","N/A",IF(Y20=0,"N/A",IF(Y20>=AQ19,11,IF(Y20>=AP19,10,IF(Y20>=AO19,9,IF(Y20>=AN19,8,IF(Y20>=AM19,7,IF(Y20>=AL19,6,IF(Y20>=AK19,5,IF(Y20>=AJ19,4,IF(Y20>=AI19,3,IF(Y20>=AH19,2,IF(Y20>=AG19,1,IF(Y20>=AF19,0,"N/A")))))))))))))) -> N/A
B26: A Standard (None) | D26: Effective # Mods | E26: =INDEX(AN24:AZ42,MATCH(B26,AN24:AN42,0),9) -> 0 | N26: Multipliers | S26: B2 Budget - Inefficient | T26: 0 | U26: =-0.25*F14 -> 0 | V26: 0 | W26: =0.3*W3 -> 0.75 | X26: 0 | Y26: =-0.25*(F46+F50) -> 0 | Z26: =0.3*W70 -> 0.75 | AA26: 3 | AB26: B2 Budget - Inefficient | AE26: 0 | AF26: =-0.25*F29 -> 0 | AG26: 0 | AH26: 0 | AI26: =0.3*INDEX(S5:W11,MATCH(B29,S5:S11,0),5) -> 0 | AJ26: 3 | AK26: 0 | AL26: =-0.25*F56 -> 0 | AM26: =0.3*INDEX(X10:AB16,MATCH(B56,X10:X16,0),5) -> 0 | AN26: B2 Budget - Fuel Inefficient | AS26: 0 | AT26: =-0.25*U4 -> -50000 | AU26: 0.25 | AV26: 0 | AW26: 3 | AX26: 0 | AY26: =-0.25*U15 -> -50000 | AZ26: 0.25 | BE26: Main Reaction Drive | BF26: 0 | BJ26: =IF(C11="No","N/A",IF(Z20=0,"N/A",IF(Z20>=AV20,16,IF(Z20>=AU20,15,IF(Z20>=AT20,14,IF(Z20>=AS20,13,IF(Z20>=AR20,12,IF(Z20>=AQ20,11,IF(Z20>=AP20,10,IF(Z20>=AO20,9,IF(Z20>=AN20,8,IF(Z20>=AM20,7,IF(Z20>=AL20,6,IF(Z20>=AK20,5,IF(Z20>=AJ20,4,IF(Z20>=AI20,3,IF(Z20>=AH20,2,IF(Z20>=AG20,1,IF(Z20>=AF20,0,"N/A"))))))))))))))))))) -> N/A
B27: A Standard (None) | D27: =INDEX(AN24:AZ42,MATCH(B25,AN24:AN42,0),10)+INDEX(AN24:AZ42,MATCH(B26,AN24:AN42,0),10)+INDEX(AN24:AZ42,MATCH(B27,AN24:AN42,0),10) -> 0 | E27: =INDEX(AN24:AZ42,MATCH(B27,AN24:AN42,0),9) -> 0 | M27: DTons | N27: Cost | O27: Power | P27: Fuel | Q27: TL | R27: # Mods | S27: B3 Budget Limited Range | T27: 0 | U27: =-0.25*F14 -> 0 | V27: 0 | W27: 0 | X27: 0 | Y27: =-0.25*(F46+F50) -> 0 | Z27: 0 | AA27: 3 | AB27: C1 Advanced Cost Reduction* | AE27: 0 | AF27: =-0.1*F29 -> 0 | AG27: 0 | AH27: 1 | AI27: 0 | AJ27: 3 | AK27: 0 | AL27: =-0.1*F56 -> 0 | AM27: 0 | AN27: C1 Advanced Cost Reduction* | AS27: 0 | AT27: =-0.1*U4 -> -20000 | AU27: 0 | AV27: 1 | AW27: 3 | AX27: 0 | AY27: =-0.1*U15 -> -20000 | AZ27: 0 | BE27: Main FTL Drive | BF27: 0 | BJ27: =IF(C11="No","N/A",IF(AA20=0,"N/A",IF(AA20>=AO21,9,IF(AA20>=AN21,8,IF(AA20>=AM21,7,IF(AA20>=AL21,6,IF(AA20>=AK21,5,IF(AA20>=AJ21,4,IF(AA20>=AI21,3,IF(AA20>=AH21,2,IF(AA20>=AG21,1,IF(AA20>=AF21,0,"N/A")))))))))))) -> N/A | BK27: =IF(BJ27="N/A","",IF(AP21<0,"Limited to J"&AC21,""))
M28: 0 | N28: 0 | O28: 0 | P28: 0 | S28: C1 Advanced Cost Reduction* | T28: 0 | U28: =-0.1*F14 -> 0 | V28: 1 | W28: 0 | X28: 0 | Y28: =-0.1*(F46+F50) -> 0 | Z28: 0 | AA28: 3 | AB28: C2 Very Advanced Cost Reduction* | AE28: 0 | AF28: =-0.2*F29 -> 0 | AG28: 0 | AH28: 2 | AI28: 0 | AJ28: 3 | AK28: 0 | AL28: =-0.2*F56 -> 0 | AM28: 0 | AN28: C2 Very Advanced Cost Reduction* | AS28: 0 | AT28: =-0.15*U4 -> -30000 | AU28: 0 | AV28: 2 | AW28: 3 | AX28: 0 | AY28: =-0.15*U15 -> -30000 | AZ28: 0 | BG28: Secondary Hull Tons
A29: FTL Drive | B29: No FTL | C29: Rating | D29: 0 | E29: =INDEX(S5:W11,MATCH(B29,S5:S11,0),4)+SUM(E32:E34) -> 0 | F29: =IF(D29=0,0,INDEX(S5:W11,MATCH(B29,S5:S11,0),3))*'Ship Info'!G31 -> 0 | H29: =IF(D29=0,0,INDEX(S5:W11,MATCH(B29,S5:S11,0),2)) -> 0 | K29: =INDEX(S5:W11,MATCH(B29,S5:S11,0),5) -> 0 | R29: =IF(N28=0,R28,3) -> 0 | S29: C2 Very Advanced Cost Reduction* | T29: 0 | U29: =-0.15*F14 -> 0 | V29: 2 | W29: 0 | X29: 0 | Y29: =-0.15*(F46+F50) -> 0 | Z29: 0 | AA29: 3 | AB29: C3 High Tech Cost Reduction* | AE29: 0 | AF29: =-0.3*F29 -> 0 | AG29: 0 | AH29: 3 | AI29: 0 | AJ29: 3 | AK29: 0 | AL29: =-0.3*F56 -> 0 | AM29: 0 | AN29: C3 High Tech Cost Reduction* | AS29: 0 | AT29: =-0.2*U4 -> -40000 | AU29: 0 | AV29: 3 | AW29: 3 | AX29: 0 | AY29: =-0.2*U15 -> -40000 | AZ29: 0 | BE29: Secondary M-Drive | BF29: 0
B30: EMP Hardened? | C30: No | F30: =IF(C30=S13,0.5*(F29+F32)," ") | S30: C3 High Tech Cost Reduction* | T30: 0 | U30: =-0.2*F14 -> 0 | V30: 3 | W30: 0 | X30: 0 | Y30: =-0.2*(F46+F50) -> 0 | Z30: 0 | AA30: 3 | AB30: D1 Advanced Decreased Jump Fuel | AE30: 0 | AF30: 0 | AG30: -0.05 | AH30: 1 | AI30: 0 | AJ30: 1 | AK30: 0 | AL30: 0 | AM30: 0 | AN30: D1 Advanced - Fuel Efficient | AS30: 0 | AT30: 0 | AU30: -0.2 | AV30: 1 | AW30: 1 | AX30: 0 | AY30: 0 | AZ30: -0.2 | BE30: Secondary Reaction Drive | BF30: 0
B31: Armored Bulkheads? | C31: No | F31: =IF(C31=S13,200000*H31," ") | H31: =IF(C31=S13,0.1*(H29+H32)," ") | M31: User Defined Mod | S31: D1 Advanced - Energy Efficient | T31: 0 | U31: 0 | V31: 1 | W31: =-0.25*W3 -> -0.625 | X31: 0 | Y31: 0 | Z31: =-0.25*W70 -> -0.625 | AA31: 1 | AB31: D2 Advanced - Early Jump | AE31: 0 | AF31: 0 | AG31: 0 | AH31: 1 | AI31: 0 | AJ31: 1 | AK31: 0 | AL31: 0 | AM31: 0 | AN31: D2 Advanced - Reduced Size | AS31: =-0.1*T4 -> -0.1 | AT31: 0 | AU31: 0 | AV31: 1 | AW31: 1 | AX31: =-0.1*T15 -> -0.1 | AY31: 0 | AZ31: 0 | BE31: Secondary FTL Drive | BF31: 0
A32: FTL Mods: | B32: A Standard (None) | E32: =INDEX(AB24:AM48,MATCH(B32,AB24:AB48,0),7) -> 0 | F32: =AE51 -> 0 | H32: =IF(D29=0,0,INDEX(AB24:AM48,MATCH(B32,AB24:AB48,0),4)+INDEX(AB24:AM48,MATCH(B33,AB24:AB48,0),4)+INDEX(AB24:AM48,MATCH(B34,AB24:AB48,0),4)) -> 0 | K32: =IF(B29=S5,0,INDEX(AB24:AM48,MATCH(B32,AB24:AB48,0),8)+INDEX(AB24:AM48,MATCH(B33,AB24:AB48,0),8)+INDEX(AB24:AM48,MATCH(B34,AB24:AB48,0),8)) -> 0 | M32: X2 | S32: D2 Advanced - Reduced Size | T32: =-0.1*T3 -> -0.05 | U32: 0 | V32: 1 | W32: 0 | X32: =-0.1*T70 -> -0.05 | Y32: 0 | Z32: 0 | AA32: 1 | AB32: D3 Advanced - Energy Efficient | AE32: 0 | AF32: 0 | AG32: 0 | AH32: 1 | AI32: =-0.25*INDEX(S5:W11,MATCH(B29,S5:S11,0),5) -> 0 | AJ32: 1 | AK32: 0 | AL32: 0 | AM32: =-0.25*INDEX(X10:AB16,MATCH(B56,X10:X16,0),5) -> 0 | AN32: D3 Advanced - Easy to Repair | AS32: 0 | AT32: 0 | AU32: 0 | AV32: 1 | AW32: 1 | AX32: 0 | AY32: 0 | AZ32: 0 | BE32: Solar Sails | BF32: 0
B33: A Standard (None) | D33: Effective # Mods | E33: =INDEX(AB24:AM48,MATCH(B33,AB24:AB48,0),7) -> 0 | N33: Multipliers | S33: D3 Advanced - Easy to Repair | T33: 0 | U33: 0 | V33: 1 | W33: 0 | X33: 0 | Y33: 0 | Z33: 0 | AA33: 1 | AB33: D4 Advanced - Reduced Size | AE33: =-0.1*INDEX(S5:W11,MATCH(B29,S5:S11,0),2) -> 0 | AF33: 0 | AG33: 0 | AH33: 1 | AI33: 0 | AJ33: 1 | AK33: =-0.1*INDEX(X10:AB16,MATCH(B56,X10:X16,0),2) -> 0 | AL33: 0 | AM33: 0 | AN33: D4 Very Advanced- Stealth | AS33: 0 | AT33: 0 | AU33: 0 | AV33: 2 | AW33: 2 | AX33: 0 | AY33: 0 | AZ33: 0
B34: A Standard (None) | D34: =INDEX(AB24:AM48,MATCH(B32,AB24:AB48,0),9)+INDEX(AB24:AM48,MATCH(B33,AB24:AB48,0),9)+INDEX(AB24:AM48,MATCH(B34,AB24:AB48,0),9) -> 0 | E34: =INDEX(AB24:AM48,MATCH(B34,AB24:AB48,0),7) -> 0 | M34: DTons | N34: Cost | O34: Power | P34: Fuel | Q34: TL | R34: # Mods | S34: D4 Advanced - Low Emissions | T34: 0 | U34: 0 | V34: 1 | W34: 0 | X34: 0 | Y34: 0 | Z34: 0 | AA34: 1 | AB34: D5 Advanced - Easy to Repair | AE34: 0 | AF34: 0 | AG34: 0 | AH34: 1 | AI34: 0 | AJ34: 1 | AK34: 0 | AL34: 0 | AM34: 0 | AN34: Pa Prototype - Increased Size | AS34: =0.25*T4 -> 0.25 | AT34: =5*U4 -> 1000000 | AU34: 0 | AV34: -1 | AW34: 3 | AX34: =0.25*T15 -> 0.25 | AY34: =5*U15 -> 1000000 | AZ34: 0 | BD34: Main and Secondary Tons can use alternate tonnages in their calculations.
M35: 0 | N35: 0 | O35: 0 | P35: 0 | Q35: 0 | R35: 0 | S35: E Concealed Drive | T35: =INDEX(AF1:AQ3,2,MATCH(D14*2,AF1:AQ1,0))*Tonnage-H14+0.25*INDEX(AF1:AQ3,2,MATCH(D14*2,AF1:AQ1,0))*Tonnage -> 0.625 | U35: -1e-09 | V35: =INDEX(AF1:AV3,3,MATCH(D14*2,AF1:AV1,0))-INDEX(AF1:AV3,3,MATCH(D14,AF1:AV1,0)) -> 0 | W35: 0 | X35: =INDEX(AF1:AQ3,2,MATCH(D46*2,AF1:AQ1,0))*Tonnage-H46+0.25*INDEX(AF1:AQ3,2,MATCH(D46*2,AF1:AQ1,0))*Tonnage -> 0.625 | Y35: -1e-09 | Z35: =INDEX(AF1:AQ3,3,MATCH(D46*2,AF1:AQ1,0))-INDEX(AF1:AQ3,3,MATCH(D46,AF1:AQ1,0)) -> 0 | AA35: 0 | AB35: E1 Very Advanced - Stealth Jump | AE35: 0 | AF35: 0 | AG35: 0 | AH35: 2 | AI35: 0 | AJ35: 2 | AK35: 0 | AL35: 0 | AM35: 0 | AN35: Pb Prototype - Fuel Inefficient | AS35: 0 | AT35: =5*U4 -> 1000000 | AU35: 0.25 | AV35: -1 | AW35: 3 | AX35: 0 | AY35: =5*U15 -> 1000000 | AZ35: 0.25
A36: Secondary Drive(s) | R36: =IF(N35=0,R35,3) -> 0 | S36: Pa Prototype - Increased Size | T36: =0.25*T3 -> 0.125 | U36: =5*F14 -> 0 | V36: -1 | W36: 0 | X36: =0.25*T70 -> 0.125 | Y36: =5*(F46+F50) -> 0 | Z36: 0 | AA36: 3 | AB36: Pa Prototype - Increased Size | AE36: =0.25*INDEX(S5:W11,MATCH(B29,S5:S11,0),2) -> 0 | AF36: =5*F29 -> 0 | AG36: 0 | AH36: -1 | AI36: 0 | AJ36: 3 | AK36: =0.25*INDEX(X10:AB16,MATCH(B56,X10:X16,0),2) -> 0 | AL36: =5*F56 -> 0 | AM36: 0 | AN36: Ta Early Prototype - Increased Size x2 | AS36: =1.5*T4 -> 1.5 | AT36: =10*U4 -> 2000000 | AU36: 0 | AV36: -2 | AW36: 3 | AX36: =1.5*T15 -> 1.5 | AY36: =10*U15 -> 2000000 | AZ36: 0 | BD36: Note: Checking combined perfomance of breakaway ships and entering full tonnage
A37: Reaction Drive | B37: No High Burn Thruster | C37: Rating | D37: 0 | E37: =INDEX(S14:V15,MATCH(B37,S14:S15,0),4)+SUM(E39:E41) -> 0 | F37: =INDEX(S14:V15,MATCH(B37,S14:S15,0),3)*'Ship Info'!G31 -> 0 | H37: =INDEX(S14:V15,MATCH(B37,S14:S15,0),2) -> 0 | S37: Pb Prototype - Inefficient | T37: 0 | U37: =5*F14 -> 0 | V37: -1 | W37: =0.3*W3 -> 0.75 | X37: =-0.2*INDEX(S69:T71,MATCH(B46,S69:S71,0),2) -> 0 | Y37: =5*(F46+F50) -> 0 | Z37: =0.3*W70 -> 0.75 | AA37: 3 | AB37: Pb Prototype - Inefficient | AE37: 0 | AF37: =5*F29 -> 0 | AG37: 0 | AH37: -1 | AI37: =0.3*INDEX(S5:W11,MATCH(B29,S5:S11,0),5) -> 0 | AJ37: 3 | AK37: 0 | AL37: =5*F56 -> 0 | AM37: =0.3*INDEX(X10:AB16,MATCH(B56,X10:X16,0),5) -> 0 | AN37: Tb Early Prototype - Fuel Inefficient x2 | AS37: =1*T4 -> 1 | AT37: =10*U4 -> 2000000 | AU37: 0.5 | AV37: -2 | AW37: 3 | AX37: =T15 -> 1 | AY37: =10*U15 -> 2000000 | AZ37: 0.5 | BD37: gives you the combined rating for Main and B/U drives working in concert.
B38: Armored Bulkheads? | C38: No | F38: =IF(C38=S13,200000*H38," ") | H38: =IF(C38=S13,0.1*(H37+H39)," ") | M38: User Defined Mod | S38: Pc Prototype - Limited Range | T38: 0 | U38: =5*F14 -> 0 | V38: -1 | W38: 0 | X38: 0 | Y38: =5*(F46+F50) -> 0 | Z38: 0 | AA38: 3 | AB38: Pc Prototype - Late Jump | AE38: 0 | AF38: =5*F29 -> 0 | AG38: 0 | AH38: -1 | AI38: 0 | AJ38: 3 | AK38: 0 | AL38: =5*F56 -> 0 | AM38: 0 | AN38: Tc Early Prototype - Increased Size, Fuel Inefficient | AS38: =1*T4 -> 1 | AT38: =10*U4 -> 2000000 | AU38: 0.25 | AV38: -2 | AW38: 3 | AX38: =T15 -> 1 | AY38: =10*U15 -> 2000000 | AZ38: 0.25
A39: Reaction Mods Mods: | B39: A Standard (None) | E39: =INDEX(AN24:AZ42,MATCH(B39,AN24:AN42,0),9) -> 0 | F39: =AY47 -> 0 | H39: =INDEX(AN24:AZ42,MATCH(B39,AN24:AN42,0),11)+INDEX(AN24:AZ42,MATCH(B40,AN24:AN42,0),11)+INDEX(AN24:AZ42,MATCH(B41,AN24:AN42,0),11) -> 0 | M39: X3 | S39: Ta Early Prototype - Orbital Range | T39: =1*T3 -> 0.5 | U39: =10*F14 -> 0 | V39: -2 | W39: 0 | X39: =1*T70 -> 0.5 | Y39: =10*(F46+F50) -> 0 | Z39: 0 | AA39: 3 | AB39: Ta Early Prototype Late Jump x2 | AE39: =1*INDEX(S5:W11,MATCH(B29,S5:S11,0),2) -> 0 | AF39: =10*F29 -> 0 | AG39: 0 | AH39: -3 | AI39: 0 | AJ39: 3 | AK39: =1*INDEX(X10:AB16,MATCH(B56,X10:X16,0),2) -> 0 | AL39: =10*F56 -> 0 | AM39: 0 | AN39: =M25&" "&N25 -> X1 | AS39: =T4*M28 -> 0 | AT39: =U4*N28 -> 0 | AU39: =P28 -> 0 | AV39: =Q28 -> 0 | AW39: =R29 -> 0 | AX39: =T15*M28 -> 0 | AY39: =U15*N28 -> 0 | AZ39: =P28 -> 0 | BD39: The Combined Rating above does not allow you to jump farther than the jump your software is rated for.
B40: A Standard (None) | D40: Effective # Mods | E40: =INDEX(AN24:AZ42,MATCH(B40,AN24:AN42,0),9) -> 0 | N40: Multipliers | S40: Tb Early Prototype - Increased Size x2 | T40: =1.5*T3 -> 0.75 | U40: =10*F14 -> 0 | V40: -2 | W40: 0 | X40: =1.5*T70 -> 0.75 | Y40: =10*(F46+F50) -> 0 | Z40: 0 | AA40: 3 | AB40: Tb Early Prototype - Increased Size x2 | AE40: =1.5*INDEX(S5:W11,MATCH(B29,S5:S11,0),2) -> 0 | AF40: =10*F29 -> 0 | AG40: 0 | AH40: -2 | AI40: 0 | AJ40: 3 | AK40: =1.5*INDEX(X10:AB16,MATCH(B56,X10:X16,0),2) -> 0 | AL40: =10*F56 -> 0 | AM40: 0 | AN40: =M32&" "&N32 -> X2 | AS40: =T4*M35 -> 0 | AT40: =U4*N35 -> 0 | AU40: =P35 -> 0 | AV40: =Q35 -> 0 | AW40: =R36 -> 0 | AX40: =T15*M35 -> 0 | AY40: =U15*N35 -> 0 | AZ40: =P35 -> 0
B41: A Standard (None) | D41: =INDEX(AN24:AZ42,MATCH(B39,AN24:AN42,0),10)+INDEX(AN24:AZ42,MATCH(B40,AN24:AN42,0),10)+INDEX(AN24:AZ42,MATCH(B41,AN24:AN42,0),10) -> 0 | E41: =INDEX(AN24:AZ42,MATCH(B41,AN24:AN42,0),9) -> 0 | M41: DTons | N41: Cost | O41: Power | P41: Fuel | Q41: TL | R41: # Mods | S41: Tc Early Prototype - Inefficient x2 | T41: =1*T3 -> 0.5 | U41: =10*F14 -> 0 | V41: -2 | W41: =0.6*W3 -> 1.5 | X41: =1*T70 -> 0.5 | Y41: =10*(F46+F50) -> 0 | Z41: =0.6*W70 -> 1.5 | AA41: 3 | AB41: Tc Early Prototype - Inefficient x2 | AE41: =1*INDEX(S5:W11,MATCH(B29,S5:S11,0),2) -> 0 | AF41: =10*F29 -> 0 | AG41: 0 | AH41: -2 | AI41: =0.6*INDEX(S5:W11,MATCH(B29,S5:S11,0),5) -> 0 | AJ41: 3 | AK41: =1*INDEX(X10:AB16,MATCH(B56,X10:X16,0),2) -> 0 | AL41: =10*F56 -> 0 | AM41: =0.6*INDEX(X10:AB16,MATCH(B56,X10:X16,0),5) -> 0 | AN41: =M39&" "&N39 -> X3 | AS41: =T4*M42 -> 0 | AT41: =U4*N42 -> 0 | AU41: =P42 -> 0 | AV41: =Q42 -> 0 | AW41: =R43 -> 0 | AX41: =T15*M42 -> 0 | AY41: =U15*N42 -> 0 | AZ41: =P42 -> 0
M42: 0 | N42: 0 | O42: 0 | P42: 0 | Q42: 0 | R42: 0 | S42: Td Early Prototype - Increased Size, Inefficient | T42: =1.25*T3 -> 0.625 | U42: =10*F14 -> 0 | V42: -2 | W42: =0.3*W3 -> 0.75 | X42: =1.25*T70 -> 0.625 | Y42: =10*(F46+F50) -> 0 | Z42: =0.3*W70 -> 0.75 | AA42: 3 | AB42: Td Early Prototype - Increased Size, Inefficient | AE42: =1.25*INDEX(S5:W11,MATCH(B29,S5:S11,0),2) -> 0 | AF42: =10*F29 -> 0 | AG42: 0 | AH42: -2 | AI42: =0.3*INDEX(S5:W11,MATCH(B29,S5:S11,0),5) -> 0 | AJ42: 3 | AK42: =1.25*INDEX(X10:AB16,MATCH(B56,X10:X16,0),2) -> 0 | AL42: =10*F56 -> 0 | AM42: =0.3*INDEX(X10:AB16,MATCH(B56,X10:X16,0),5) -> 0 | AN42: =M46&" "&N46 -> X4 | AS42: =T4*M49 -> 0 | AT42: =U4*N49 -> 0 | AU42: =P49 -> 0 | AV42: =Q49 -> 0 | AW42: =R50 -> 0 | AX42: =T15*M49 -> 0 | AY42: =U15*N49 -> 0 | AZ42: =P49 -> 0
R43: =IF(N42=0,R42,3) -> 0 | S43: Te Early Prototype- Increased Size, Limit Rng | T43: =1.25*T3 -> 0.625 | U43: =10*F14 -> 0 | V43: -2 | W43: 0 | X43: =1.25*T70 -> 0.625 | Y43: =10*(F46+F50) -> 0 | Z43: 0 | AA43: 3 | AB43: Te Early Prototype Late Jump, Inefficient | AE43: =1*INDEX(S5:W11,MATCH(B29,S5:S11,0),2) -> 0 | AF43: =10*F29 -> 0 | AG43: 0 | AH43: -2 | AI43: =0.3*INDEX(S5:W11,MATCH(B29,S5:S11,0),5) -> 0 | AJ43: 3 | AK43: =1*INDEX(X10:AB16,MATCH(B56,X10:X16,0),2) -> 0 | AL43: =10*F56 -> 0 | AM43: =0.3*INDEX(X10:AB16,MATCH(B56,X10:X16,0),5) -> 0
B44: No Solar Sails | C44: Rating | D44: =INDEX(S16:W17,MATCH(B44,S16:S17,0),5) | F44: =INDEX(S16:W17,MATCH(B44,S16:S17,0),3)*'Ship Info'!G31 -> 0 | H44: =INDEX(S16:W17,MATCH(B44,S16:S17,0),2) -> 0 | S44: Tf Early Prototype- Inefficient, Limit Rng | T44: =1*T3 -> 0.5 | U44: =10*F14 -> 0 | V44: -2 | W44: =0.3*W3 -> 0.75 | X44: =1*T70 -> 0.5 | Y44: =10*(F46+F50) -> 0 | Z44: =0.3*W70 -> 0.75 | AA44: 3 | AB44: Tf Early Prototype Increased Size, Late Jump | AE44: =1.25*INDEX(S5:W11,MATCH(B29,S5:S11,0),2) -> 0 | AF44: =10*F29 -> 0 | AG44: 0 | AH44: -2 | AI44: 0 | AJ44: 3 | AK44: =1.25*INDEX(X10:AB16,MATCH(B56,X10:X16,0),2) -> 0 | AL44: =10*F56 -> 0 | AM44: 0
M45: User Defined Mod | S45: =M25&" "&N25 -> X1 | T45: =M28*T3 -> 0 | U45: =N28*F14 -> 0 | V45: =Q28 -> 0 | W45: =O28*W3 -> 0 | X45: =M28*T70 -> 0 | Y45: =N28*F46 -> 0 | Z45: =O28*W70 -> 0 | AA45: =R29 -> 0 | AB45: =M25&" "&N25 -> X1 | AE45: =M28*INDEX(S5:W11,MATCH(B29,S5:S11,0),2) -> 0 | AF45: =N28*F29 -> 0 | AG45: =P28 -> 0 | AH45: =Q28 -> 0 | AI45: =O28*INDEX(S5:W11,MATCH(B29,S5:S11,0),5) -> 0 | AJ45: =R29 -> 0 | AK45: =M29*INDEX(X10:AB16,MATCH(B56,X10:X16,0),2) -> 0 | AL45: =N28*F56 -> 0 | AM45: =O28*INDEX(X10:AB16,MATCH(B56,X10:X16,0),5) -> 0
A46: M-Drive | B46: No Back Up Drive | C46: Rating | D46: 0 | E46: =INDEX(S69:W71,MATCH(B46,S69:S71,0),4)+SUM(E52:E54) -> 0 | F46: =INDEX(S69:W71,MATCH(B46,S69:S71,0),3)*'Ship Info'!G31 -> 0 | H46: =INDEX(S69:W71,MATCH(B46,S69:S71,0),2) -> 0 | K46: =INDEX(S69:W71,MATCH(B46,S69:S71,0),5) -> 0 | M46: X4 | S46: =M32&" "&N32 -> X2 | T46: =M35*T3 -> 0 | U46: =N35*F14 -> 0 | V46: =Q35 -> 0 | W46: =O35*W3 -> 0 | X46: =M35*T70 -> 0 | Y46: =N35*F46 -> 0 | Z46: =O35*W70 -> 0 | AA46: =R36 -> 0 | AB46: =M32&" "&N32 -> X2 | AE46: =M35*INDEX(S5:W11,MATCH(B29,S5:S11,0),2) -> 0 | AF46: =N35*F29 -> 0 | AG46: =P35 -> 0 | AH46: =Q35 -> 0 | AI46: =O35*INDEX(S5:W11,MATCH(B29,S5:S11,0),5) -> 0 | AJ46: =R36 -> 0 | AK46: =R36*INDEX(X10:AB16,MATCH(B56,X10:X16,0),2) -> 0 | AL46: =N36*F56 -> 0 | AM46: =O36*INDEX(X10:AB16,MATCH(B56,X10:X16,0),5) -> 0 | AP46: Mn Reac | BA46: HBT Fuel
B47: EMP Hardened? | C47: No | F47: =IF(C47=S13,0.5*(SUM(F46,F49,F52))," ") | N47: Multipliers | S47: =M39&" "&N39 -> X3 | T47: =M42*T3 -> 0 | U47: =N42*F14 -> 0 | V47: =Q42 -> 0 | W47: =O42*W3 -> 0 | X47: =M42*T70 -> 0 | Y47: =N42*F46 -> 0 | Z47: =O42*W70 -> 0 | AA47: =R43 -> 0 | AB47: =M39&" "&N39 -> X3 | AE47: =M42*INDEX(S5:W11,MATCH(B29,S5:S11,0),2) -> 0 | AF47: =N42*F29 -> 0 | AG47: =P42 -> 0 | AH47: =Q42 -> 0 | AI47: =O42*INDEX(S5:W11,MATCH(B29,S5:S11,0),5) -> 0 | AJ47: =R43 -> 0 | AK47: =M43*INDEX(X10:AB16,MATCH(B56,X10:X16,0),2) -> 0 | AL47: =N42*F56 -> 0 | AM47: =O42*INDEX(X10:AB16,MATCH(B56,X10:X16,0),5) -> 0 | AP47: Fuel | AQ47: =SUM(1,AQ48:AQ50) -> 1 | AS47: Mods | AT47: =IF(SUM(AT48:AT50)=0,INDEX(Y3:AA6,MATCH(SUM(E25:E27),Y3:Y6,0),3)*F23,SUM(AT48:AT50)) -> 0 | AX47: Mods | AY47: =IF(SUM(AY48:AY50)=0,INDEX(Y3:AA6,MATCH(SUM(E39:E41),Y3:Y6,0),3)*F37,SUM(AY48:AY50)) -> 0 | BA47: =SUM(1,BA48:BA50) -> 1
B48: Armored Bulkheads? | C48: No | F48: =IF(C48=S13,200000*H48," ") | H48: =IF(C48=S13,0.1*(SUM(H46,H49,H52))," ") | M48: DTons | N48: Cost | O48: Power | P48: Fuel | Q48: TL | R48: # Mods | S48: =M46&" "&N46 -> X4 | T48: =M49*T3 -> 0 | U48: =N49*F14 -> 0 | V48: =Q49 -> 0 | W48: =O49*W3 -> 0 | X48: =M49*T70 -> 0 | Y48: =N49*F46 -> 0 | Z48: =O49*W70 -> 0 | AA48: =R50 -> 0 | AB48: =M46&" "&N46 -> X4 | AE48: =M49*INDEX(S5:W11,MATCH(B29,S5:S11,0),2) -> 0 | AF48: =N49*F29 -> 0 | AG48: =P49 -> 0 | AH48: =Q49 -> 0 | AI48: =O49*INDEX(S5:W11,MATCH(B29,S5:S11,0),5) -> 0 | AJ48: =R50 -> 0 | AK48: =M50*INDEX(X10:AB16,MATCH(B56,X10:X16,0),2) -> 0 | AL48: =N49*F56 -> 0 | AM48: =O49*INDEX(X10:AB16,MATCH(B56,X10:X16,0),5) -> 0 | AQ48: =INDEX($AN$24:$AV$42,MATCH(B25,$AN$24:$AN$42,0),8) -> 0 | AS48: 1 | AT48: =INDEX($AN$24:$AV$42,MATCH(B25,$AN$24:$AN$42,0),7) -> 0 | AX48: 1 | AY48: =INDEX($AN$24:$AZ$42,MATCH(B39,$AN$24:$AN$42,0),12) -> 0 | BA48: =INDEX($AN$24:$AZ$42,MATCH(B39,$AN$24:$AN$42,0),13) -> 0
B49: Deep Space Manoeuvering System? | C49: No | D49: =IF(C49=S13,(AA1-8)*5&"% Efficiency","") | F49: =IF(C49=S13,0.6*SUM(F46,F52:F54),0) -> 0 | H49: =IF(C49=S13,SUM(H46,H52:H54)*((200-((AA1-9)*25))/100)," ") | K49: =IF(C49=S13,SUM(K46,K52:K54)*3,"") | M49: 0 | N49: 0 | O49: 0 | P49: 0 | Q49: 0 | R49: 0 | T49: Mods Cr | U49: =IF(SUM(U50:U52)=0,INDEX(Y3:AA6,MATCH(SUM(E19:E21),Y3:Y6,0),3)*F14,SUM(U50:U52)) -> 0 | X49: Mods Cr | Y49: =IF(SUM(Y50:Y52)=0,INDEX(Y3:AA6,MATCH(SUM(E52:E54),Y3:Y6,0),3)*F46,SUM(Y50:Y52)) -> 0 | AG49: MnFTL | AI49: BU FTL | AQ49: =INDEX($AN$24:$AV$42,MATCH(B26,$AN$24:$AN$42,0),8) -> 0 | AS49: 2 | AT49: =INDEX($AN$24:$AV$42,MATCH(B26,$AN$24:$AN$42,0),7) -> 0 | AX49: 2 | AY49: =INDEX($AN$24:$AZ$42,MATCH(B40,$AN$24:$AN$42,0),12) -> 0 | BA49: =INDEX($AN$24:$AZ$42,MATCH(B40,$AN$24:$AN$42,0),13) -> 0
B50: Short Duration Maneuver Drive (SDM)? | C50: No | D50: =IF(C50=S14,(AA2-8)*5&"% Efficiency","") | F50: =IF(C50="No",0,F46*-0.9) -> 0 | R50: =IF(N49=0,R49,3) -> 0 | S50: Backups | T50: 1 | U50: =INDEX($S$24:$U$48,MATCH(B19,$S$24:$S$48,0),3) -> 0 | X50: 1 | Y50: =INDEX($S$24:$AA$48,MATCH(B52,$S$24:$S$48,0),7) -> 0 | AG50: Fuel | AI50: Fuel | AQ50: =INDEX($AN$24:$AV$42,MATCH(B27,$AN$24:$AN$42,0),8) -> 0 | AS50: 3 | AT50: =INDEX($AN$24:$AV$42,MATCH(B27,$AN$24:$AN$42,0),7) -> 0 | AX50: 3 | AY50: =INDEX($AN$24:$AZ$42,MATCH(B41,$AN$24:$AN$42,0),12) -> 0 | BA50: =INDEX($AN$24:$AZ$42,MATCH(B41,$AN$24:$AN$42,0),13) -> 0
B51: Variable Emission Drive? | C51: No | F51: =IF(C51="No",0,4*SUM(F46,F49:F50,F52,)) -> 0 | H51: =IF(C51="No",0,0.2*SUM(H47,H49:H50,H52)) -> 0 | S51: Mains | T51: 2 | U51: =INDEX($S$24:$U$48,MATCH(B20,$S$24:$S$48,0),3) -> 0 | X51: 2 | Y51: =INDEX($S$24:$AA$48,MATCH(B53,$S$24:$S$48,0),7) -> 0 | AD51: Mods | AE51: =IF(SUM(AE52:AE54)=0,INDEX(Y3:AA6,MATCH(SUM(E32:E34),Y3:Y6,0),3)*F29,SUM(AE52:AE54)) -> 0 | AG51: =SUM(1,AG52:AG54) -> 1 | AI51: =SUM(1,AI52:AI54) -> 1 | AK51: mods | AL51: =IF(SUM(AL52:AL54)=0,INDEX(Y3:AA6,MATCH(SUM(E59:E61),Y3:Y6,0),3)*F56,SUM(AL52:AL54)) -> 0
A52: M-Drive Mods: | B52: A Standard (None) | E52: =INDEX($S$24:$AA$48,MATCH(B52,$S$24:$S$48,0),4) -> 0 | F52: =Y49 -> 0 | H52: =INDEX(S24:AA48,MATCH(B52,S24:S48,0),6)+INDEX(S24:AA48,MATCH(B53,S24:S48,0),6)+INDEX(S24:AA48,MATCH(B54,S24:S48,0),6) -> 0 | K52: =INDEX(S24:AA48,MATCH(B52,S24:S48,0),8)+INDEX(S24:AA48,MATCH(B53,S24:S48,0),8)+INDEX(S24:AA48,MATCH(B54,S24:S48,0),8) -> 0 | T52: 3 | U52: =INDEX($S$24:$U$48,MATCH(B21,$S$24:$S$48,0),3) -> 0 | X52: 3 | Y52: =INDEX($S$24:$AA$48,MATCH(B54,$S$24:$S$48,0),7) -> 0 | AD52: 1 | AE52: =INDEX($AB$24:$AM$48,MATCH(B32,$AB$24:$AB$48,0),5) -> 0 | AG52: =INDEX($AB$24:$AM$48,MATCH(B32,$AB$24:$AB$48,0),6) -> 0 | AI52: =INDEX($AB$24:$AM$48,MATCH(B59,$AB$24:$AB$48,0),6) -> 0 | AK52: 1 | AL52: =INDEX($AB$24:$AM$48,MATCH(B59,$AB$24:$AB$48,0),11) -> 0
B53: A Standard (None) | D53: Effective # Mods | E53: =INDEX($S$24:$AA$48,MATCH(B53,$S$24:$S$48,0),4) -> 0 | S53: Backup | T53: Tons | U53: Cost | V53: TL | W53: Power | AD53: 2 | AE53: =INDEX($AB$24:$AM$48,MATCH(B33,$AB$24:$AB$48,0),5) -> 0 | AG53: =INDEX($AB$24:$AM$48,MATCH(B33,$AB$24:$AB$48,0),6) -> 0 | AI53: =INDEX($AB$24:$AM$48,MATCH(B60,$AB$24:$AB$48,0),6) -> 0 | AK53: 2 | AL53: =INDEX($AB$24:$AM$48,MATCH(B60,$AB$24:$AB$48,0),11) -> 0
B54: A Standard (None) | D54: =INDEX(S24:AA48,MATCH(B52,S24:S48,0),9)+INDEX(S24:AA48,MATCH(B53,S24:S48,0),9)+INDEX(S24:AA48,MATCH(B54,S24:S48,0),9) -> 0 | E54: =INDEX($S$24:$AA$48,MATCH(B54,$S$24:$S$48,0),4) -> 0 | AD54: 3 | AE54: =INDEX($AB$24:$AM$48,MATCH(B34,$AB$24:$AB$48,0),5) -> 0 | AG54: =INDEX($AB$24:$AM$48,MATCH(B34,$AB$24:$AB$48,0),6) -> 0 | AI54: =INDEX($AB$24:$AM$48,MATCH(B61,$AB$24:$AB$48,0),6) -> 0 | AK54: 3 | AL54: =INDEX($AB$24:$AM$48,MATCH(B61,$AB$24:$AB$48,0),11) -> 0
S55: No FTL | T55: 0 | U55: 0 | V55: 0 | W55: 0 | AF55: FTL | AH55: Reaction | AP55: Reaction
A56: FTL | B56: No FTL | C56: Rating | D56: 0 | E56: =INDEX(X10:AB16,MATCH(B56,X10:X16,0),4)+SUM(E59:E61) -> 0 | F56: =IF(D56=0,0,INDEX(X10:AB16,MATCH(B56,X10:X16,0),3))*'Ship Info'!G31 -> 0 | H56: =IF(D56=0,0,INDEX(X10:AB16,MATCH(B56,X10:X16,0),2)) -> 0 | K56: =IF(D56=0,0,INDEX(X10:AB16,MATCH(B56,X10:X16,0),5)) -> 0 | S56: Hyperdrive | AB56: Fuel Tab Mod | AF56: md | AG56: rating | AH56: md | AI56: rating | AP56: 0 | AQ56: 0
B57: EMP Hardened? | C57: No | F57: =IF(C57=S37,0.5*(F56+F59)," ") | S57: Jump Drive | AB57: FTL | AC57: =INDEX(AE57:AG58,MATCH(C6,AE57:AE58,0),2)-'1-Hull'!T96 -> 1 | AD57: =INDEX(AE57:AG58,MATCH(C6,AE57:AE58,0),3) -> 0 | AE57: Backups | AF57: =AI51 -> 1 | AG57: =D56 -> 0 | AH57: =BA47 -> 1 | AI57: =D37 -> 0 | AP57: 0.01 | AQ57: 0.5
B58: Armored Bulkheads? | C58: No | F58: =IF(C58=S13,200000*H58," ") | H58: =IF(C58=S13,0.1*(H56+H59)," ") | S58: Space Folding Drive | AB58: Reaction | AC58: =INDEX(AE57:AI58,MATCH(C6,AE57:AE58,0),4) -> 1 | AD58: =INDEX(AE57:AI58,MATCH(C6,AE57:AE58,0),5) -> 0 | AE58: Mains | AF58: =AG51 -> 1 | AG58: =D29 -> 0 | AH58: =AQ47 -> 1 | AI58: =D23 -> 0 | AP58: 0.02 | AQ58: 1
A59: FTL Mods: | B59: A Standard (None) | E59: =INDEX($AB$24:$AM$48,MATCH(B59,$AB$24:$AB$48,0),7) -> 0 | F59: =AL51 -> 0 | H59: =IF(D56=0,0,INDEX(AB24:AM48,MATCH(B59,AB24:AB48,0),10)+INDEX(AB24:AM48,MATCH(B60,AB24:AB48,0),10)+INDEX(AB24:AM48,MATCH(B61,AB24:AB48,0),10)) -> 0 | K59: =INDEX(AB24:AM48,MATCH(B59,AB24:AB48,0),12)+INDEX(AB24:AM48,MATCH(B60,AB24:AB48,0),12)+INDEX(AB24:AM48,MATCH(B61,AB24:AB48,0),12) -> 0 | S59: Warp Drive | AP59: 0.03 | AQ59: 1.5
B60: A Standard (None) | D60: Effective # Mods | E60: =INDEX($AB$24:$AM$48,MATCH(B60,$AB$24:$AB$48,0),7) -> 0 | AP60: 0.04 | AQ60: 2
B61: A Standard (None) | D61: =INDEX(AB24:AM48,MATCH(B59,AB24:AB48,0),9)+INDEX(AB24:AM48,MATCH(B60,AB24:AB48,0),9)+INDEX(AB24:AM48,MATCH(B61,AB24:AB48,0),9) -> 0 | E61: =INDEX($AB$24:$AM$48,MATCH(B61,$AB$24:$AB$48,0),7) -> 0 | AP61: 0.05 | AQ61: 2.5
S62: Page Tonnage | U62: Optional | V62: =SUM(V63:V65) -> 0 | Z62: Main M-Drive Mod for record sheet | AE62: A Standard (None) | AF62: ="" | AP62: 0.06 | AQ62: 3
A63: Note: | B63: EMP Hardened units draw power prior to the power reduction caused by ion weapons | S63: =SUM(H14:H61) -> 0 | U63: Other | V63: =SUM('6-Comp'!Y14) -> 0 | Z63: =INDEX($AE$62:$AF$86,MATCH(B19,$AE$62:$AE$86,0),2) | AE63: B1 Budget - Increased Size | AF63: Budget-Increased Size | AP63: 0.07 | AQ63: 3.5
U64: Small FTL | V64: =IF(C7="Yes",1,0) -> 0 | Z64: =INDEX($AE$62:$AF$86,MATCH(B20,$AE$62:$AE$86,0),2) | AB64: EMP | AC64: =C15 -> No | AE64: B2 Budget - Inefficient | AF64: Budget-Inefficient | AP64: 0.08 | AQ64: 4
A65: Note: | B65: Armored Bulkheads reduce the severity of a critical hit by 1 (minimum Severity 1) | S65: Page Power | U65: FTL TL | V65: =IF(C8="Yes",1,0) -> 0 | Z65: =INDEX($AE$62:$AF$86,MATCH(B21,$AE$62:$AE$86,0),2) | AB65: Armor | AC65: =C16 -> No | AE65: B3 Budget Limited Range | AF65: Budget-Limited Range | AP65: 0.09 | AQ65: 4.5
S66: =SUM(K14:K61) -> 0 | AB66: DSMS | AC66: =C17 -> No | AE66: C1 Advanced Cost Reduction* | AF66: Cost Reduction 1* | AP66: 0.1 | AQ66: 5
A67: Note: | B67: The Easy to Repair Mod grants a +1 DM to any repair rolls for that system, unless otherwise noted. | Z67: =IF(Z63=AE62,"",Z63) | AA67: =IF(Z67="","",IF(AND(Z63=Z64,Z63=Z65)," x3",IF(OR(Z63=Z64,Z63=Z65)," x2",""))) | AE67: C2 Very Advanced Cost Reduction* | AF67: Cost Reduction 2* | AP67: 0.11 | AQ67: 5.5
S68: Secondary Drive | T68: Tonnage | U68: Cost | V68: TL | W68: Power | Z68: =IF(OR(Z67="",Z64="",Z64=Z63),"",", ")&IF(OR(Z64=Z63,Z64=AE62),"",Z64) | AA68: =IF(Z68="","",IF(Z68=Z65," x2","")) | AE68: C3 High Tech Cost Reduction* | AF68: Cost Reduction 3* | AP68: 0.12 | AQ68: 6
A69: Note: | B69: The Stealth Mod on a Thrust unit provides a -1 DM to opposing Sensor Ops. | S69: No Back Up Drive | T69: 0 | U69: 0 | V69: 0 | W69: 0 | Z69: =IF(OR(AND(Z67="",Z68=""),Z65="",Z65=Z63,Z65=Z64),"",", ")&IF(OR(Z65=Z67,Z65=Z68,Z65=AE62),"",Z65) | AE69: D1 Advanced - Energy Efficient | AF69: Efficient | AP69: 0.13 | AQ69: 6.5
B70: On an FTL unit, it dampens the exit and re-entry emissions, making detection difficult. | S70: Manoeuvre Drive | T70: =T21*INDEX(AF1:AQ3,2,MATCH(D46,AF1:AQ1,0)) -> 0.5 | U70: =2000000*(T70+H52) -> 1000000 | V70: =INDEX(AF1:AQ3,3,MATCH(D46,AF1:AQ1,0)) -> 9 | W70: =IF(D46>0,D46*0.1*U107,0.1*U107*0.25) -> 2.5 | AE70: D2 Advanced - Reduced Size | AF70: Reduced Size | AP70: 0.14 | AQ70: 7
Z71: B/U M-Drive Mod for record sheet | AE71: D3 Advanced - Easy to Repair | AF71: Easy to Repair | AP71: 0.15 | AQ71: 7.5
A72: Note: | B72: The toggle for which set to base fuel calculations on allows you to base fuel storage on | S72: Errors | T72: =SUM(T73,T74,T82,W74,T87) -> 0 | Z72: =INDEX($AE$62:$AF$86,MATCH(B52,$AE$62:$AE$86,0),2) | AE72: D4 Advanced - Low Emissions | AF72: Low Emissions | AP72: 0.16 | AQ72: 8
B73: either the most efficient or least efficient system, based on your mods. | S73: Module with drives | T73: =IF(AND(S63>0,OR('Ship Info'!F7,'Ship Info'!F4)),1,0) -> 0 | Z73: =INDEX($AE$62:$AF$86,MATCH(B53,$AE$62:$AE$86,0),2) | AB73: EMP | AC73: =C47 -> No | AE73: E Concealed Drive | AF73: Concealed Drive | AP73: 0.17 | AQ73: 8.5
S74: Thrust Errors | T74: =SUM(T75:T80)+T73 -> 0 | V74: Total Mods Error | W74: =SUM(W75:W80) -> 0 | Z74: =INDEX($AE$62:$AF$86,MATCH(B54,$AE$62:$AE$86,0),2) | AB74: Armor | AC74: =C48 -> No | AE74: Pa Prototype - Increased Size | AF74: Increased Size Prototype | AP74: 0.18 | AQ74: 9
A75: Note: | B75: The rating for the Concealed Drive Mod is the actual thrust delivered. The tonnage and cost are | S75: TL Main | T75: =IF(E14>E2,1,0) -> 0 | V75: Mn M | W75: =IF(D21>3,1,0) -> 0 | AB75: DSMS | AC75: =C49 -> No | AE75: Pb Prototype - Inefficient | AF75: Inefficient Prototype | AP75: 0.19 | AQ75: 9.5
B76: calculated using doubled that thrust + 25% | S76: TL Main Mod | T76: =IF(E19>E2,1,0) -> 0 | V76: Mn R | W76: =IF(D27>3,1,0) -> 0 | Z76: =IF(Z72=AE62,"",Z72) | AA76: =IF(Z76="","",IF(AND(Z72=Z73,Z72=Z74)," x3",IF(OR(Z72=Z73,Z72=Z74)," x2",""))) | AE76: Pc Prototype - Limited Range | AF76: Ltd Rng Prototype | AP76: 0.2 | AQ76: 10
S77: TL HBT | T77: =IF(E37>E2,1,0) -> 0 | V77: Mn F | W77: =IF(D34>3,1,0) -> 0 | Z77: =IF(OR(Z76="",Z73="",Z73=Z72),"",", ")&IF(OR(Z73=Z72,Z73=AE62),"",Z73) | AA77: =IF(Z77="","",IF(Z73=Z74," x2","")) | AE77: Ta Early Prototype - Orbital Range | AF77: Orbital Early Prototype | AP77: 0.21 | AQ77: 10.5
S78: TL HBT Mod | T78: =IF(E39>E2,1,0) -> 0 | V78: Sec R | W78: =IF(D41>3,1,0) -> 0 | Z78: =IF(OR(AND(Z76="",Z77=""),Z74="",Z74=Z72,Z74=Z73),"",", ")&IF(OR(Z74=Z72,Z74=Z73,Z74=AE62),"",Z74) | AE78: Tb Early Prototype - Increased Size x2 | AF78: Increased Size x2 Early Prototype | AP78: 0.22 | AQ78: 11
S79: TL BU M Drive | T79: =IF(E46>E2,1,0) -> 0 | V79: Sec M | W79: =IF(D54>3,1,0) -> 0 | AE79: Tc Early Prototype - Inefficient x2 | AF79: Inefficient x2 Early Prototype | AP79: 0.23 | AQ79: 11.5
S80: TL BU M Drive Mod | T80: =IF(E52>E2,1,0) -> 0 | V80: Sec F | W80: =IF(D61>3,1,0) -> 0 | AE80: Td Early Prototype - Increased Size, Inefficient | AF80: Increased Size, Inefficient Early Prototype | AP80: 0.24 | AQ80: 12
AE81: Te Early Prototype- Increased Size, Limit Rng | AF81: Increased Size, Ltd Rng Early Prototype | AP81: 0.25 | AQ81: 12.5
S82: Jump Errors | T82: =SUM(T83:T85)+T73 -> 0 | U82: FTL No | V82: <100 | W82: FTL>0 | X82: And | AE82: Tf Early Prototype- Inefficient, Limit Rng | AF82: Inefficient, Ltd Rng Early Prototype | AP82: 0.26 | AQ82: 13
S83: Hull<100 | T83: =IF(X83=3,1,0) -> 0 | U83: =IF(C7=S12,1,0) -> 1 | V83: =IF('1-Hull'!B4<100,1,0) -> 0 | W83: =IF(D29>0,1,0) -> 0 | X83: =SUM(U83:W83) -> 1 | AE83: =M25&" "&N25 -> X1 | AF83: =N25 -> 0 | AP83: 0.27 | AQ83: 13.5
S84: TL FTL | T84: =IF(E29>E2,1,0) -> 0 | AE84: =M32&" "&N32 -> X2 | AF84: =N32 -> 0 | AP84: 0.28 | AQ84: 14
S85: TL FTL Mod | T85: =IF(E32>E2,1,0) -> 0 | AE85: =M39&" "&N39 -> X3 | AF85: =N39 -> 0 | AP85: 0.29 | AQ85: 14.5
AE86: =M46&" "&N46 -> X4 | AF86: =N46 -> 0 | AP86: 0.3 | AQ86: 15
S87: TL high | T87: =IF(MAX(E14:E61)>E2,1,0) -> 0 | AE87: Reaction | AP87: 0.31 | AQ87: 15.5
Z88: Main R-Drive Mod for record sheet | AE88: A Standard (None) | AF88: ="" | AP88: 0.32 | AQ88: 16
T89: Tons | U89: Cost | Z89: =INDEX($AE$88:$AF$106,MATCH(B25,$AE$88:$AE$106,0),2) | AE89: B1 Budget - Increased Size | AF89: Budget-Increased Size
S90: Mdrive | T90: =SUM(H14:H27,H37:H54) -> 0 | U90: =SUM(F14:F27,F37:F54) -> 0 | Z90: =INDEX($AE$88:$AF$106,MATCH(B26,$AE$88:$AE$106,0),2) | AE90: B2 Budget - Fuel Inefficient | AF90: Budget-Inefficient
S91: =IF(B14=S2,"","M-Drive: "&D14&" "&Z67&AA67&Z68&AA68&Z69&IF(AC66="No","",", DSMS "&D17)&IF(C18="No","",", Variable Emissions")&IF(AC64="No","",", EMP")&IF(AC65="No","",", Armored")&IF(C9=S107,"",", Rated for "&TEXT(U107,"#,###")&" Dtons")) | Z91: =INDEX($AE$88:$AF$106,MATCH(B27,$AE$88:$AE$106,0),2) | AB91: Armor | AC91: =C24 -> No | AE91: C1 Advanced Cost Reduction* | AF91: Cost Reduction 1*
S92: =IF(B46=S69,"",", B/U M-Drive: "&D46&" "&Z76&AA76&Z77&AA77&Z78&IF(AC75="No","",", DSMS "&D49)&IF(C51="No","",", Variable Emissions")&IF(AC73="No","",", EMP")&IF(AC74="No","",", Armored")&IF(C9=S107,"",", Rated for "&TEXT(U107,"#,###")&" Dtons")) | AE92: C2 Very Advanced Cost Reduction* | AF92: Cost Reduction 2*
S93: =IF(AND(S91="",S92=""),"No M-Drive","") -> No M-Drive | Z93: =IF(Z89=AE88,"",Z89) | AA93: =IF(Z93="","",IF(AND(Z89=Z90,Z89=Z91)," x3",IF(OR(Z89=Z90,Z89=Z91)," x2",""))) | AE93: C3 High Tech Cost Reduction* | AF93: Cost Reduction 3*
S94: R Drive | Z94: =IF(OR(Z93="",Z90="",Z90=Z89),"",", ")&IF(OR(Z90=Z89,Z90=AE88),"",Z90) | AA94: =IF(Z94="","",IF(Z94=Z91," x2","")) | AE94: D1 Advanced - Fuel Efficient | AF94: Efficient
S95: =IF(S91="","",", ")&IF(B23=S2,"","R-Drive: "&D23&" "&Z93&AA93&Z94&AA94&Z95&IF(AC91="No","",", Armored")&IF(C9=S107,"",", Rated for "&U110&" Dtons")) | Z95: =IF(OR(AND(Z93="",Z94=""),Z91="",Z91=Z89,Z91=Z90),"",", ")&IF(OR(Z91=Z93,Z91=Z94,Z91=AE88),"",Z91) | AE95: D2 Advanced - Reduced Size | AF95: Reduced Size
S96: =IF(D37=0,"",", High Burn Thruster: "&D37&" "&Z102&AA102&Z103&AA103&Z104&IF(AC100="No","",", Armored")&IF(C9=S107,"",", Rated for "&U110&" Dtons")) | AE96: D3 Advanced - Easy to Repair | AF96: Easy to Repair
Z97: B/U R-Drive Mod for record sheet | AE97: D4 Very Advanced- Stealth | AF97: Stealth
S98: =S91&S92&S93&S95&S96&IF(B44=S17,", Solar Sails","")&IF(C9=S107,"",", Drives Rated for "&U110&" Dtons") -> No M-Drive | Z98: =INDEX($AE$88:$AF$106,MATCH(B39,$AE$88:$AE$106,0),2) | AE98: Pa Prototype - Increased Size | AF98: Increased Size Prototype
Z99: =INDEX($AE$88:$AF$106,MATCH(B40,$AE$88:$AE$106,0),2) | AE99: Pb Prototype - Fuel Inefficient | AF99: Inefficient Prototype
S100: FTL | T100: =SUM(H29:H32,H56:H59) -> 0 | U100: =SUM(F29:F32,F56:F59) -> 0 | Z100: =INDEX($AE$88:$AF$106,MATCH(B41,$AE$88:$AE$106,0),2) | AB100: Armor | AC100: =C38 -> No | AE100: Ta Early Prototype - Increased Size x2 | AF100: Increased Size x2 Early Prototype
...

Sheet 3-Pwr Plant
A1: ='Ship Info'!A1 -> Ship's Class Name | B1: ='Ship Info'!B1 -> 0 | F1: Cost | S1: Power Plant Type | T1: Tonnage | U1: Cost | V1: TL | W1: P/Ton | X1: Fuel
A2: Class Role | B2: ='Ship Info'!B2 -> 0 | D2: Tech Level: | E2: =Tech_Level -> 12 | F2: ='Ship Info'!G2 -> 6177000 | S2: TL 6 Fission | T2: =$D$11/W2 -> 2.5 | U2: =(T2)*400000 -> 1000000 | V2: 6 | W2: 8 | X2: =IF(T2=0,0,IF((T2+$H$12)<10,IF(AND($B$4<100,'4-Fuel'!C4=$S$17),0.1*(T2+$H$12),1),0.1*(T2+$H$12))) -> 1 | Y2: 0
B3: ='1-Hull'!B3 -> Standard Automation - Costs x 1 | H3: =S41 -> 1.3333333 | S3: TL 6 Stirling Fission | T3: =$D$11/W3 -> 6.6666667 | U3: =T3*400000 -> 2666666.7 | V3: 6 | W3: 3 | X3: 0 | Y3: 10 | Z3: Pwr Mod for record sheet
A4: Tonnage | B4: ='1-Hull'!B4 -> 100 | F4: Page Total | H4: Available Space | K4: Required Power | S4: TL 7 Chemical | T4: =$D$11/W4 -> 4 | U4: =(T4)*0.25*1000000 -> 1000000 | V4: 7 | W4: 5 | X4: =20*(T4+$H$12) -> 80 | Y4: 0 | Z4: =INDEX($S$19:$Z$32,MATCH(B12,$S$19:$S$32,0),8)
F5: =SUM(F11:F22) -> 1333333.3 | H5: Unused | I5: Max | K5: Unused | L5: Max | S5: TL 8 Stirling Fission | T5: =$D$11/W5 -> 5 | U5: =T5*600000 -> 3000000 | V5: 8 | W5: 4 | X5: 0 | Y5: 15 | Z5: =INDEX($S$19:$Z$32,MATCH(B13,$S$19:$S$32,0),8)
H6: ='Ship Info'!I3 -> 92.53 | I6: ='1-Hull'!I6 -> 100 | K6: ='Ship Info'!L3 -> 0 | L6: =SUM(D11,L12) -> 20 | S6: TL 8 Fusion | T6: =$D$11/W6 -> 2 | U6: =(T6)*500000 -> 1000000 | V6: 8 | W6: 10 | X6: =IF(T6=0,0,0.1*(T6+$H$12)) -> 0.2 | Y6: 0 | Z6: =INDEX($S$19:$Z$32,MATCH(B14,$S$19:$S$32,0),8)
B7: Ignore HG'22 Prohibitions on Power Plants in Modules? | C7: Yes | H7: Item Tons | S7: TL 12 Stirling Fission | T7: =$D$11/W7 -> 3.3333333 | U7: =T7*800000 -> 2666666.7 | V7: 12 | W7: 6 | X7: 0 | Y7: 20
N8: Power Distribution | S8: TL 12 Fusion | T8: =$D$11/W8 -> 1.3333333 | U8: =(T8)*1000000 -> 1333333.3 | V8: 12 | W8: 15 | X8: =IF(T8=0,0,0.1*(T8+$H$12)) -> 0.13333333 | Y8: 0 | Z8: =IF(Z4=Z19,"",Z4) | AA8: =IF(Z8="","",IF(AND(Z4=Z5,Z4=Z6)," x3",IF(OR(Z4=Z5,Z4=Z6)," x2","")))
A9: Engineering | B9: * Indicates a non-MgT2-standard Mod | E9: TL | N9: Basic | O9: ='1-Hull'!K11 -> 20 | S9: TL 15 Fusion | T9: =$D$11/W9 -> 1 | U9: =(T9)*2000000 -> 2000000 | V9: 15 | W9: 20 | X9: =IF(T9=0,0,0.1*(T9+$H$12)) -> 0.1 | Y9: 0 | Z9: =IF(OR(Z8="",Z5="",Z5=Z4),"",", ")&IF(OR(Z5=Z4,Z5=Z19),"",Z5) | AA9: =IF(OR(Z5="",AA8=" x3"),"",IF(Z5=Z6," x2",""))
C10: Nominal | N10: Hull+ | O10: =SUM('1-Hull'!K14:K20) -> 0 | S10: TL 20 Antimatter | T10: =$D$11/W10 -> 0.2 | U10: =10000000*(T10) -> 2000000 | V10: 20 | W10: 100 | X10: =IF(T10=0,0,IF(T10<10,IF(AND($B$4<100,'4-Fuel'!$C$4=$S$17),0.1*(T10+$H$12),1),0.1*(T10+$H$12))) -> 1 | Y10: 0 | Z10: =IF(OR(AND(Z8="",Z9=""),Z6="",Z6=Z4,Z6=Z5),"",", ")&IF(OR(Z6=Z4,Z6=Z5,Z6=Z19),"",Z6)
A11: Power Plant | B11: TL 12 Fusion | C11: Power Output | D11: 20 | E11: =INDEX(S2:V10,MATCH(B11,S2:S10,0),4)+SUM(E12:E14) -> 12 | F11: =INDEX(S2:U10,MATCH(B11,S2:S10,0),3)*'Ship Info'!G31 -> 1333333.3 | H11: =INDEX(S2:T10,MATCH(B11,S2:S10,0),2) -> 1.3333333 | N11: Main M | O11: ='2-Drives'!K14+'2-Drives'!K19 -> 0
A12: Mods | B12: A Standard (None) | D12: =IF(T48,"Error: Module","") | E12: =INDEX(S19:V32,MATCH(B12,S19:S32,0),4) -> 0 | F12: =U36 -> 0 | H12: =INDEX(S19:W32,MATCH(B12,S19:S32,0),2)+INDEX(S19:W32,MATCH(B13,S19:S32,0),2)+INDEX(S19:W32,MATCH(B14,S19:S32,0),2) -> 0 | L12: =INDEX(S19:W32,MATCH(B12,S19:S32,0),5)+INDEX(S19:W32,MATCH(B13,S19:S32,0),5)+INDEX(S19:W32,MATCH(B14,S19:S32,0),5) -> 0 | N12: Main FTL | O12: ='2-Drives'!K29+'2-Drives'!K32 -> 0 | S12: =INDEX(S2:V10,MATCH(B11,S2:S10,0),4) -> 12 | Z12: =Z8&AA8&Z9&AA9&Z10
B13: A Standard (None) | D13: Effective # Mods | E13: =INDEX(S19:V32,MATCH(B13,S19:S32,0),4) -> 0 | N13: BU/ M | O13: ='2-Drives'!K46+'2-Drives'!K52 -> 0 | P13: Yes | Q13: Include B/U M-Drive in Battle Load? | S13: No | T13: 0 | U13: 0 | V13: 0
B14: A Standard (None) | D14: =INDEX(S19:Z32,MATCH(B12,S19:S32,0),7)+INDEX(S19:Z32,MATCH(B13,S19:S32,0),7)+INDEX(S19:Z32,MATCH(B14,S19:S32,0),7) -> 0 | E14: =INDEX(S19:V32,MATCH(B14,S19:S32,0),4) -> 0 | N14: B/U FTL | O14: ='2-Drives'!K56+'2-Drives'!K59 -> 0 | S14: TL 10 | T14: 100000 | U14: 40 | V14: 10
B15: Emergency Power System? | C15: No | F15: =IF(C15=S17,0.1*(F11+F12)*'Ship Info'!G31," ") | H15: =IF(C15=S17,0.1*(H11+H12),"") | L15: =IF(C15=S17,0.9*L6," ") | N15: Fuel | O15: ='4-Fuel'!S27 -> 0 | S15: TL 12 | T15: 200000 | U15: 60 | V15: 12
B16: Armored Bulkheads? | C16: No | F16: =IF(C16=S17,200000*H16*'Ship Info'!G31,"") | H16: =IF(C16=S17,0.1*(H11+H12+H18+H20),"") | N16: Sensors | O16: ='7-Sensors'!S17 -> 0 | S16: No | T16: 0 | U16: 0
D17: # Batteries | N17: Weap | O17: ='8a-Weapons'!Q9 -> 0 | S17: Yes | T17: 1 | U17: 14
B18: High Efficiency Batteries? | C18: No | D18: 0 | E18: =INDEX(S13:V15,MATCH(C18,S13:S15,0),4) -> 0 | F18: =INDEX(S13:U15,MATCH(C18,S13:S15,0),2)*D18*'Ship Info'!G31 -> 0 | H18: =IF(C18=S13,0,D18) -> 0 | L18: =INDEX(S13:U15,MATCH(C18,S13:S15,0),3)*D18 -> 0 | N18: Screen | O18: =SUM('8b-Screens'!K9:K39) -> 0
D19: # of Systems | N19: Optional | O19: =SUM('9b-Optional'!K9:K73,'9b-Optional'!K127:K191,'9a-Optional'!K10:K67) -> 0 | S19: A Standard (None) | T19: 0 | U19: 0 | V19: 0 | W19: 0 | Y19: 0 | Z19: =""
A20: No Jump Rating | B20: Jump Collectors/Accumulators? | C20: No | D20: 0 | E20: =INDEX(S16:U17,MATCH(C20,S16:S17,0),3) -> 0 | F20: =H20*500000*'Ship Info'!G31 -> 0 | H20: =IF(AND('2-Drives'!B29=" No FTL",'2-Drives'!B56=" No FTL"),0,IF(MAX('2-Drives'!D29,'2-Drives'!D56)=0,0, (MAX('2-Drives'!D29,'2-Drives'!D56)*(0.01*'2-Drives'!C4)+5)*D20*INDEX(S16:U17,MATCH(C20,S16:S17,0),2))) -> 0 | N20: Stateroom | O20: =SUM('11-Staterooms'!K15:K107) -> 0 | S20: B1 Budget - Increased Size | T20: =0.25*H11 -> 0.33333333 | U20: =-0.25*F11 -> -333333.33 | V20: 0 | W20: 0 | Y20: 3 | Z20: Budget-Increased Size
D21: # Units | N21: Cargo | O21: =SUM('12-Cargo'!K9:K52) -> 0 | S21: B2 Budget - Inefficient | T21: 0 | U21: =-0.25*F11 -> -333333.33 | V21: 0 | W21: =-0.25*D11 -> -5 | Y21: 3 | Z21: Budget - Inefficient
B22: Solar Panels? | C22: No | D22: 0 | E22: =INDEX(S52:V56,MATCH(C22,S52:S56,0),2) -> 0 | F22: =INDEX(S52:V56,MATCH(C22,S52:S56,0),4)*D22 -> 0 | H22: =IF(C22=S52,0,D22) -> 0 | L22: =INDEX(S52:V56,MATCH(C22,S52:S56,0),3)*D22 -> 0 | N22: DSMS | O22: =SUM('2-Drives'!K17,'2-Drives'!K49) -> 0 | S22: C1 Advanced Cost Reduction* | T22: 0 | U22: =-0.1*F11 -> -133333.33 | V22: 1 | W22: 0 | Y22: 3 | Z22: TL Cost Reduction 1*
N23: Max Load | O23: =SUM(O9:O10,O11,O13,MAX(O12,O14),O15:O22) -> 20 | S23: C2 Very Advanced Cost Reduction* | T23: 0 | U23: =-0.15*F11 -> -200000 | V23: 2 | W23: 0 | Y23: 3 | Z23: TL Cost Reduction 2*
S24: C3 High Tech Cost Reduction* | T24: 0 | U24: =-0.2*F11 -> -266666.67 | V24: 3 | W24: 0 | Y24: 3 | Z24: TL Cost Reduction 3*
B25: Note: An Emergency Power System provides 90% power for five turns if the Power Plant suffers a Severity 3+ critical hit. | N25: Battle Load | S25: D1 Advanced - Reduced Size | T25: =-0.1*H11 -> -0.13333333 | U25: 0 | V25: 1 | W25: 0 | Y25: 1 | Z25: Reduced Size
B26: On a Severity 6+, the Emergency Power System is also destroyed. | N26: Btl Load | O26: =SUM(O9/2,O11,IF(P13="Yes",O13,0),O16:O18) -> 10 | S26: D2 Advanced - Easy to Repair | T26: 0 | U26: 0 | V26: 1 | W26: 0 | Y26: 1 | Z26: Easy to repair
B27: Note: Armored Bulkheads reduce the severity of a critical hit by 1 (minimum Severity 1) | M27: (CS-1) | N27: ="+10%" -> +10% | O27: =ROUNDUP(O26/0.9,0) -> 12 | S27: E1 Advanced - Increased Power | T27: 0 | U27: 0 | V27: 2 | W27: =0.1*D11 -> 2 | Y27: 2 | Z27: Increased Power
M28: (CS-2) | N28: ="+20%" -> +20% | O28: =ROUNDUP(O26/0.8,0) -> 13 | S28: Pa Prototype - Increased Size | T28: =0.25*H11 -> 0.33333333 | U28: =5*F11 -> 6666666.7 | V28: -1 | W28: 0 | Y28: 3 | Z28: Increased Size Prototype
B29: Note: Jump Collectors are accumulators that power the jump drive over a week's time for a stationary ship in space | M29: (CS-3) | N29: ="+70%" -> +70% | O29: =ROUNDUP(O26/0.3,0) -> 34 | S29: Pb Prototype - Inefficient | T29: 0 | U29: =5*F11 -> 6666666.7 | V29: -1 | W29: =-0.25*D11 -> -5 | Y29: 3 | Z29: Inefficient Prototype
S30: Ta Early Prototype - Increased Size x2 | T30: =1.5*H11 -> 2 | U30: =10*F11 -> 13333333 | V30: -2 | W30: 0 | Y30: 3 | Z30: Increased Size Early Prototype
B31: Note: The Battle Load section of the Power Distribution Table provides a conservative estimate of power needs in combat. | S31: Tb Early Prototype - Inefficient x2 | T31: =1*H11 -> 1.3333333 | U31: =10*F11 -> 13333333 | V31: -2 | W31: =-0.5*D11 -> -10 | Y31: 3 | Z31: Inefficient Early Prototype
B32: The Plus 10, 20 and 70 fields show the initial power output needed to maintain power to basic and combat systems after the ship suffers the indicated critical hit. | S32: Tc Early Prototype - Increased Size/Inefficient | T32: =1.25*H11 -> 1.6666667 | U32: =10*F11 -> 13333333 | V32: -3 | W32: =-0.25*D11 -> -5 | Y32: 3 | Z32: Increased Size/Inefficient Early Prototype
S34: =B11&", Output: "&D11&IF(AND(Z4="",Z5="",Z6=""),"",", "&Z8&AA8&Z9&AA9&Z10)&IF(C15=S16,"",", Emergency Power")&IF(C16=S16,"",", Armored")&IF(C18=S13,"",", "&D18&"x "&C18&" Batteries")&IF(C20=S16,"",", Jump Collectors x"&D20)&IF(D22>0,", "&D22&" Units of "&C22&" Solar Panels: "&L22&" Base Power","") -> TL 12 Fusion, Output: 20
T36: Mods | U36: =IF(SUM(U37:U39)=0,INDEX(V43:X46,MATCH(SUM(E12:E14),V43:V46,0),3)*F11,SUM(U37:U39)) -> 0
T37: 1 | U37: =INDEX(S19:U32,MATCH(B12,S19:S32,0),3) -> 0
T38: 2 | U38: =INDEX(S19:U32,MATCH(B13,S19:S32,0),3) -> 0
T39: 3 | U39: =INDEX(S19:U32,MATCH(B14,S19:S32,0),3) -> 0
S40: Page Tonnage
S41: =SUM(H11:H22) -> 1.3333333
V42: Mod Price modifier
S43: Error | T43: =SUM(T44:T49) -> 0 | V43: 0 | X43: 0
S44: PWR Plant TL | T44: =IF(E11>E2,1,0) -> 0 | V44: 1 | X44: 0.1
S45: PWR Mod >3 | T45: =IF(D14>3,1,0) -> 0 | V45: 2 | X45: 0.25
S46: Btty TL | T46: =IF(E18>E2,1,0) -> 0 | V46: 3 | X46: 0.5
S47: Accumulator TL | T47: =IF(E20>E2,1,0) -> 0
S48: Module | T48: =IF(C7=S17,0,IF(AND(U48,SUM('3-Pwr Plant'!H11:H12)>0),1,0)) -> 0 | U48: =IF('Ship Info'!F7,IF(AND('Ship Info'!F7,'Ship Info'!I6="Yes"),0,1),0) -> 0 | V48: <<Pod?
S49: Small Plant Minimum | T49: =IF(AND(D11>0,D11<1),1,0) -> 0
S51: Solar Panels | T51: TL | U51: PPU | V51: Cost
S52: No | T52: 0 | U52: 0 | V52: 0
S53: Basic | T53: 6 | U53: 0.25 | V53: 100000
S54: Improved | T54: 8 | U54: 0.5 | V54: 200000
S55: Enhanced | T55: 10 | U55: 1 | V55: 300000
S56: Advanced | T56: 12 | U56: 2 | V56: 400000
S57: FTL?
S58: =IF(MAX('2-Drives'!D29,'2-Drives'!D56)=0,0,1) -> 0

Sheet 4-Fuel
A1: ='Ship Info'!A1 -> Ship's Class Name | B1: ='Ship Info'!B1 -> 0 | F1: Cost | S1: Fuel Scoop | U1: Chemical plant?
A2: Class Role | B2: ='Ship Info'!B2 -> 0 | D2: Tech Level: | E2: =Tech_Level -> 12 | F2: ='Ship Info'!G2 -> 6177000 | S2: Included Free w/ Streamlining | U2: =IF('3-Pwr Plant'!B11='3-Pwr Plant'!S3,1,0) -> 0
H3: =S24 -> 0.13333333 | K3: =S27 -> 0 | S3: Standard Installed
B4: Use Small Craft Catalog Fuel Rule? | C4: Yes | F4: Page Total | H4: Available Space | K4: Required Power | S4: High Yield Installed | U4: =B13 -> Uninstalled
B5: Use SCC Fuel for All Ships (House Rule)? | C5: Yes | F5: =SUM(F12:F47) -> 0 | H5: Unused | I5: Max | K5: Unused | L5: Max | S5: Uninstalled | U5: =500000*V5 -> 0 | V5: =IF(U4=S4,0.01*Tonnage,0) -> 0
H6: ='Ship Info'!I3 -> 92.53 | I6: ='1-Hull'!I6 -> 100 | K6: ='Ship Info'!L3 -> 0 | L6: ='3-Pwr Plant'!L6 -> 20
A7: Main Fuel Tanks | B7: Standard Fuel Tanks | E7: =INDEX(S17:V19,MATCH(B7,S17:S19,0),4) -> 7 | S7: Hull Type
A8: Reaction Thrust-Hours | B8: 0 | C8: Thrust Points: | D8: =IF(B8=0,"N/A",10*V9*B8) -> N/A | H8: =V9*0.025*'1-Hull'!B4*B8*'2-Drives'!AC58 -> 0 | S8: ='1-Hull'!B8 -> Partial
A9: =T11&" Available x "&U11&" pc" -> Jumps Available x 1 pc | B9: 0 | H9: =IF(LEFT('2-Drives'!B29,10)="Jump Drive",'2-Drives'!U107*0.1*B9,0)*'2-Drives'!AC57 -> 0 | S9: Drive type | T9: No | U9: Reaction Rating | V9: =MAX(U10:U13) -> 1
A10: Power Plant | B10: Weeks of Operation | C10: 4 | D10: Low Capacity Warning | H10: =IF(INDEX('3-Pwr Plant'!S2:X10,MATCH('3-Pwr Plant'!B11,'3-Pwr Plant'!S2:S10,0),6)=0,0,IF(C10=0,0,IF('3-Pwr Plant'!D11=0,0,IF(U2=0,IF(OR(AND($C$4=$T$10,$C$5=$T$10),AND(Tonnage<100,$C$4=$T$10)),C10*INDEX('3-Pwr Plant'!S2:X10,MATCH('3-Pwr Plant'!B11,'3-Pwr Plant'!S2:S10,0),6)/4,MAX(,1,C10*INDEX('3-Pwr Plant'!S2:X10,MATCH('3-Pwr Plant'!B11,'3-Pwr Plant'!S2:S10,0),6)/4)),C10*INDEX('3-Pwr Plant'!S2:X10,MATCH('3-Pwr Plant'!B11,'3-Pwr Plant'!S2:S10,0),6)/4)))) -> 0.13333333 | I10: =IF(INDEX('3-Pwr Plant'!S2:Y10,MATCH('3-Pwr Plant'!B11,'3-Pwr Plant'!S2:S10,0),7)=0,"",INDEX('3-Pwr Plant'!S2:Y10,MATCH('3-Pwr Plant'!B11,'3-Pwr Plant'!S2:S10,0),7)&" Year Lifespan, Loses "&TEXT(INDEX('3-Pwr Plant'!S2:Y10,MATCH('3-Pwr Plant'!B11,'3-Pwr Plant'!S2:S10,0),2),"#,###.##")&" Power Points Per Year After") | S10: ='2-Drives'!B23 -> No Drive | T10: Yes | U10: =IF(S10="Reaction Drive",'2-Drives'!D23,0) -> 0
B11: Additional Tons of Fuel | C11: 0 | H11: =C11 -> 0 | S11: ='2-Drives'!B29 -> No FTL | T11: =IF(RIGHT(S11,3)="op)","Hops",IF(RIGHT(S11,3)="ip)","Skips","Jumps")) -> Jumps | U11: =IF(T11="Skips",100,IF(T11="Hops",10,1)) -> 1
B12: Armored Bulkheads? | C12: No | F12: =IF(H12>0,200000*H12," ") | H12: =IF(C12=T10,0.1*SUM(H13:H40,H8:H11),0) -> 0 | S12: ='2-Drives'!B37 -> No High Burn Thruster | U12: =IF(S12="High Burn Thruster",'2-Drives'!D37,0) -> 0
A13: Fuel Scoops | B13: Uninstalled | F13: =IF(B13=S3,1000000,IF(U4=S4,U5,0)) -> 0 | H13: =V5 -> 0 | S13: ='2-Drives'!B46 -> No Back Up Drive | U13: =IF(S13="Reaction Drive",'2-Drives'!D46,0) -> 0
S14: Installed
B15: Tons of Fuel Refined Per Day | C15: Tons | D15: Fuel Capacity | S15: Not installed
A16: Fuel Processor | B16: =20*C16 -> 0 | C16: 0 | D16: =SUM(H9:H11) -> 0.13333333 | F16: =50000*C16 -> 0 | H16: =C16 -> 0 | K16: =C16 -> 0
S17: Metal Hydride Fuel Tanks | T17: 2 | U17: 200000 | V17: 9
A18: Ramscoop | B18: Uninstalled | D18: Tons Per Week | F18: =H18*250000 -> 0 | H18: =IF(B18=$S$5,0,IF(0.01*Tonnage+5<10,10+C19,0.01*Tonnage+5+C19)) -> 0 | S18: Mixed: Use fields below | T18: 0 | U18: 0 | V18: 9
A19: =IF(T37=0,"","Streamlined w/ Ramscoop") | B19: Additional Tonnage: | C19: 0 | D19: =H18*5 -> 0 | S19: Standard Fuel Tanks | T19: 1 | U19: 0 | V19: =IF('3-Pwr Plant'!B11="Fission",4,IF('3-Pwr Plant'!B11="Chemical",5,IF('3-Pwr Plant'!B11="Fusion TL 08",6,7))) -> 7
A21: >>> See Cargo Tab for additional information. | D21: Error | S21: Streamlined | T21: =IF('1-Hull'!B8="Streamlined",1,0) -> 0
A22: Collapsible Fuel Tank | B22: ="(Requires Cargo Bay, No Piping to Jump Drive) Cargo: "&TEXT(SUM('12-Cargo'!D18,'12-Cargo'!D22,'12-Cargo'!D26),"#,###") -> (Requires Cargo Bay, No Piping to Jump Drive) Cargo: | C22: Tons | D22: =IF(T30=0,"",S30)&IF(T34=0,""," /"&S34&"/") | S22: Adjustable Hull | T22: =IF('1-Hull'!A20="None",0,1) -> 0
A23: Not installed | B23: Bladder size when full: | C23: 0 | D23: =IF(T31=0,"","//"&S31&"//") | F23: =C23*500 -> 0 | S23: Page Tonnage | U23: Main Fuel Tanks
S24: =SUM(H7:H47) -> 0.13333333 | U24: =SUM(H8:H11) -> 0.13333333
A25: Mountable Fuel Tank | B25: ="(Requires Cargo Bay, Direct Feed to Jump Drives) Cargo: "&TEXT(SUM('12-Cargo'!D18,'12-Cargo'!D22,'12-Cargo'!D26),"#,###") -> (Requires Cargo Bay, Direct Feed to Jump Drives) Cargo: | C25: Tons | D25: =IF(T32=0,"",S32)&IF(T34=0,""," /"&S34&"/")
A26: Not installed | B26: Tank Size: | C26: 0 | D26: =IF(T33=0,"","//"&S33&"//") | F26: =C26*1000 -> 0 | S26: Page Power
S27: =SUM(K16,K32,K47) -> 0
A28: Fuel/Cargo Container | B28: Quantity of Bays | C28: Tons Per Bay
B29: 0 | C29: 0 | F29: =B29*H29*5000 -> 0 | H29: =(B29*C29*1.05)-IF(C30=T9,0,IF(B29*C29>D16,D16,B29*C29)) -> 0 | S29: Error | T29: =SUM(T30:T41) -> 0 | U29: =SUM(U30:U34) -> 0
B30: Convert Main Tanks to Fuel/Cargo? | C30: No | S30: CFT not installed | T30: =IF(AND(A23=S15,C23>0),1,0) -> 0
B31: Cargo Crane | C31: No | F31: =1000000*H31 -> 0 | H31: =IF(C31=S48,0,(2.5+0.5*ROUNDUP((C29/150),0))*B29) -> 0 | S31: CFT > Cargo | T31: =IF(C23>SUM('12-Cargo'!D18,'12-Cargo'!D22,'12-Cargo'!D26),1,0) -> 0 | U31: =T31 -> 0
B32: Loading Belts | C32: No | E32: =INDEX(S44:U46,MATCH(C32,S44:S46,0),2) -> 0 | F32: =INDEX(S44:U46,MATCH(C32,S44:S46,0),3)*B29 -> 0 | H32: =IF(C32=S44,0,B29) -> 0 | K32: =IF(C32=S44,0,B29) -> 0 | S32: DMT not installed | T32: =IF(AND(A26=S15,C26>0),1,0) -> 0
S33: DFT > Cargo | T33: =IF(C26>SUM('12-Cargo'!D18,'12-Cargo'!D22,'12-Cargo'!D26),1,0) -> 0 | U33: =T33 -> 0
S34: CFT+DFT>Cargo | T34: =IF(C23+C26>SUM('12-Cargo'!D18,'12-Cargo'!D22,'12-Cargo'!D26),1,0) -> 0 | U34: =T34 -> 0
A35: Drop Tank Mounts | C35: Tons | S35: Mixed Tank Input> Fuel | T35: =IF(C39>SUM(H8:H11),1,0) -> 0
A36: Not installed | B36: Attached Drop Tank Capacity: | C36: 0 | F36: =C36*0.004*500000 -> 0 | H36: =C36*0.004 -> 0 | S36: No Fuel | T36: =IF(AND(AND(INDEX('3-Pwr Plant'!S2:X10,MATCH('3-Pwr Plant'!B11,'3-Pwr Plant'!S2:S10,0),6)>0,H10=0),L6>0),1,0) -> 0
S37: Streamlined Ramscoop | T37: =IF(B18=S5,0,IF(T21=0,0,IF(SUM(T21:T22)=2,0,1))) -> 0
C38: Tons | S38: FuelScoop Stream,NoScoop | T38: =IF(T21=0,0,IF(AND(T21=1,OR(U4=S2,U4=S4)),0,1)) -> 0
B39: Standard Fuel Tanks | C39: 0 | D39: =IF(T35=0,"","//"&S35&"//") | S39: FuelscoopUnstreamFreeScoop | T39: =IF(T21=1,0,IF(AND(T21=0,U4=S2),1,0)) -> 0
B40: Metal Hydride Fuel Tanks | C40: 0 | F40: =200000*H40 -> 0 | H40: =C40 -> 0 | S40: Fuel Overfow | T40: =U56 -> 0
A42: Note: | B42: Metal hydride storage: If the ship sustains a fuel leak, fuel loss will be | S42: =SUM(H8:H11)&" tons"&", "&C10&" Weeks"&IF(B9=0,"",", "&B9&" ")&T11&IF(B8=0,"",", "&B8&" "&A8)&IF(B7=S17,", "&S17,IF(B7=S18,", "&C39&"/"&C40&" tons Standard/Metal Hydride Tanks",""))&IF(C12=T9,"",", Armored")&IF(C16=0,"",", "&C16&" tons "&A16)&IF(A23=S15,"",", "&C23&" tons "&A22)&IF(A26=S15,"",", "&C26&" tons "&A25)&IF(A36=S15,"",", "&C36&" tons "&A35)&IF(F29>0,", "&B29&" x "&C29&" Tons "&A28,"") -> 0.133333333333333 tons, 4 WeeksJumps
B43: reduced to 25% of the amount indicated, to a minimum of 1 ton. | S43: Fuel/Cargo options
S44: No | T44: 0 | U44: 0
B45: User Defined Fuel Storage | S45: =IF(H29>0,"Standard","No") -> No | T45: 7 | U45: 3000
A46: Description | C46: Tons | D46: Source | S46: =IF(H29>0,"Advanced","No") -> No | T46: 12 | U46: 10000
C47: 0 | D47: Hull | F47: =IF(D47=S53,C51+(C47*B51),0) -> 0 | H47: =IF(D47=S53,C49+(C47*B49),0) -> 0 | K47: =D49+(D51*C47) -> 0
B48: Tons Per Ton of Fuel + | C48: Flat Ton Usage | D48: Power | S48: No
B49: 1 | C49: 0 | D49: 0 | S49: =IF(H29>0,"Yes","No") -> No
B50: Cost Per Ton of Fuel + | C50: Flat Cost | D50: Power/Ton
B51: 0 | C51: 0 | D51: 0
B52: Internal Cargo Available: | C52: =SUM('12-Cargo'!H18,'12-Cargo'!H22,'12-Cargo'!H26,'12-Cargo'!H32) -> 0 | D52: Bays/Internal | S52: Source
B53: External Cargo Available: | C53: =SUM('12-Cargo'!D11:D13) -> 0 | D53: Nets/Racks | S53: Hull | T53: =Tonnage -> 100 | U53: =IF(AND($D$47=S53,$C$47>T53),1,0) -> 0
S54: Internal Cargo Bays | T54: =C52 -> 0 | U54: =IF(AND($D$47=S54,$C$47>T54),1,0) -> 0
A55: ="-This section allows you to make a custom/non-standard Fuel Storage system, or to introduce" -> -This section allows you to make a custom/non-standard Fuel Storage system, or to introduce | S55: External Cargo | T55: =C53 -> 0 | U55: =IF(AND($D$47=S55,$C$47>T55),1,0) -> 0
A56: new technologies prior to implementaion in this sheet. | U56: =SUM(U53:U55) -> 0
A57: ="-Cost/Usage per ton of fuel is added to flat cost/use. This is for a set connector size/cost" -> -Cost/Usage per ton of fuel is added to flat cost/use. This is for a set connector size/cost
A58: and a per unit size/cost.

Sheet 5-Bridge
A1: ='Ship Info'!A1 -> Ship's Class Name | B1: ='Ship Info'!B1 -> 0 | F1: Cost | S1: Bridge | T1: Tonnage | U1: Cost | V1: Size | AH1: EDGE>>
A2: Class Role | B2: ='Ship Info'!B2 -> 0 | D2: Tech Level: | E2: =Tech_Level -> 12 | F2: ='Ship Info'!G2 -> 6177000 | S2: =IF('Ship Info'!E6<>"Ship","No Bridge",IF('10-Crew'!J36>='5-Bridge'!T22,"Drone Ship","No Bridge")) -> No Bridge | T2: 0 | U2: 0 | W2: =IF('Ship Info'!E6<>"Ship","No Bridge",IF('10-Crew'!J36>='5-Bridge'!T22,"Drone Ship","No Bridge")) -> No Bridge
H3: =S20 -> 6 | S3: =IF('Ship Info'!F6,"Command Center (Mil)","") | T3: =IF('Ship Info'!F5,0,T4) -> 0 | U3: =200000*ROUNDUP(Tonnage/100,0) -> 200000 | W3: =IF('Ship Info'!F6,"DM+1 to all Tactics (naval) checks","Error, Wrong selection for type") -> Error, Wrong selection for type
A4: Tonnage | B4: ='1-Hull'!B4 -> 100 | F4: Page Total | H4: Available Space | K4: Required Power | S4: =IF('Ship Info'!F6,"Control Center","") | T4: =IF('Ship Info'!F5,0,IF(Tonnage>2500000,100,IF(Tonnage>100000,80,IF(Tonnage>20000,60,IF(Tonnage>5000,40,IF(Tonnage>500,20,10)))))) -> 0 | U4: =100000*ROUNDUP(Tonnage/100,0) -> 100000 | W4: =IF('Ship Info'!F6,"No Modifiers","Error, Wrong selection for type") -> Error, Wrong selection for type
F5: =SUM(F9:F30) -> 500000 | H5: Unused | I5: Max | K5: Unused | L5: Max | S5: =IF('Ship Info'!F5,"Cockpit","") -> Cockpit | T5: =IF('Ship Info'!F6,0,1.5) -> 1.5 | U5: 10000 | W5: =IF('Ship Info'!F5,"24 hours of Life Support","Error, Wrong selection for type") -> 24 hours of Life Support | AA5: None
A6: ="This ship requires "&T22-'10-Crew'!J36&" additional Virtual Crew to be a Drone Ship" -> This ship requires 2 additional Virtual Crew to be a Drone Ship | H6: ='Ship Info'!I3 -> 92.53 | I6: ='1-Hull'!I6 -> 100 | K6: ='Ship Info'!L3 -> 0 | L6: ='3-Pwr Plant'!L6 -> 20 | S6: =IF('Ship Info'!F5,"Command Bridge","") -> Command Bridge | T6: =IF('Ship Info'!F6,0,T10+40) -> 46 | U6: =U33 -> 30500000 | W6: =IF('Ship Info'!F5,"DM+1 to all Tactics (naval) checks","Error, Wrong selection for type") -> DM+1 to all Tactics (naval) checks | AA6: Command Bridge | AC6: =OR(A9=S6,A13=AA6) -> FALSE
H7: Item Tons | S7: =IF('Ship Info'!F5,"Detachable Bridge","") -> Detachable Bridge | T7: =IF('Ship Info'!F6,0,T10*1.2) -> 7.2 | U7: =1.5*U10 -> 750000 | V7: =IF(B4<51,1,IF(B4<V15,2,IF(B4<201,3,IF(B4<1001,4,IF(B4<2001,5,IF(B4<100001,6,7)))))) -> 2 | W7: =IF('Ship Info'!F5,"Lifeboat with two weeks of life support and Thrust 0)","Error, Wrong selection for type") -> Lifeboat with two weeks of life support and Thrust 0)
A8: Main Bridge | B8: Use Core24 Bridge Rule | E8: TL | S8: =IF('Ship Info'!F5,"Dual Cockpit","") -> Dual Cockpit | T8: =IF('Ship Info'!F6,0,2.5) -> 2.5 | U8: 15000 | W8: =IF('Ship Info'!F5,"24 hours of Life Support","Error, Wrong selection for type") -> 24 hours of Life Support | Z8: =OR(A9=S5,A9=S8) -> FALSE | AA8: 0 | AB8: 1 | AC8: 2 | AD8: 3 | AE8: 4 | AF8: 5 | AG8: 6 | AH8: 7
A9: Standard Bridge | B9: =IFERROR(INDEX(S2:W12,MATCH(A9,S2:S12,0),5),"Wrong selection for type") -> No Modifiers | F9: =IFERROR(INDEX(S2:W12,MATCH(A9,S2:S12,0),3),0) -> 500000 | H9: =IFERROR(INDEX(S2:W12,MATCH(A9,S2:S12,0),2),IF('Ship Info'!F7,1,0)) -> 6 | S9: =IF('Ship Info'!F5,"Small Bridge","") -> Small Bridge | T9: =IF('Ship Info'!F6,0,HLOOKUP(V9,AA8:AH9,2)) -> 3 | U9: =ROUNDUP(B4/100,0)*250000 -> 250000 | V9: =V10-1 -> 1 | W9: =IF('Ship Info'!F5,"DM-1 for all Ship's Ops checks from Bridge","Error, Wrong selection for type") -> DM-1 for all Ship's Ops checks from Bridge | AA9: 3 | AB9: 3 | AC9: 6 | AD9: 10 | AE9: 20 | AF9: 40 | AG9: 60 | AH9: =40+(20*ROUNDUP(Tonnage/100000,0)) -> 60
A10: Standard Controls | B10: =INDEX(S16:W17,MATCH(A10,S16:S17,0),5) -> No Modifiers | E10: =INDEX(S16:W17,MATCH(A10,S16:S17,0),2) -> 7 | F10: =INDEX(S16:W17,MATCH(A10,S16:S17,0),3) -> 0 | S10: =IF('Ship Info'!F5,"Standard Bridge","") -> Standard Bridge | T10: =IF('Ship Info'!F6,0,HLOOKUP(V10,AB8:AH9,2)) -> 6 | U10: =ROUNDUP(B4/100,0)*500000 -> 500000 | V10: =IF(B4<51,1,IF(B4<V15,2,IF(B4<201,3,IF(B4<1001,4,IF(B4<2001,5,IF(B4<100001,6,7)))))) -> 2 | W10: =IF('Ship Info'!F5,"No Modifiers","Error Wrong selection for type") -> No Modifiers | Y10: =AND(OR(A9=S7,A9=S10),A13=AA5) -> TRUE
S11: Ship-Heart Chamber | T11: =30+0.01*Tonnage -> 31 | U11: =ROUNDUP(Tonnage/100,0)*1000000 -> 1000000 | W11: Droyne Bridge
A12: Add Command Bridge Status to an Existing Bridge | C12: Quantity | S12: Ship-Heart Citadel | T12: =40+0.01*Tonnage -> 41 | U12: =ROUNDUP(Tonnage/100,0)*1250000 -> 1250000 | W12: Droyne Bridge - Armored
A13: None | B13: =IF(A13=AA6,W6," ") | C13: 0 | F13: =C13*IF(B4<5000,0,IF(A13=AA6,30000000,0)) -> 0 | H13: =C13*IF(B4<5000,0,IF(A13=AA6,40,0)) -> 0
A14: Standard Controls | B14: =INDEX(S16:W17,MATCH(A14,S16:S17,0),5) -> No Modifiers | C14: ="Max = "&C17+1 -> Max = 1 | E14: =INDEX(S16:Y17,MATCH(A14,S16:S17,0),2) -> 7 | F14: =IF(A13=AA5,0,INDEX(S16:Y17,MATCH(A14,S16:S17,0),7))*C13 -> 0 | S14: =IFERROR(INDEX(S2:S12,MATCH(A9,S2:S12,0),1),1) -> Standard Bridge
U15: Rule Selection: | V15: =IF(B8="Use Core24 Bridge Rule",101,100) -> 101
A16: Auxilliary Control Room | C16: Quantity | S16: Holographic Controls | T16: 9 | U16: =0.25*F9 -> 125000 | W16: DM+2 to Initiative | Y16: =0.25*F13 -> 0 | Z16: =0.25*F17 -> 0
A17: N/A | B17: =INDEX(S32:W36,MATCH(A17,S32:S36,0),5) -> No Aux Con | C17: 0 | F17: =INDEX(S32:X38,MATCH(A17,S32:S38,0),3)*C17 -> 0 | H17: =INDEX(S32:T36,MATCH(A17,S32:S36,0),2)*C17 -> 0 | S17: Standard Controls | T17: 7 | U17: 0 | W17: No Modifiers
A18: Standard Controls | B18: =INDEX(S16:W17,MATCH(A18,S16:S17,0),5) -> No Modifiers | E18: =INDEX(S16:Y17,MATCH(A18,S16:S17,0),2) -> 7 | F18: =IF(A17=S32,0,INDEX(S16:Z17,MATCH(A18,S16:S17,0),8))*C17 -> 0
C19: Module Control Rooms must be SCC's | S19: Page Tonnage
B20: Number of Aux Con's set up as Specialist Command Centers: | C20: 0 | S20: =SUM(H9:H22) -> 6
B21: (Denote the specializations of SCC's in Notes)
B22: Armored Bulkheads: | C22: No | F22: =200000*H22 -> 0 | H22: =IF(C22="No",0,0.1*SUM(H8:H19)) -> 0 | S22: Bridge Crew: | T22: ='10-Crew'!F11-'10-Crew'!H11-'10-Crew'!K11+'10-Crew'!F12-'10-Crew'!K12+'10-Crew'!F17-'10-Crew'!K17 -> 2
A24: No Robot Brain Interface | F24: =IF(A24=S50,0,IF(A24=S51,Tonnage*5000,Tonnage*7000)) -> 0
S25: =IF(A9=S9,"Small ","")&"Bridge: "&IF(A10=S16,"Initiative+2",IF(Y10=TRUE,W10,""))&""&IF(AC6=TRUE," Tactics+1","")&""&IF(A9=S9,"DM -1 All Bridge Checks","")&""&IF(Z8=TRUE,"Cockpit","") -> Bridge: No Modifiers
A26: Robot Handbook Robot Brain
B27: =INDEX(S53:V56,MATCH(A27,S53:S56,0),4) | E27: =INDEX(S53:V56,MATCH(A27,S53:S56,0),2) -> 0 | F27: =INDEX(S53:V56,MATCH(A27,S53:S56,0),3) -> 0
S28: No
A29: Custom Robot Brain | B29: Notes | S29: Yes
S31: Bridge | T31: Tonnage | U31: Cost | V31: Size
S32: N/A | T32: 0 | U32: 0 | V32: 0 | W32: No Aux Con
S33: Command Bridge | T33: =T6 -> 46 | U33: =U36+30000000 -> 30500000 | W33: DM+1 to all Tactics (naval) checks
S34: Detachable Bridge | T34: =T36*1.2 -> 12 | U34: =1.5*U36 -> 750000 | V34: =IF(B4<51,1,IF(B4<100,2,IF(B4<201,3,IF(B4<1001,4,IF(B4<2001,5,IF(B4<100001,6,7)))))) -> 3 | W34: Lifeboat with two weeks of life support and Thrust 0
S35: Small Bridge | T35: =HLOOKUP(V35,AA8:AH9,2) -> 6 | U35: =ROUNDUP(B4/100,0)*250000 -> 250000 | V35: =V36-1 -> 2 | W35: DM-1 for all Ship's Ops checks from Bridge
S36: Standard Bridge | T36: =HLOOKUP(V36,AB8:AH9,2) -> 10 | U36: =ROUNDUP(B4/100,0)*500000 -> 500000 | V36: =IF(B4<51,1,IF(B4<100,2,IF(B4<201,3,IF(B4<1001,4,IF(B4<2001,5,IF(B4<100001,6,7)))))) -> 3 | W36: No Modifiers
S37: Ship-Heart Chamber | T37: =30+0.01*Tonnage -> 31 | U37: =ROUNDUP(Tonnage/100,0)*1000000 -> 1000000 | W37: Droyne Bridge
S38: Ship-Heart Citadel | T38: =40+0.01*Tonnage -> 41 | U38: =ROUNDUP(Tonnage/100,0)*1250000 -> 1250000 | W38: Droyne Bridge - Armored
S40: Errors | T40: =IFERROR(SUM(T41:T48),1) -> 0
S41: CMD 1 | T41: =IF(AND(B4<5000,A9=S6),1,0) -> 0
S42: CMD 2 | T42: =IF(AND(B4<5000,A13=AA6),1,0) -> 0
S43: CMD 3 | T43: =IF(AND(B4<5000,A17=S33),1,0) -> 0
S44: Cockpit 1 | T44: =IF(OR(AND(B4>99,A9=S5),AND(B4>99,A9=S8)),1,0) -> 0
S45: Small Small Bridge | T45: =IFERROR(IF(AND(H9=0,'Ship Info'!F7),0,IF(AND(,S2="No Bridge",H9=0),1,0)),1) -> 0
S46: Module w/ Bridge | T46: =IF(AND(H17=S20,C17=C20),0,IFERROR(IF(AND(S20>0,'Ship Info'!F7),1,0),1)) -> 0
S47: Checksum | T47: =IF(S14=A9,0,1) -> 0
S48: TL | T48: =IF(OR(E27>TL,E30>TL),1,0) -> 0
S50: No Robot Brain Interface
S51: Robot Brain Interfaces Installed
S52: Haptic Robot Brain Interfaces Installed
S53: ="" | V53: =""
S54: Alpha | T54: 10 | U54: =IF(TL>11,40000,IF(TL>10,80000,130000)) -> 40000 | V54: No avatars, max 4 tasks, DM-2 on each additional task
S55: Brian | T55: 12 | U55: 1000000 | V55: Basic Avatar, Max 8 tasks, DM-1 on each additional task
S56: Omega | T56: 12 | U56: 10000000 | V56: 4 Avatars, 8 Drones, Advanced Swarm
S59: =IF(A27="",0,A27) -> 0 | T59: A25 | U59: =IF(S59=0,"",S59)
S60: =A30 -> 0 | T60: A28 | U60: =IF(S60=0,"",S60) | AH60: EDGE>>
S61: =IF(AND(S59=0,S60=0),"",IF(OR(S59=0,S60=0),U59&U60,U59&"/"&U60))

Sheet 6-Comp
A1: ='Ship Info'!A1 -> Ship's Class Name | B1: ='Ship Info'!B1 -> 0 | F1: Cost | S1: ="" | T1: 0 | U1: 0 | V1: 0 | AF1: Edge>>>
A2: Class Role | B2: ='Ship Info'!B2 -> 0 | C2: Tech Level: | D2: ='Ship Info'!F2 -> 12 | F2: ='Ship Info'!G2 -> 6177000 | S2: Comp/ 5 | T2: 7 | U2: 30000 | V2: 5
S3: Comp/10 | T3: 9 | U3: 160000 | V3: 10
A4: Tonnage | B4: ='1-Hull'!B4 -> 100 | F4: Page Total | S4: Comp/15 | T4: 11 | U4: 2000000 | V4: 15 | X4: SSD | AC4: Cost mod | AD4: TL mod
B5: Optional Rule | F5: =IF(AND(C7="No",'Ship Info'!F7),0,SUM(F9:F44,F48:F67)) -> 30000 | I5: Optional Rule | S5: Comp/20 | T5: 12 | U5: 5000000 | V5: 20 | X5: F/C | Y5: =IF(B21=S25,IF(B24=S36,"N/A",INDEX(S36:T41,MATCH(B24,S36:S41,0),2)),INDEX(S25:T28,MATCH(B21,S25:S28,0),2)) -> N/A | AB5: Early Prototype* | AC5: 10 | AD5: -2 | AE5: 10 | AF5: -2
B6: Allow both Main and B/U to run programs at the same time? | C6: No | I6: Use CSC tie in for proto/retro Computers? | L6: Standard | S6: Comp/25 | T6: 13 | U6: 10000000 | V6: 25 | X6: Missile | Y6: =INDEX(S75:T78,MATCH(B33,S75:S78,0),2) -> N/A | AB6: Prototype* | AC6: 5 | AD6: -1 | AE6: 5 | AF6: -1
B7: Allow Modules to have a separate Computer? | C7: Yes | S7: Comp/30 | T7: 14 | U7: 20000000 | V7: 30 | X7: BatSys | Y7: =INDEX(S45:T48,MATCH(B26,S45:S48,0),2) -> N/A | AB7: Standard | AC7: 1 | AD7: 0 | AE7: 1 | AF7: 0
A8: Computer | S8: Comp/35 | T8: 15 | U8: 30000000 | V8: 35 | X8: Evade | Y8: =INDEX(S59:T62,MATCH(B30,S59:S62,0),2) -> N/A | AB8: Retro* | AC8: =1*(1/(2^(AD8))) -> 0.03125 | AD8: =D2-INDEX(S1:T17,MATCH(B9,S1:S17,0),2) -> 5 | AE8: =1*(1/(2^(AF8))) -> 1 | AF8: =IF(INDEX(S1:T17,MATCH(B13,S1:S17,0),2)=0,0,D2-INDEX(S1:T17,MATCH(B13,S1:S17,0),2)) -> 0
